Workbook
Name \0: #REF!
Name \0: !#REF!
Name \00: #REF!
Name \1: #REF!
Name \44333: #REF!
Name \a: #N/A
Name \add9a: #REF!
Name \b: #REF!
Name \b: !#REF!
Name \c: #REF!
Name \c: !#REF!
Name \Convergence: 1.79769313486231E+59
Name \d: #REF!
Name \d: !#REF!
Name \D2: #N/A
Name \DA: #N/A
Name \DA2: #N/A
Name \e: #N/A
Name \f: #REF!
Name \f: !#REF!
Name \g: #REF!
Name \g: !#REF!
Name \GA: #N/A
Name \h: #REF!
Name \h: !#REF!
Name \i: #REF!
Name \i: !#REF!
Name \IA: #N/A
Name \IterationCount: 0
Name \j: #REF!
Name \JA: #N/A
Name \K: #REF!
Name \K: !#REF!
Name \L: #REF!
Name \L: !#REF!
Name \L0: #N/A
Name \L1: #N/A
Name \L11: #N/A
Name \L2: #N/A
Name \m: #REF!
Name \m: !#REF!
Name \MACROS: #REF!
Name \MENU: #REF!
Name \n: #REF!
Name \n: !#REF!
Name \ñ: #REF!
Name \ñ: !#REF!
Name \O: #REF!
Name \P: #REF!
Name \P: !#REF!
Name \PRECIOS: #REF!
Name \PRECIOS: !#REF!
Name \q: #REF!
Name \q: !#REF!
Name \r: #N/A
Name \s: #REF!
Name \s: !#REF!
Name \SA: #N/A
Name \SALVAR: #N/A
Name \t: #REF!

Sheet CARÁTULA de QPS
M1: SUPERINTENDENCIA DE INGENIERÍA | AJ1: CÓDIGO: PCS-IN-FO-019 Ver. 01 / 22-May-2022
B3: PROYECTOS DE CAPITAL SOSTENIBLE
M4: CANTIDADES Y PRECIOS OFERTADOS (QPS) | AJ4: CÓDIGO DE DOC.:
AJ5: =P13&"_"&D51 -> CRD-QPS-11760-G-33-4001_C
C7: =+"WBS Nº: "&AX7 -> WBS Nº: 1760 | AX7: 1760 | AY7: .
C10: AÑO: 2025
C13: QPS Nº: | P13: CRD-QPS-11760-G-33-4001
C16: CANTIDADES Y PRECIOS OFERTADOS (QPS)
B23: SISTEMA DE DOSIFICACIÓN DE FLOCULANTE AWTP - PL
C28: DISCIPLINA: GENERAL
C31: Preparado por:
C32: GRUPO CREDCO S.A.C.
C35: Aprobado por:
C37: Ingeniero Líder | U37: : | V37: Raul Gilio
C38: Gerente de Proyecto - CREDCO | U38: : | V38: Victor Soto
C39: Gerente de Proyecto - MYSRL | U39: : | V39: Victor Castillo
C41: Rev. | F41: Elaborado | L41: Emitido para | AB41: Fecha | AG41: Revisado | AM41: Aprobado
C42: A | F42: C.M./G.C./F.D./A.B. | L42: Emitido para revisión interna | AB42: 45869 | AG42: M.T. | AM42: V.S.
C43: B | F43: C.M./G.C./F.D./A.B. | L43: Emitido para revisión del cliente | AB43: 45870 | AG43: M.T. | AM43: V.S.
C44: C | F44: C.M./G.C./F.D./A.B. | L44: Emitido para revisión del cliente | AB44: 45889 | AG44: M.T. | AM44: V.S.
C46: Comentarios:
D51: C

Sheet CARATULA CPQ - COLUMBITO

Sheet QPS
B1: PROYECTOS DE CAPITAL SOSTENIBLE | G1: SUPERINTENDENCIA DE INGENIERÍA | S1: Código: PCS-IN-FO-008 Vers 01 / 23-May-2022 | X1: =TEXT(C16,"0.0000") -> 1.0101
X2: =IF(ISNUMBER(C16),TEXT(C16,"0.0000"),C16) -> 1.0101
X3: =SUBSTITUTE(TEXT(C16,"0.0000"),".","") -> 10101
G4: CANTIDADES Y PRECIOS OFERTADOS (QPS) | S4: =+"CÓDIGO DE DOC. CRD-QPS-11760-G-33-4001_"&'CARÁTULA de QPS'!D51 -> CÓDIGO DE DOC. CRD-QPS-11760-G-33-4001_C | X4: =TEXT(C15,"0.0000") -> 1.0100
B5: ÁREA: | E5: PAMPA LARGA | T5: QPS No. : | U5: =+'CARÁTULA de QPS'!P13 -> CRD-QPS-11760-G-33-4001 | X5: =TEXT(C38,"0.0000") -> 2.0410
B6: CÓDIGO DE FACILIDAD: | E6: - | T6: REV. : | U6: =+'CARÁTULA de QPS'!D51 -> C | X6: =REPLACE(TEXT(C16,"0.0000"),5,0,".") -> 1.01.01
B7: WBS No.: | E7: 1760 | T7: FECHA: | U7: =+'CARÁTULA de QPS'!AB44 -> 45889 | X7: =SUMIFS(APU!O:O,APU!A:A,REPLACE(TEXT(C16,"0.0000"),5,0,"."),APU!G:G,"hh") -> 200
B8: FCR No.: | E8: - | T8: ELABORADO POR: | U8: =+'CARÁTULA de QPS'!F42 -> C.M./G.C./F.D./A.B. | X8: =SUMIFS(APU!O:O,APU!A:A,C120,APU!G:G,"hh") -> 32.16
B9: SOW No.: | E9: CRD-SOW-11760-G-33-4001
B11: Artículo de Pago | C11: Ítem | D11: CÓDIGO DE COSTO | G11: Descripción de la Actividad | N11: Tamaño | O11: Clase | Q11: Estado alcance | R11: Especialidad | S11: Cantidad | U11: Precio | AK11: Rótulos suministro (auxiliar) | AM11: Mapeo especialidad (auxiliar)
D12: Código de Área | E12: Código de Sub Área | F12: Código de Actividad | T12: Unidad | U12: Unitario | V12: Oferta Total | AK12: Suministro MY | AM12: GENERAL | AN12: Civil
T13: Básica | U13: Ofertado | W13: hh | AB13: hh | AC13: Rendimiento /DIA | AD13: Duración (días) | AE13: Cód. norm. | AG13: % Avance | AH13: HH ganadas | AI13: Clave única | AK13: Suministro Contratista | AM13: CIVIL | AN13: Civil
B14: GENERAL | AM14: MECÁNICA - TUBERIAS | AN14: Mecanica
B15: 8.1 | C15: 1.01 | D15: - | E15: - | F15: - | G15: TRABAJOS PRELIMINARES | N15: - | O15: - | P15: =IF(TRIM($G15)="","",TRIM($G15)&IF(OR(TRIM($N15)="",TRIM($N15)="-"),""," - "&TRIM($N15))&IF(OR(TRIM($O15)="",TRIM($O15)="-"),""," - "&TRIM($O15))&IF(ISNUMBER(SEARCH("SUMINISTRO",$G15))," - "&$AK$13,IF(ISNUMBER(SEARCH("MONTAJE",$G15))," - "&$AK$12,""))) -> TRABAJOS PRELIMINARES | Q15: En alcance | R15: {=IF($G15="","",IFERROR(VLOOKUP(LOOKUP(2,1/(($B$14:$B15<>"")*($C$14:$C15="")),$B$14:$B15),$AM$12:$AN$16,2,FALSE),""))} -> Civil | AB15: {=IF($S15="","",SUMIFS(APU!$O:$O,APU!$A:$A,IF(ISNUMBER($C15),REPLACE(TEXT($C15,"0.0000"),5,0,"."),$C15),APU!$G:$G,"hh")/MAX(1,SUMPRODUCT(($C$15:$C$262=$C15)*($S$15:$S$262<>""))))} | AC15: =IF($S15="","",IFERROR(VLOOKUP($AE15,APU!$V:$X,2,FALSE),"")) | AD15: =IF(OR($S15="",$AC15="",N($AC15)=0),"",$S15/$AC15) | AE15: =IF($C15="","",IF(ISNUMBER($C15),REPLACE(TEXT($C15,"0.0000"),5,0,"."),$C15)) -> 1.01.00 | AH15: =IF($S15="","",$AB15*N($AG15)) | AI15: =IF($S15="","",$AE15&IF(TRIM($N15)="",""," | "&TRIM($N15))&IF(OR(TRIM($O15)="",TRIM($O15)="-"),""," | "&TRIM($O15))) | AM15: ELECTRICIDAD | AN15: Electrica
B16: 8.1.1 | C16: =+C15+0.0001 -> 1.0101 | D16: - | E16: - | F16: - | G16: Movilización y desmovilización | N16: - | O16: - | P16: =IF(TRIM($G16)="","",TRIM($G16)&IF(OR(TRIM($N16)="",TRIM($N16)="-"),""," - "&TRIM($N16))&IF(OR(TRIM($O16)="",TRIM($O16)="-"),""," - "&TRIM($O16))&IF(ISNUMBER(SEARCH("SUMINISTRO",$G16))," - "&$AK$13,IF(ISNUMBER(SEARCH("MONTAJE",$G16))," - "&$AK$12,""))) -> Movilización y desmovilización | Q16: En alcance | R16: {=IF($G16="","",IFERROR(VLOOKUP(LOOKUP(2,1/(($B$14:$B16<>"")*($C$14:$C16="")),$B$14:$B16),$AM$12:$AN$16,2,FALSE),""))} -> Civil | S16: 1 | T16: Glb. | U16: =APU!K3 -> 6797.26 | V16: =U16*S16 -> 6797.26 | AB16: {=IF($S16="","",SUMIFS(APU!$O:$O,APU!$A:$A,IF(ISNUMBER($C16),REPLACE(TEXT($C16,"0.0000"),5,0,"."),$C16),APU!$G:$G,"hh")/MAX(1,SUMPRODUCT(($C$15:$C$262=$C16)*($S$15:$S$262<>""))))} -> 200 | AC16: =IF($S16="","",IFERROR(VLOOKUP($AE16,APU!$V:$X,2,FALSE),"")) -> 0.2 | AD16: =IF(OR($S16="",$AC16="",N($AC16)=0),"",$S16/$AC16) -> 5 | AE16: =IF($C16="","",IF(ISNUMBER($C16),REPLACE(TEXT($C16,"0.0000"),5,0,"."),$C16)) -> 1.01.01 | AH16: =IF($S16="","",$AB16*N($AG16)) -> 0 | AI16: =IF($S16="","",$AE16&IF(TRIM($N16)="",""," | "&TRIM($N16))&IF(OR(TRIM($O16)="",TRIM($O16)="-"),""," | "&TRIM($O16))) -> 1.01.01 | - | AM16: INSTRUMENTACIÓN | AN16: Electrica
B17: 8.1.2 | C17: =+C16+0.0001 -> 1.0102 | D17: - | E17: - | F17: - | G17: Trazo y replanteo (preliminar y durante la obra) | N17: - | O17: - | P17: =IF(TRIM($G17)="","",TRIM($G17)&IF(OR(TRIM($N17)="",TRIM($N17)="-"),""," - "&TRIM($N17))&IF(OR(TRIM($O17)="",TRIM($O17)="-"),""," - "&TRIM($O17))&IF(ISNUMBER(SEARCH("SUMINISTRO",$G17))," - "&$AK$13,IF(ISNUMBER(SEARCH("MONTAJE",$G17))," - "&$AK$12,""))) -> Trazo y replanteo (preliminar y durante la obra) | Q17: En alcance | R17: {=IF($G17="","",IFERROR(VLOOKUP(LOOKUP(2,1/(($B$14:$B17<>"")*($C$14:$C17="")),$B$14:$B17),$AM$12:$AN$16,2,FALSE),""))} -> Civil | S17: 1 | T17: Glb. | U17: =APU!K16 -> 518.25029 | V17: =U17*S17 -> 518.25029 | AB17: {=IF($S17="","",SUMIFS(APU!$O:$O,APU!$A:$A,IF(ISNUMBER($C17),REPLACE(TEXT($C17,"0.0000"),5,0,"."),$C17),APU!$G:$G,"hh")/MAX(1,SUMPRODUCT(($C$15:$C$262=$C17)*($S$15:$S$262<>""))))} -> 48 | AC17: =IF($S17="","",IFERROR(VLOOKUP($AE17,APU!$V:$X,2,FALSE),"")) -> 0.5 | AD17: =IF(OR($S17="",$AC17="",N($AC17)=0),"",$S17/$AC17) -> 2 | AE17: =IF($C17="","",IF(ISNUMBER($C17),REPLACE(TEXT($C17,"0.0000"),5,0,"."),$C17)) -> 1.01.02 | AH17: =IF($S17="","",$AB17*N($AG17)) -> 0 | AI17: =IF($S17="","",$AE17&IF(TRIM($N17)="",""," | "&TRIM($N17))&IF(OR(TRIM($O17)="",TRIM($O17)="-"),""," | "&TRIM($O17))) -> 1.01.02 | -
B18: 8.1.3 | C18: =+C17+0.0001 -> 1.0103 | D18: - | E18: - | F18: - | G18: Limpieza del área de trabajo | N18: - | O18: - | P18: =IF(TRIM($G18)="","",TRIM($G18)&IF(OR(TRIM($N18)="",TRIM($N18)="-"),""," - "&TRIM($N18))&IF(OR(TRIM($O18)="",TRIM($O18)="-"),""," - "&TRIM($O18))&IF(ISNUMBER(SEARCH("SUMINISTRO",$G18))," - "&$AK$13,IF(ISNUMBER(SEARCH("MONTAJE",$G18))," - "&$AK$12,""))) -> Limpieza del área de trabajo | Q18: En alcance | R18: {=IF($G18="","",IFERROR(VLOOKUP(LOOKUP(2,1/(($B$14:$B18<>"")*($C$14:$C18="")),$B$14:$B18),$AM$12:$AN$16,2,FALSE),""))} -> Civil | S18: 1 | T18: Glb. | U18: =APU!K33 -> 236.976 | V18: =U18*S18 -> 236.976 | AB18: {=IF($S18="","",SUMIFS(APU!$O:$O,APU!$A:$A,IF(ISNUMBER($C18),REPLACE(TEXT($C18,"0.0000"),5,0,"."),$C18),APU!$G:$G,"hh")/MAX(1,SUMPRODUCT(($C$15:$C$262=$C18)*($S$15:$S$262<>""))))} -> 33.6 | AC18: =IF($S18="","",IFERROR(VLOOKUP($AE18,APU!$V:$X,2,FALSE),"")) -> 1 | AD18: =IF(OR($S18="",$AC18="",N($AC18)=0),"",$S18/$AC18) -> 1 | AE18: =IF($C18="","",IF(ISNUMBER($C18),REPLACE(TEXT($C18,"0.0000"),5,0,"."),$C18)) -> 1.01.03 | AH18: =IF($S18="","",$AB18*N($AG18)) -> 0 | AI18: =IF($S18="","",$AE18&IF(TRIM($N18)="",""," | "&TRIM($N18))&IF(OR(TRIM($O18)="",TRIM($O18)="-"),""," | "&TRIM($O18))) -> 1.01.03 | -
B19: CIVIL | AB19: {=IF($S19="","",SUMIFS(APU!$O:$O,APU!$A:$A,IF(ISNUMBER($C19),REPLACE(TEXT($C19,"0.0000"),5,0,"."),$C19),APU!$G:$G,"hh")/MAX(1,SUMPRODUCT(($C$15:$C$262=$C19)*($S$15:$S$262<>""))))} | AC19: =IF($S19="","",IFERROR(VLOOKUP($AE19,APU!$V:$X,2,FALSE),"")) | AD19: =IF(OR($S19="",$AC19="",N($AC19)=0),"",$S19/$AC19) | AE19: =IF($C19="","",IF(ISNUMBER($C19),REPLACE(TEXT($C19,"0.0000"),5,0,"."),$C19)) | AH19: =IF($S19="","",$AB19*N($AG19)) | AI19: =IF($S19="","",$AE19&IF(TRIM($N19)="",""," | "&TRIM($N19))&IF(OR(TRIM($O19)="",TRIM($O19)="-"),""," | "&TRIM($O19)))
B20: 8.2.1 | C20: 2.01 | D20: - | E20: - | F20: - | G20: DEMOLICIÓN | N20: - | O20: - | P20: =IF(TRIM($G20)="","",TRIM($G20)&IF(OR(TRIM($N20)="",TRIM($N20)="-"),""," - "&TRIM($N20))&IF(OR(TRIM($O20)="",TRIM($O20)="-"),""," - "&TRIM($O20))&IF(ISNUMBER(SEARCH("SUMINISTRO",$G20))," - "&$AK$13,IF(ISNUMBER(SEARCH("MONTAJE",$G20))," - "&$AK$12,""))) -> DEMOLICIÓN | Q20: En alcance | R20: {=IF($G20="","",IFERROR(VLOOKUP(LOOKUP(2,1/(($B$14:$B20<>"")*($C$14:$C20="")),$B$14:$B20),$AM$12:$AN$16,2,FALSE),""))} -> Civil | AB20: {=IF($S20="","",SUMIFS(APU!$O:$O,APU!$A:$A,IF(ISNUMBER($C20),REPLACE(TEXT($C20,"0.0000"),5,0,"."),$C20),APU!$G:$G,"hh")/MAX(1,SUMPRODUCT(($C$15:$C$262=$C20)*($S$15:$S$262<>""))))} | AC20: =IF($S20="","",IFERROR(VLOOKUP($AE20,APU!$V:$X,2,FALSE),"")) | AD20: =IF(OR($S20="",$AC20="",N($AC20)=0),"",$S20/$AC20) | AE20: =IF($C20="","",IF(ISNUMBER($C20),REPLACE(TEXT($C20,"0.0000"),5,0,"."),$C20)) -> 2.01.00 | AH20: =IF($S20="","",$AB20*N($AG20)) | AI20: =IF($S20="","",$AE20&IF(TRIM($N20)="",""," | "&TRIM($N20))&IF(OR(TRIM($O20)="",TRIM($O20)="-"),""," | "&TRIM($O20)))
B21: 8.2.1 | C21: =+C20+0.0001 -> 2.0101 | D21: - | E21: - | F21: - | G21: Demolición de bases e = 50 cm | P21: =IF(TRIM($G21)="","",TRIM($G21)&IF(OR(TRIM($N21)="",TRIM($N21)="-"),""," - "&TRIM($N21))&IF(OR(TRIM($O21)="",TRIM($O21)="-"),""," - "&TRIM($O21))&IF(ISNUMBER(SEARCH("SUMINISTRO",$G21))," - "&$AK$13,IF(ISNUMBER(SEARCH("MONTAJE",$G21))," - "&$AK$12,""))) -> Demolición de bases e = 50 cm | Q21: En alcance | R21: {=IF($G21="","",IFERROR(VLOOKUP(LOOKUP(2,1/(($B$14:$B21<>"")*($C$14:$C21="")),$B$14:$B21),$AM$12:$AN$16,2,FALSE),""))} -> Civil | S21: 1.28 | T21: m3 | U21: =APU!K41 -> 420.851 | V21: =U21*S21 -> 538.68928 | AB21: {=IF($S21="","",SUMIFS(APU!$O:$O,APU!$A:$A,IF(ISNUMBER($C21),REPLACE(TEXT($C21,"0.0000"),5,0,"."),$C21),APU!$G:$G,"hh")/MAX(1,SUMPRODUCT(($C$15:$C$262=$C21)*($S$15:$S$262<>""))))} -> 53.76 | AC21: =IF($S21="","",IFERROR(VLOOKUP($AE21,APU!$V:$X,2,FALSE),"")) -> 0.4 | AD21: =IF(OR($S21="",$AC21="",N($AC21)=0),"",$S21/$AC21) -> 3.2 | AE21: =IF($C21="","",IF(ISNUMBER($C21),REPLACE(TEXT($C21,"0.0000"),5,0,"."),$C21)) -> 2.01.01 | AH21: =IF($S21="","",$AB21*N($AG21)) -> 0 | AI21: =IF($S21="","",$AE21&IF(TRIM($N21)="",""," | "&TRIM($N21))&IF(OR(TRIM($O21)="",TRIM($O21)="-"),""," | "&TRIM($O21))) -> 2.01.01
B22: 8.2.2 | C22: 2.02 | D22: - | E22: - | F22: - | G22: CONCRETO SIMPLE | P22: =IF(TRIM($G22)="","",TRIM($G22)&IF(OR(TRIM($N22)="",TRIM($N22)="-"),""," - "&TRIM($N22))&IF(OR(TRIM($O22)="",TRIM($O22)="-"),""," - "&TRIM($O22))&IF(ISNUMBER(SEARCH("SUMINISTRO",$G22))," - "&$AK$13,IF(ISNUMBER(SEARCH("MONTAJE",$G22))," - "&$AK$12,""))) -> CONCRETO SIMPLE | Q22: En alcance | R22: {=IF($G22="","",IFERROR(VLOOKUP(LOOKUP(2,1/(($B$14:$B22<>"")*($C$14:$C22="")),$B$14:$B22),$AM$12:$AN$16,2,FALSE),""))} -> Civil | AB22: {=IF($S22="","",SUMIFS(APU!$O:$O,APU!$A:$A,IF(ISNUMBER($C22),REPLACE(TEXT($C22,"0.0000"),5,0,"."),$C22),APU!$G:$G,"hh")/MAX(1,SUMPRODUCT(($C$15:$C$262=$C22)*($S$15:$S$262<>""))))} | AC22: =IF($S22="","",IFERROR(VLOOKUP($AE22,APU!$V:$X,2,FALSE),"")) | AD22: =IF(OR($S22="",$AC22="",N($AC22)=0),"",$S22/$AC22) | AE22: =IF($C22="","",IF(ISNUMBER($C22),REPLACE(TEXT($C22,"0.0000"),5,0,"."),$C22)) -> 2.02.00 | AH22: =IF($S22="","",$AB22*N($AG22)) | AI22: =IF($S22="","",$AE22&IF(TRIM($N22)="",""," | "&TRIM($N22))&IF(OR(TRIM($O22)="",TRIM($O22)="-"),""," | "&TRIM($O22)))
B23: 8.2.2 | C23: =+C22+0.0001 -> 2.0201 | D23: - | E23: - | F23: - | G23: Concreto simple f'c=100 kg/cm2 | P23: =IF(TRIM($G23)="","",TRIM($G23)&IF(OR(TRIM($N23)="",TRIM($N23)="-"),""," - "&TRIM($N23))&IF(OR(TRIM($O23)="",TRIM($O23)="-"),""," - "&TRIM($O23))&IF(ISNUMBER(SEARCH("SUMINISTRO",$G23))," - "&$AK$13,IF(ISNUMBER(SEARCH("MONTAJE",$G23))," - "&$AK$12,""))) -> Concreto simple f'c=100 kg/cm2 | Q23: En alcance | R23: {=IF($G23="","",IFERROR(VLOOKUP(LOOKUP(2,1/(($B$14:$B23<>"")*($C$14:$C23="")),$B$14:$B23),$AM$12:$AN$16,2,FALSE),""))} -> Civil | S23: =(0.9*0.45+2*0.5*1.2)*0.05 -> 0.08025 | T23: m3 | U23: =APU!K57 -> 268.55525 | V23: =U23*S23 -> 21.551559 | AB23: {=IF($S23="","",SUMIFS(APU!$O:$O,APU!$A:$A,IF(ISNUMBER($C23),REPLACE(TEXT($C23,"0.0000"),5,0,"."),$C23),APU!$G:$G,"hh")/MAX(1,SUMPRODUCT(($C$15:$C$262=$C23)*($S$15:$S$262<>""))))} -> 0.35096 | AC23: =IF($S23="","",IFERROR(VLOOKUP($AE23,APU!$V:$X,2,FALSE),"")) -> 15 | AD23: =IF(OR($S23="",$AC23="",N($AC23)=0),"",$S23/$AC23) -> 0.00535 | AE23: =IF($C23="","",IF(ISNUMBER($C23),REPLACE(TEXT($C23,"0.0000"),5,0,"."),$C23)) -> 2.02.01 | AH23: =IF($S23="","",$AB23*N($AG23)) -> 0 | AI23: =IF($S23="","",$AE23&IF(TRIM($N23)="",""," | "&TRIM($N23))&IF(OR(TRIM($O23)="",TRIM($O23)="-"),""," | "&TRIM($O23))) -> 2.02.01
B24: 8.2.3 | C24: 2.03 | D24: - | E24: - | F24: - | G24: CONCRETO ARMADO | P24: =IF(TRIM($G24)="","",TRIM($G24)&IF(OR(TRIM($N24)="",TRIM($N24)="-"),""," - "&TRIM($N24))&IF(OR(TRIM($O24)="",TRIM($O24)="-"),""," - "&TRIM($O24))&IF(ISNUMBER(SEARCH("SUMINISTRO",$G24))," - "&$AK$13,IF(ISNUMBER(SEARCH("MONTAJE",$G24))," - "&$AK$12,""))) -> CONCRETO ARMADO | Q24: En alcance | R24: {=IF($G24="","",IFERROR(VLOOKUP(LOOKUP(2,1/(($B$14:$B24<>"")*($C$14:$C24="")),$B$14:$B24),$AM$12:$AN$16,2,FALSE),""))} -> Civil | AB24: {=IF($S24="","",SUMIFS(APU!$O:$O,APU!$A:$A,IF(ISNUMBER($C24),REPLACE(TEXT($C24,"0.0000"),5,0,"."),$C24),APU!$G:$G,"hh")/MAX(1,SUMPRODUCT(($C$15:$C$262=$C24)*($S$15:$S$262<>""))))} | AC24: =IF($S24="","",IFERROR(VLOOKUP($AE24,APU!$V:$X,2,FALSE),"")) | AD24: =IF(OR($S24="",$AC24="",N($AC24)=0),"",$S24/$AC24) | AE24: =IF($C24="","",IF(ISNUMBER($C24),REPLACE(TEXT($C24,"0.0000"),5,0,"."),$C24)) -> 2.03.00 | AH24: =IF($S24="","",$AB24*N($AG24)) | AI24: =IF($S24="","",$AE24&IF(TRIM($N24)="",""," | "&TRIM($N24))&IF(OR(TRIM($O24)="",TRIM($O24)="-"),""," | "&TRIM($O24)))
B25: 8.2.3 | C25: =+C24+0.0001 -> 2.0301 | D25: - | E25: - | F25: - | G25: Concreto f'c=25MPa, Cemento tipo HS | P25: =IF(TRIM($G25)="","",TRIM($G25)&IF(OR(TRIM($N25)="",TRIM($N25)="-"),""," - "&TRIM($N25))&IF(OR(TRIM($O25)="",TRIM($O25)="-"),""," - "&TRIM($O25))&IF(ISNUMBER(SEARCH("SUMINISTRO",$G25))," - "&$AK$13,IF(ISNUMBER(SEARCH("MONTAJE",$G25))," - "&$AK$12,""))) -> Concreto f'c=25MPa, Cemento tipo HS | Q25: En alcance | R25: {=IF($G25="","",IFERROR(VLOOKUP(LOOKUP(2,1/(($B$14:$B25<>"")*($C$14:$C25="")),$B$14:$B25),$AM$12:$AN$16,2,FALSE),""))} -> Civil | S25: =(0.9*0.45*0.5+2*0.5*1.2*0.5)+0.0675+0.027 -> 0.897 | T25: m3 | U25: =APU!K75 -> 321.20525 | V25: =U25*S25 -> 288.12111 | AB25: {=IF($S25="","",SUMIFS(APU!$O:$O,APU!$A:$A,IF(ISNUMBER($C25),REPLACE(TEXT($C25,"0.0000"),5,0,"."),$C25),APU!$G:$G,"hh")/MAX(1,SUMPRODUCT(($C$15:$C$262=$C25)*($S$15:$S$262<>""))))} -> 3.92288 | AC25: =IF($S25="","",IFERROR(VLOOKUP($AE25,APU!$V:$X,2,FALSE),"")) -> 15 | AD25: =IF(OR($S25="",$AC25="",N($AC25)=0),"",$S25/$AC25) -> 0.0598 | AE25: =IF($C25="","",IF(ISNUMBER($C25),REPLACE(TEXT($C25,"0.0000"),5,0,"."),$C25)) -> 2.03.01 | AH25: =IF($S25="","",$AB25*N($AG25)) -> 0 | AI25: =IF($S25="","",$AE25&IF(TRIM($N25)="",""," | "&TRIM($N25))&IF(OR(TRIM($O25)="",TRIM($O25)="-"),""," | "&TRIM($O25))) -> 2.03.01
B26: 8.2.3 | C26: =+C25+0.0001 -> 2.0302 | D26: - | E26: - | F26: - | G26: Encofrado y desencofrado | P26: =IF(TRIM($G26)="","",TRIM($G26)&IF(OR(TRIM($N26)="",TRIM($N26)="-"),""," - "&TRIM($N26))&IF(OR(TRIM($O26)="",TRIM($O26)="-"),""," - "&TRIM($O26))&IF(ISNUMBER(SEARCH("SUMINISTRO",$G26))," - "&$AK$13,IF(ISNUMBER(SEARCH("MONTAJE",$G26))," - "&$AK$12,""))) -> Encofrado y desencofrado | Q26: En alcance | R26: {=IF($G26="","",IFERROR(VLOOKUP(LOOKUP(2,1/(($B$14:$B26<>"")*($C$14:$C26="")),$B$14:$B26),$AM$12:$AN$16,2,FALSE),""))} -> Civil | S26: =(0.9+0.45+2*(0.5+1.2))+1.8+0.45 -> 7 | T26: m2 | U26: =APU!K96 -> 29.719167 | V26: =U26*S26 -> 208.03417 | AB26: {=IF($S26="","",SUMIFS(APU!$O:$O,APU!$A:$A,IF(ISNUMBER($C26),REPLACE(TEXT($C26,"0.0000"),5,0,"."),$C26),APU!$G:$G,"hh")/MAX(1,SUMPRODUCT(($C$15:$C$262=$C26)*($S$15:$S$262<>""))))} -> 6.8444444 | AC26: =IF($S26="","",IFERROR(VLOOKUP($AE26,APU!$V:$X,2,FALSE),"")) -> 18 | AD26: =IF(OR($S26="",$AC26="",N($AC26)=0),"",$S26/$AC26) -> 0.38888889 | AE26: =IF($C26="","",IF(ISNUMBER($C26),REPLACE(TEXT($C26,"0.0000"),5,0,"."),$C26)) -> 2.03.02 | AH26: =IF($S26="","",$AB26*N($AG26)) -> 0 | AI26: =IF($S26="","",$AE26&IF(TRIM($N26)="",""," | "&TRIM($N26))&IF(OR(TRIM($O26)="",TRIM($O26)="-"),""," | "&TRIM($O26))) -> 2.03.02
B27: 8.2.3 | C27: =+C26+0.0001 -> 2.0303 | D27: - | E27: - | F27: - | G27: Acero de Refuerzo (ASTM A-615 G 60, fy = 420 MPa) | P27: =IF(TRIM($G27)="","",TRIM($G27)&IF(OR(TRIM($N27)="",TRIM($N27)="-"),""," - "&TRIM($N27))&IF(OR(TRIM($O27)="",TRIM($O27)="-"),""," - "&TRIM($O27))&IF(ISNUMBER(SEARCH("SUMINISTRO",$G27))," - "&$AK$13,IF(ISNUMBER(SEARCH("MONTAJE",$G27))," - "&$AK$12,""))) -> Acero de Refuerzo (ASTM A-615 G 60, fy = 420 MPa) | Q27: En alcance | R27: {=IF($G27="","",IFERROR(VLOOKUP(LOOKUP(2,1/(($B$14:$B27<>"")*($C$14:$C27="")),$B$14:$B27),$AM$12:$AN$16,2,FALSE),""))} -> Civil | S27: =((0.45*2+1)*5+(1.8+1)*3+(0.5*2+1)*6+(2.4+1)*3)*1.55+23 -> 85.155 | T27: kg | U27: =APU!K117 -> 2.4012752 | V27: =U27*S27 -> 204.48059 | AB27: {=IF($S27="","",SUMIFS(APU!$O:$O,APU!$A:$A,IF(ISNUMBER($C27),REPLACE(TEXT($C27,"0.0000"),5,0,"."),$C27),APU!$G:$G,"hh")/MAX(1,SUMPRODUCT(($C$15:$C$262=$C27)*($S$15:$S$262<>""))))} -> 5.994912 | AC27: =IF($S27="","",IFERROR(VLOOKUP($AE27,APU!$V:$X,2,FALSE),"")) -> 250 | AD27: =IF(OR($S27="",$AC27="",N($AC27)=0),"",$S27/$AC27) -> 0.34062 | AE27: =IF($C27="","",IF(ISNUMBER($C27),REPLACE(TEXT($C27,"0.0000"),5,0,"."),$C27)) -> 2.03.03 | AH27: =IF($S27="","",$AB27*N($AG27)) -> 0 | AI27: =IF($S27="","",$AE27&IF(TRIM($N27)="",""," | "&TRIM($N27))&IF(OR(TRIM($O27)="",TRIM($O27)="-"),""," | "&TRIM($O27))) -> 2.03.03
B28: 8.2.4 | C28: 2.04 | D28: - | E28: - | F28: - | G28: OTROS | P28: =IF(TRIM($G28)="","",TRIM($G28)&IF(OR(TRIM($N28)="",TRIM($N28)="-"),""," - "&TRIM($N28))&IF(OR(TRIM($O28)="",TRIM($O28)="-"),""," - "&TRIM($O28))&IF(ISNUMBER(SEARCH("SUMINISTRO",$G28))," - "&$AK$13,IF(ISNUMBER(SEARCH("MONTAJE",$G28))," - "&$AK$12,""))) -> OTROS | Q28: En alcance | R28: {=IF($G28="","",IFERROR(VLOOKUP(LOOKUP(2,1/(($B$14:$B28<>"")*($C$14:$C28="")),$B$14:$B28),$AM$12:$AN$16,2,FALSE),""))} -> Civil | AB28: {=IF($S28="","",SUMIFS(APU!$O:$O,APU!$A:$A,IF(ISNUMBER($C28),REPLACE(TEXT($C28,"0.0000"),5,0,"."),$C28),APU!$G:$G,"hh")/MAX(1,SUMPRODUCT(($C$15:$C$262=$C28)*($S$15:$S$262<>""))))} | AC28: =IF($S28="","",IFERROR(VLOOKUP($AE28,APU!$V:$X,2,FALSE),"")) | AD28: =IF(OR($S28="",$AC28="",N($AC28)=0),"",$S28/$AC28) | AE28: =IF($C28="","",IF(ISNUMBER($C28),REPLACE(TEXT($C28,"0.0000"),5,0,"."),$C28)) -> 2.04.00 | AH28: =IF($S28="","",$AB28*N($AG28)) | AI28: =IF($S28="","",$AE28&IF(TRIM($N28)="",""," | "&TRIM($N28))&IF(OR(TRIM($O28)="",TRIM($O28)="-"),""," | "&TRIM($O28)))
B29: 8.2.4 | C29: =+C28+0.0001 -> 2.0401 | D29: - | E29: - | F29: - | G29: Varilla roscada tipo HAS o equivalente tecnico Ø 1" L=30cm, contratuerca y arandela, tipo de anclaje quimico adhesivo HIT-HY 200 o equivalente tecnico | P29: =IF(TRIM($G29)="","",TRIM($G29)&IF(OR(TRIM($N29)="",TRIM($N29)="-"),""," - "&TRIM($N29))&IF(OR(TRIM($O29)="",TRIM($O29)="-"),""," - "&TRIM($O29))&IF(ISNUMBER(SEARCH("SUMINISTRO",$G29))," - "&$AK$13,IF(ISNUMBER(SEARCH("MONTAJE",$G29))," - "&$AK$12,""))) -> Varilla roscada tipo HAS o equivalente tecnico Ø 1" L=30cm, contratuerca y arandela, tipo de anclaje quimico adhesivo HIT-HY 200 o equivalente tecnico | Q29: En alcance | R29: {=IF($G29="","",IFERROR(VLOOKUP(LOOKUP(2,1/(($B$14:$B29<>"")*($C$14:$C29="")),$B$14:$B29),$AM$12:$AN$16,2,FALSE),""))} -> Civil | S29: 12 | T29: UND | U29: =APU!K135 -> 117.23702 | V29: =U29*S29 -> 1406.8442 | AB29: {=IF($S29="","",SUMIFS(APU!$O:$O,APU!$A:$A,IF(ISNUMBER($C29),REPLACE(TEXT($C29,"0.0000"),5,0,"."),$C29),APU!$G:$G,"hh")/MAX(1,SUMPRODUCT(($C$15:$C$262=$C29)*($S$15:$S$262<>""))))} -> 10.08 | AC29: =IF($S29="","",IFERROR(VLOOKUP($AE29,APU!$V:$X,2,FALSE),"")) -> 20 | AD29: =IF(OR($S29="",$AC29="",N($AC29)=0),"",$S29/$AC29) -> 0.6 | AE29: =IF($C29="","",IF(ISNUMBER($C29),REPLACE(TEXT($C29,"0.0000"),5,0,"."),$C29)) -> 2.04.01 | AH29: =IF($S29="","",$AB29*N($AG29)) -> 0 | AI29: =IF($S29="","",$AE29&IF(TRIM($N29)="",""," | "&TRIM($N29))&IF(OR(TRIM($O29)="",TRIM($O29)="-"),""," | "&TRIM($O29))) -> 2.04.01
B30: 8.2.4 | C30: =+C29+0.0001 -> 2.0402 | D30: - | E30: - | F30: - | G30: Juntas de expansión de acuerdo al plano estándar CRD-DWG-11760-1-33-4002 | P30: =IF(TRIM($G30)="","",TRIM($G30)&IF(OR(TRIM($N30)="",TRIM($N30)="-"),""," - "&TRIM($N30))&IF(OR(TRIM($O30)="",TRIM($O30)="-"),""," - "&TRIM($O30))&IF(ISNUMBER(SEARCH("SUMINISTRO",$G30))," - "&$AK$13,IF(ISNUMBER(SEARCH("MONTAJE",$G30))," - "&$AK$12,""))) -> Juntas de expansión de acuerdo al plano estándar CRD-DWG-11760-1-33-4002 | Q30: En alcance | R30: {=IF($G30="","",IFERROR(VLOOKUP(LOOKUP(2,1/(($B$14:$B30<>"")*($C$14:$C30="")),$B$14:$B30),$AM$12:$AN$16,2,FALSE),""))} -> Civil | S30: =1.8+0.9+(1+2.4)*2 -> 9.5 | T30: m | U30: =+APU!K152 -> 22.76202 | V30: =U30*S30 -> 216.23919 | AB30: {=IF($S30="","",SUMIFS(APU!$O:$O,APU!$A:$A,IF(ISNUMBER($C30),REPLACE(TEXT($C30,"0.0000"),5,0,"."),$C30),APU!$G:$G,"hh")/MAX(1,SUMPRODUCT(($C$15:$C$262=$C30)*($S$15:$S$262<>""))))} -> 7.98 | AC30: =IF($S30="","",IFERROR(VLOOKUP($AE30,APU!$V:$X,2,FALSE),"")) -> 20 | AD30: =IF(OR($S30="",$AC30="",N($AC30)=0),"",$S30/$AC30) -> 0.475 | AE30: =IF($C30="","",IF(ISNUMBER($C30),REPLACE(TEXT($C30,"0.0000"),5,0,"."),$C30)) -> 2.04.02 | AH30: =IF($S30="","",$AB30*N($AG30)) -> 0 | AI30: =IF($S30="","",$AE30&IF(TRIM($N30)="",""," | "&TRIM($N30))&IF(OR(TRIM($O30)="",TRIM($O30)="-"),""," | "&TRIM($O30))) -> 2.04.02
B31: 8.2.4 | C31: =+C30+0.0001 -> 2.0403 | D31: - | E31: - | F31: - | G31: Soporte metálico ASTM A36 para tuberías y tableros eléctricos | P31: =IF(TRIM($G31)="","",TRIM($G31)&IF(OR(TRIM($N31)="",TRIM($N31)="-"),""," - "&TRIM($N31))&IF(OR(TRIM($O31)="",TRIM($O31)="-"),""," - "&TRIM($O31))&IF(ISNUMBER(SEARCH("SUMINISTRO",$G31))," - "&$AK$13,IF(ISNUMBER(SEARCH("MONTAJE",$G31))," - "&$AK$12,""))) -> Soporte metálico ASTM A36 para tuberías y tableros eléctricos | Q31: En alcance | R31: {=IF($G31="","",IFERROR(VLOOKUP(LOOKUP(2,1/(($B$14:$B31<>"")*($C$14:$C31="")),$B$14:$B31),$AM$12:$AN$16,2,FALSE),""))} -> Civil | S31: =556.74+96.75 -> 653.49 | T31: kg | U31: =+APU!K169 -> 6.8543616 | V31: =U31*S31 -> 4479.2568 | AB31: {=IF($S31="","",SUMIFS(APU!$O:$O,APU!$A:$A,IF(ISNUMBER($C31),REPLACE(TEXT($C31,"0.0000"),5,0,"."),$C31),APU!$G:$G,"hh")/MAX(1,SUMPRODUCT(($C$15:$C$262=$C31)*($S$15:$S$262<>""))))} -> 43.914528 | AC31: =IF($S31="","",IFERROR(VLOOKUP($AE31,APU!$V:$X,2,FALSE),"")) -> 250 | AD31: =IF(OR($S31="",$AC31="",N($AC31)=0),"",$S31/$AC31) -> 2.61396 | AE31: =IF($C31="","",IF(ISNUMBER($C31),REPLACE(TEXT($C31,"0.0000"),5,0,"."),$C31)) -> 2.04.03 | AH31: =IF($S31="","",$AB31*N($AG31)) -> 0 | AI31: =IF($S31="","",$AE31&IF(TRIM($N31)="",""," | "&TRIM($N31))&IF(OR(TRIM($O31)="",TRIM($O31)="-"),""," | "&TRIM($O31))) -> 2.04.03
B32: 8.2.4 | C32: =+C31+0.0001 -> 2.0404 | D32: - | E32: - | F32: - | G32: Placa base para soportería de tuberías | P32: =IF(TRIM($G32)="","",TRIM($G32)&IF(OR(TRIM($N32)="",TRIM($N32)="-"),""," - "&TRIM($N32))&IF(OR(TRIM($O32)="",TRIM($O32)="-"),""," - "&TRIM($O32))&IF(ISNUMBER(SEARCH("SUMINISTRO",$G32))," - "&$AK$13,IF(ISNUMBER(SEARCH("MONTAJE",$G32))," - "&$AK$12,""))) -> Placa base para soportería de tuberías | Q32: En alcance | R32: {=IF($G32="","",IFERROR(VLOOKUP(LOOKUP(2,1/(($B$14:$B32<>"")*($C$14:$C32="")),$B$14:$B32),$AM$12:$AN$16,2,FALSE),""))} -> Civil | S32: =287.3+43.62 -> 330.92 | T32: kg | U32: =+APU!K190 -> 6.8543616 | V32: =U32*S32 -> 2268.2453 | AB32: {=IF($S32="","",SUMIFS(APU!$O:$O,APU!$A:$A,IF(ISNUMBER($C32),REPLACE(TEXT($C32,"0.0000"),5,0,"."),$C32),APU!$G:$G,"hh")/MAX(1,SUMPRODUCT(($C$15:$C$262=$C32)*($S$15:$S$262<>""))))} -> 22.237824 | AC32: =IF($S32="","",IFERROR(VLOOKUP($AE32,APU!$V:$X,2,FALSE),"")) -> 250 | AD32: =IF(OR($S32="",$AC32="",N($AC32)=0),"",$S32/$AC32) -> 1.32368 | AE32: =IF($C32="","",IF(ISNUMBER($C32),REPLACE(TEXT($C32,"0.0000"),5,0,"."),$C32)) -> 2.04.04 | AH32: =IF($S32="","",$AB32*N($AG32)) -> 0 | AI32: =IF($S32="","",$AE32&IF(TRIM($N32)="",""," | "&TRIM($N32))&IF(OR(TRIM($O32)="",TRIM($O32)="-"),""," | "&TRIM($O32))) -> 2.04.04
B33: 8.2.4 | C33: =+C32+0.0001 -> 2.0405 | D33: - | E33: - | F33: - | G33: Mortero de nivelacion de cemento e=25 mm, De acuerdo Especificación técnica 000.215.03600_0 | P33: =IF(TRIM($G33)="","",TRIM($G33)&IF(OR(TRIM($N33)="",TRIM($N33)="-"),""," - "&TRIM($N33))&IF(OR(TRIM($O33)="",TRIM($O33)="-"),""," - "&TRIM($O33))&IF(ISNUMBER(SEARCH("SUMINISTRO",$G33))," - "&$AK$13,IF(ISNUMBER(SEARCH("MONTAJE",$G33))," - "&$AK$12,""))) -> Mortero de nivelacion de cemento e=25 mm, De acuerdo Especificación técnica 000.215.03600_0 | Q33: En alcance | R33: {=IF($G33="","",IFERROR(VLOOKUP(LOOKUP(2,1/(($B$14:$B33<>"")*($C$14:$C33="")),$B$14:$B33),$AM$12:$AN$16,2,FALSE),""))} -> Civil | S33: =104.15+0.01125+0.004125 -> 104.16538 | T33: Lt | U33: =+APU!K211 -> 21.550511 | V33: =U33*S33 -> 2244.817 | AB33: {=IF($S33="","",SUMIFS(APU!$O:$O,APU!$A:$A,IF(ISNUMBER($C33),REPLACE(TEXT($C33,"0.0000"),5,0,"."),$C33),APU!$G:$G,"hh")/MAX(1,SUMPRODUCT(($C$15:$C$262=$C33)*($S$15:$S$262<>""))))} -> 174.99783 | AC33: =IF($S33="","",IFERROR(VLOOKUP($AE33,APU!$V:$X,2,FALSE),"")) -> 10 | AD33: =IF(OR($S33="",$AC33="",N($AC33)=0),"",$S33/$AC33) -> 10.416538 | AE33: =IF($C33="","",IF(ISNUMBER($C33),REPLACE(TEXT($C33,"0.0000"),5,0,"."),$C33)) -> 2.04.05 | AH33: =IF($S33="","",$AB33*N($AG33)) -> 0 | AI33: =IF($S33="","",$AE33&IF(TRIM($N33)="",""," | "&TRIM($N33))&IF(OR(TRIM($O33)="",TRIM($O33)="-"),""," | "&TRIM($O33))) -> 2.04.05
B34: 8.2.4 | C34: =+C33+0.0001 -> 2.0406 | D34: - | E34: - | F34: - | G34: Perno de expansión 1/2"x3" | P34: =IF(TRIM($G34)="","",TRIM($G34)&IF(OR(TRIM($N34)="",TRIM($N34)="-"),""," - "&TRIM($N34))&IF(OR(TRIM($O34)="",TRIM($O34)="-"),""," - "&TRIM($O34))&IF(ISNUMBER(SEARCH("SUMINISTRO",$G34))," - "&$AK$13,IF(ISNUMBER(SEARCH("MONTAJE",$G34))," - "&$AK$12,""))) -> Perno de expansión 1/2"x3" | Q34: En alcance | R34: {=IF($G34="","",IFERROR(VLOOKUP(LOOKUP(2,1/(($B$14:$B34<>"")*($C$14:$C34="")),$B$14:$B34),$AM$12:$AN$16,2,FALSE),""))} -> Civil | S34: 102 | T34: UND | U34: =+APU!K229 -> 11.860789 | V34: =U34*S34 -> 1209.8004 | AB34: {=IF($S34="","",SUMIFS(APU!$O:$O,APU!$A:$A,IF(ISNUMBER($C34),REPLACE(TEXT($C34,"0.0000"),5,0,"."),$C34),APU!$G:$G,"hh")/MAX(1,SUMPRODUCT(($C$15:$C$262=$C34)*($S$15:$S$262<>""))))} -> 114.24 | AC34: =IF($S34="","",IFERROR(VLOOKUP($AE34,APU!$V:$X,2,FALSE),"")) -> 15 | AD34: =IF(OR($S34="",$AC34="",N($AC34)=0),"",$S34/$AC34) -> 6.8 | AE34: =IF($C34="","",IF(ISNUMBER($C34),REPLACE(TEXT($C34,"0.0000"),5,0,"."),$C34)) -> 2.04.06 | AH34: =IF($S34="","",$AB34*N($AG34)) -> 0 | AI34: =IF($S34="","",$AE34&IF(TRIM($N34)="",""," | "&TRIM($N34))&IF(OR(TRIM($O34)="",TRIM($O34)="-"),""," | "&TRIM($O34))) -> 2.04.06
B35: 8.2.4 | C35: =+C34+0.0001 -> 2.0407 | D35: - | E35: - | F35: - | G35: Perno de expansión 5/8"x3" | P35: =IF(TRIM($G35)="","",TRIM($G35)&IF(OR(TRIM($N35)="",TRIM($N35)="-"),""," - "&TRIM($N35))&IF(OR(TRIM($O35)="",TRIM($O35)="-"),""," - "&TRIM($O35))&IF(ISNUMBER(SEARCH("SUMINISTRO",$G35))," - "&$AK$13,IF(ISNUMBER(SEARCH("MONTAJE",$G35))," - "&$AK$12,""))) -> Perno de expansión 5/8"x3" | Q35: En alcance | R35: {=IF($G35="","",IFERROR(VLOOKUP(LOOKUP(2,1/(($B$14:$B35<>"")*($C$14:$C35="")),$B$14:$B35),$AM$12:$AN$16,2,FALSE),""))} -> Civil | S35: 26 | T35: UND | U35: =+APU!K246 -> 13.860789 | V35: =U35*S35 -> 360.3805 | AB35: {=IF($S35="","",SUMIFS(APU!$O:$O,APU!$A:$A,IF(ISNUMBER($C35),REPLACE(TEXT($C35,"0.0000"),5,0,"."),$C35),APU!$G:$G,"hh")/MAX(1,SUMPRODUCT(($C$15:$C$262=$C35)*($S$15:$S$262<>""))))} -> 29.12 | AC35: =IF($S35="","",IFERROR(VLOOKUP($AE35,APU!$V:$X,2,FALSE),"")) -> 15 | AD35: =IF(OR($S35="",$AC35="",N($AC35)=0),"",$S35/$AC35) -> 1.7333333 | AE35: =IF($C35="","",IF(ISNUMBER($C35),REPLACE(TEXT($C35,"0.0000"),5,0,"."),$C35)) -> 2.04.07 | AH35: =IF($S35="","",$AB35*N($AG35)) -> 0 | AI35: =IF($S35="","",$AE35&IF(TRIM($N35)="",""," | "&TRIM($N35))&IF(OR(TRIM($O35)="",TRIM($O35)="-"),""," | "&TRIM($O35))) -> 2.04.07
B36: 8.2.4 | C36: =+C35+0.0001 -> 2.0408 | D36: - | E36: - | F36: - | G36: Perno de expansión 3/4"x5" | P36: =IF(TRIM($G36)="","",TRIM($G36)&IF(OR(TRIM($N36)="",TRIM($N36)="-"),""," - "&TRIM($N36))&IF(OR(TRIM($O36)="",TRIM($O36)="-"),""," - "&TRIM($O36))&IF(ISNUMBER(SEARCH("SUMINISTRO",$G36))," - "&$AK$13,IF(ISNUMBER(SEARCH("MONTAJE",$G36))," - "&$AK$12,""))) -> Perno de expansión 3/4"x5" | Q36: En alcance | R36: {=IF($G36="","",IFERROR(VLOOKUP(LOOKUP(2,1/(($B$14:$B36<>"")*($C$14:$C36="")),$B$14:$B36),$AM$12:$AN$16,2,FALSE),""))} -> Civil | S36: 12 | T36: UND | U36: =+APU!K263 -> 14.432217 | V36: =U36*S36 -> 173.18661 | AB36: {=IF($S36="","",SUMIFS(APU!$O:$O,APU!$A:$A,IF(ISNUMBER($C36),REPLACE(TEXT($C36,"0.0000"),5,0,"."),$C36),APU!$G:$G,"hh")/MAX(1,SUMPRODUCT(($C$15:$C$262=$C36)*($S$15:$S$262<>""))))} -> 13.44 | AC36: =IF($S36="","",IFERROR(VLOOKUP($AE36,APU!$V:$X,2,FALSE),"")) -> 15 | AD36: =IF(OR($S36="",$AC36="",N($AC36)=0),"",$S36/$AC36) -> 0.8 | AE36: =IF($C36="","",IF(ISNUMBER($C36),REPLACE(TEXT($C36,"0.0000"),5,0,"."),$C36)) -> 2.04.08 | AH36: =IF($S36="","",$AB36*N($AG36)) -> 0 | AI36: =IF($S36="","",$AE36&IF(TRIM($N36)="",""," | "&TRIM($N36))&IF(OR(TRIM($O36)="",TRIM($O36)="-"),""," | "&TRIM($O36))) -> 2.04.08
B37: 8.2.4 | C37: =+C36+0.0001 -> 2.0409 | D37: - | E37: - | F37: - | G37: Pernos de anclaje embebido ASTM A36 Ø1/2" de 180 mm de los pedestales | P37: =IF(TRIM($G37)="","",TRIM($G37)&IF(OR(TRIM($N37)="",TRIM($N37)="-"),""," - "&TRIM($N37))&IF(OR(TRIM($O37)="",TRIM($O37)="-"),""," - "&TRIM($O37))&IF(ISNUMBER(SEARCH("SUMINISTRO",$G37))," - "&$AK$13,IF(ISNUMBER(SEARCH("MONTAJE",$G37))," - "&$AK$12,""))) -> Pernos de anclaje embebido ASTM A36 Ø1/2" de 180 mm de los pedestales | Q37: En alcance | R37: {=IF($G37="","",IFERROR(VLOOKUP(LOOKUP(2,1/(($B$14:$B37<>"")*($C$14:$C37="")),$B$14:$B37),$AM$12:$AN$16,2,FALSE),""))} -> Civil | S37: 28 | T37: UND | U37: =+APU!K280 -> 29.759754 | V37: =U37*S37 -> 833.27312 | AB37: {=IF($S37="","",SUMIFS(APU!$O:$O,APU!$A:$A,IF(ISNUMBER($C37),REPLACE(TEXT($C37,"0.0000"),5,0,"."),$C37),APU!$G:$G,"hh")/MAX(1,SUMPRODUCT(($C$15:$C$262=$C37)*($S$15:$S$262<>""))))} -> 47.04 | AC37: =IF($S37="","",IFERROR(VLOOKUP($AE37,APU!$V:$X,2,FALSE),"")) -> 10 | AD37: =IF(OR($S37="",$AC37="",N($AC37)=0),"",$S37/$AC37) -> 2.8 | AE37: =IF($C37="","",IF(ISNUMBER($C37),REPLACE(TEXT($C37,"0.0000"),5,0,"."),$C37)) -> 2.04.09 | AH37: =IF($S37="","",$AB37*N($AG37)) -> 0 | AI37: =IF($S37="","",$AE37&IF(TRIM($N37)="",""," | "&TRIM($N37))&IF(OR(TRIM($O37)="",TRIM($O37)="-"),""," | "&TRIM($O37))) -> 2.04.09
B38: 8.2.4 | C38: =+C37+0.0001 -> 2.041 | D38: - | E38: - | F38: - | G38: Picado, escarificado y limpieza sobre losa existente | P38: =IF(TRIM($G38)="","",TRIM($G38)&IF(OR(TRIM($N38)="",TRIM($N38)="-"),""," - "&TRIM($N38))&IF(OR(TRIM($O38)="",TRIM($O38)="-"),""," - "&TRIM($O38))&IF(ISNUMBER(SEARCH("SUMINISTRO",$G38))," - "&$AK$13,IF(ISNUMBER(SEARCH("MONTAJE",$G38))," - "&$AK$12,""))) -> Picado, escarificado y limpieza sobre losa existente | Q38: En alcance | R38: {=IF($G38="","",IFERROR(VLOOKUP(LOOKUP(2,1/(($B$14:$B38<>"")*($C$14:$C38="")),$B$14:$B38),$AM$12:$AN$16,2,FALSE),""))} -> Civil | S38: 0.615 | T38: m2 | U38: =+APU!K296 -> 13.08936 | V38: =U38*S38 -> 8.0499564 | AB38: {=IF($S38="","",SUMIFS(APU!$O:$O,APU!$A:$A,IF(ISNUMBER($C38),REPLACE(TEXT($C38,"0.0000"),5,0,"."),$C38),APU!$G:$G,"hh")/MAX(1,SUMPRODUCT(($C$15:$C$262=$C38)*($S$15:$S$262<>""))))} -> 0.6888 | AC38: =IF($S38="","",IFERROR(VLOOKUP($AE38,APU!$V:$X,2,FALSE),"")) -> 15 | AD38: =IF(OR($S38="",$AC38="",N($AC38)=0),"",$S38/$AC38) -> 0.041 | AE38: =IF($C38="","",IF(ISNUMBER($C38),REPLACE(TEXT($C38,"0.0000"),5,0,"."),$C38)) -> 2.04.10 | AH38: =IF($S38="","",$AB38*N($AG38)) -> 0 | AI38: =IF($S38="","",$AE38&IF(TRIM($N38)="",""," | "&TRIM($N38))&IF(OR(TRIM($O38)="",TRIM($O38)="-"),""," | "&TRIM($O38))) -> 2.04.10
B39: MECÁNICA - TUBERIAS | AB39: {=IF($S39="","",SUMIFS(APU!$O:$O,APU!$A:$A,IF(ISNUMBER($C39),REPLACE(TEXT($C39,"0.0000"),5,0,"."),$C39),APU!$G:$G,"hh")/MAX(1,SUMPRODUCT(($C$15:$C$262=$C39)*($S$15:$S$262<>""))))} | AC39: =IF($S39="","",IFERROR(VLOOKUP($AE39,APU!$V:$X,2,FALSE),"")) | AD39: =IF(OR($S39="",$AC39="",N($AC39)=0),"",$S39/$AC39) | AE39: =IF($C39="","",IF(ISNUMBER($C39),REPLACE(TEXT($C39,"0.0000"),5,0,"."),$C39)) | AH39: =IF($S39="","",$AB39*N($AG39)) | AI39: =IF($S39="","",$AE39&IF(TRIM($N39)="",""," | "&TRIM($N39))&IF(OR(TRIM($O39)="",TRIM($O39)="-"),""," | "&TRIM($O39)))
B40: 8.3.1 | C40: 3.01 | D40: - | E40: - | F40: - | G40: GENERALES | P40: =IF(TRIM($G40)="","",TRIM($G40)&IF(OR(TRIM($N40)="",TRIM($N40)="-"),""," - "&TRIM($N40))&IF(OR(TRIM($O40)="",TRIM($O40)="-"),""," - "&TRIM($O40))&IF(ISNUMBER(SEARCH("SUMINISTRO",$G40))," - "&$AK$13,IF(ISNUMBER(SEARCH("MONTAJE",$G40))," - "&$AK$12,""))) -> GENERALES | Q40: En alcance | R40: {=IF($G40="","",IFERROR(VLOOKUP(LOOKUP(2,1/(($B$14:$B40<>"")*($C$14:$C40="")),$B$14:$B40),$AM$12:$AN$16,2,FALSE),""))} -> Mecanica | AB40: {=IF($S40="","",SUMIFS(APU!$O:$O,APU!$A:$A,IF(ISNUMBER($C40),REPLACE(TEXT($C40,"0.0000"),5,0,"."),$C40),APU!$G:$G,"hh")/MAX(1,SUMPRODUCT(($C$15:$C$262=$C40)*($S$15:$S$262<>""))))} | AC40: =IF($S40="","",IFERROR(VLOOKUP($AE40,APU!$V:$X,2,FALSE),"")) | AD40: =IF(OR($S40="",$AC40="",N($AC40)=0),"",$S40/$AC40) | AE40: =IF($C40="","",IF(ISNUMBER($C40),REPLACE(TEXT($C40,"0.0000"),5,0,"."),$C40)) -> 3.01.00 | AH40: =IF($S40="","",$AB40*N($AG40)) | AI40: =IF($S40="","",$AE40&IF(TRIM($N40)="",""," | "&TRIM($N40))&IF(OR(TRIM($O40)="",TRIM($O40)="-"),""," | "&TRIM($O40)))
B41: 8.3.1 | C41: 3.01.01 | D41: - | E41: - | F41: - | G41: Etiquetado de tuberías | N41: - | O41: - | P41: =IF(TRIM($G41)="","",TRIM($G41)&IF(OR(TRIM($N41)="",TRIM($N41)="-"),""," - "&TRIM($N41))&IF(OR(TRIM($O41)="",TRIM($O41)="-"),""," - "&TRIM($O41))&IF(ISNUMBER(SEARCH("SUMINISTRO",$G41))," - "&$AK$13,IF(ISNUMBER(SEARCH("MONTAJE",$G41))," - "&$AK$12,""))) -> Etiquetado de tuberías | Q41: En alcance | R41: {=IF($G41="","",IFERROR(VLOOKUP(LOOKUP(2,1/(($B$14:$B41<>"")*($C$14:$C41="")),$B$14:$B41),$AM$12:$AN$16,2,FALSE),""))} -> Mecanica | S41: 1 | T41: Glb. | U41: =+APU!K312 -> 2447.404 | V41: =U41*S41 -> 2447.404 | AB41: {=IF($S41="","",SUMIFS(APU!$O:$O,APU!$A:$A,IF(ISNUMBER($C41),REPLACE(TEXT($C41,"0.0000"),5,0,"."),$C41),APU!$G:$G,"hh")/MAX(1,SUMPRODUCT(($C$15:$C$262=$C41)*($S$15:$S$262<>""))))} -> 168 | AC41: =IF($S41="","",IFERROR(VLOOKUP($AE41,APU!$V:$X,2,FALSE),"")) -> 0.1 | AD41: =IF(OR($S41="",$AC41="",N($AC41)=0),"",$S41/$AC41) -> 10 | AE41: =IF($C41="","",IF(ISNUMBER($C41),REPLACE(TEXT($C41,"0.0000"),5,0,"."),$C41)) -> 3.01.01 | AH41: =IF($S41="","",$AB41*N($AG41)) -> 0 | AI41: =IF($S41="","",$AE41&IF(TRIM($N41)="",""," | "&TRIM($N41))&IF(OR(TRIM($O41)="",TRIM($O41)="-"),""," | "&TRIM($O41))) -> 3.01.01 | -
B42: 8.3.1.2 | C42: 3.01.02 | D42: - | E42: - | F42: - | G42: Limpieza con agua | N42: - | O42: - | P42: =IF(TRIM($G42)="","",TRIM($G42)&IF(OR(TRIM($N42)="",TRIM($N42)="-"),""," - "&TRIM($N42))&IF(OR(TRIM($O42)="",TRIM($O42)="-"),""," - "&TRIM($O42))&IF(ISNUMBER(SEARCH("SUMINISTRO",$G42))," - "&$AK$13,IF(ISNUMBER(SEARCH("MONTAJE",$G42))," - "&$AK$12,""))) -> Limpieza con agua | Q42: En alcance | R42: {=IF($G42="","",IFERROR(VLOOKUP(LOOKUP(2,1/(($B$14:$B42<>"")*($C$14:$C42="")),$B$14:$B42),$AM$12:$AN$16,2,FALSE),""))} -> Mecanica | S42: 1 | T42: Glb. | U42: =+APU!K327 -> 545.4808 | V42: =U42*S42 -> 545.4808 | AB42: {=IF($S42="","",SUMIFS(APU!$O:$O,APU!$A:$A,IF(ISNUMBER($C42),REPLACE(TEXT($C42,"0.0000"),5,0,"."),$C42),APU!$G:$G,"hh")/MAX(1,SUMPRODUCT(($C$15:$C$262=$C42)*($S$15:$S$262<>""))))} -> 33.6 | AC42: =IF($S42="","",IFERROR(VLOOKUP($AE42,APU!$V:$X,2,FALSE),"")) -> 0.5 | AD42: =IF(OR($S42="",$AC42="",N($AC42)=0),"",$S42/$AC42) -> 2 | AE42: =IF($C42="","",IF(ISNUMBER($C42),REPLACE(TEXT($C42,"0.0000"),5,0,"."),$C42)) -> 3.01.02 | AH42: =IF($S42="","",$AB42*N($AG42)) -> 0 | AI42: =IF($S42="","",$AE42&IF(TRIM($N42)="",""," | "&TRIM($N42))&IF(OR(TRIM($O42)="",TRIM($O42)="-"),""," | "&TRIM($O42))) -> 3.01.02 | -
B43: 8.3.1.3 | C43: 3.01.03 | D43: - | E43: - | F43: - | G43: Pruebas de tuberías | N43: - | O43: - | P43: =IF(TRIM($G43)="","",TRIM($G43)&IF(OR(TRIM($N43)="",TRIM($N43)="-"),""," - "&TRIM($N43))&IF(OR(TRIM($O43)="",TRIM($O43)="-"),""," - "&TRIM($O43))&IF(ISNUMBER(SEARCH("SUMINISTRO",$G43))," - "&$AK$13,IF(ISNUMBER(SEARCH("MONTAJE",$G43))," - "&$AK$12,""))) -> Pruebas de tuberías | Q43: En alcance | R43: {=IF($G43="","",IFERROR(VLOOKUP(LOOKUP(2,1/(($B$14:$B43<>"")*($C$14:$C43="")),$B$14:$B43),$AM$12:$AN$16,2,FALSE),""))} -> Mecanica | S43: 1 | T43: Glb. | U43: =+APU!K343 -> 890.9616 | V43: =U43*S43 -> 890.9616 | AB43: {=IF($S43="","",SUMIFS(APU!$O:$O,APU!$A:$A,IF(ISNUMBER($C43),REPLACE(TEXT($C43,"0.0000"),5,0,"."),$C43),APU!$G:$G,"hh")/MAX(1,SUMPRODUCT(($C$15:$C$262=$C43)*($S$15:$S$262<>""))))} -> 67.2 | AC43: =IF($S43="","",IFERROR(VLOOKUP($AE43,APU!$V:$X,2,FALSE),"")) -> 0.25 | AD43: =IF(OR($S43="",$AC43="",N($AC43)=0),"",$S43/$AC43) -> 4 | AE43: =IF($C43="","",IF(ISNUMBER($C43),REPLACE(TEXT($C43,"0.0000"),5,0,"."),$C43)) -> 3.01.03 | AH43: =IF($S43="","",$AB43*N($AG43)) -> 0 | AI43: =IF($S43="","",$AE43&IF(TRIM($N43)="",""," | "&TRIM($N43))&IF(OR(TRIM($O43)="",TRIM($O43)="-"),""," | "&TRIM($O43))) -> 3.01.03 | -
B44: 8.3.2 | C44: =+C40+0.01 -> 3.02 | D44: - | E44: - | F44: - | G44: Acero de Refuerzo (ASTM A-615 G 60, fy = 420 MPa) | P44: =IF(TRIM($G44)="","",TRIM($G44)&IF(OR(TRIM($N44)="",TRIM($N44)="-"),""," - "&TRIM($N44))&IF(OR(TRIM($O44)="",TRIM($O44)="-"),""," - "&TRIM($O44))&IF(ISNUMBER(SEARCH("SUMINISTRO",$G44))," - "&$AK$13,IF(ISNUMBER(SEARCH("MONTAJE",$G44))," - "&$AK$12,""))) -> Acero de Refuerzo (ASTM A-615 G 60, fy = 420 MPa) | Q44: En alcance | R44: {=IF($G44="","",IFERROR(VLOOKUP(LOOKUP(2,1/(($B$14:$B44<>"")*($C$14:$C44="")),$B$14:$B44),$AM$12:$AN$16,2,FALSE),""))} -> Mecanica | AB44: {=IF($S44="","",SUMIFS(APU!$O:$O,APU!$A:$A,IF(ISNUMBER($C44),REPLACE(TEXT($C44,"0.0000"),5,0,"."),$C44),APU!$G:$G,"hh")/MAX(1,SUMPRODUCT(($C$15:$C$262=$C44)*($S$15:$S$262<>""))))} | AC44: =IF($S44="","",IFERROR(VLOOKUP($AE44,APU!$V:$X,2,FALSE),"")) | AD44: =IF(OR($S44="",$AC44="",N($AC44)=0),"",$S44/$AC44) | AE44: =IF($C44="","",IF(ISNUMBER($C44),REPLACE(TEXT($C44,"0.0000"),5,0,"."),$C44)) -> 3.02.00 | AH44: =IF($S44="","",$AB44*N($AG44)) | AI44: =IF($S44="","",$AE44&IF(TRIM($N44)="",""," | "&TRIM($N44))&IF(OR(TRIM($O44)="",TRIM($O44)="-"),""," | "&TRIM($O44)))
B45: 8.3.2 | C45: 3.02.01 | D45: - | E45: - | F45: - | G45: Desmontaje y traslado de bombas existentes | N45: - | O45: - | P45: =IF(TRIM($G45)="","",TRIM($G45)&IF(OR(TRIM($N45)="",TRIM($N45)="-"),""," - "&TRIM($N45))&IF(OR(TRIM($O45)="",TRIM($O45)="-"),""," - "&TRIM($O45))) -> Desmontaje y traslado de bombas existentes | Q45: En alcance | R45: {=IF($G45="","",IFERROR(VLOOKUP(LOOKUP(2,1/(($B$14:$B45<>"")*($C$14:$C45="")),$B$14:$B45),$AM$12:$AN$16,2,FALSE),""))} -> Mecanica | S45: 4 | T45: UND | U45: =+APU!K359 -> 434.0648 | V45: =U45*S45 -> 1736.2592 | AB45: {=IF($S45="","",SUMIFS(APU!$O:$O,APU!$A:$A,IF(ISNUMBER($C45),REPLACE(TEXT($C45,"0.0000"),5,0,"."),$C45),APU!$G:$G,"hh")/MAX(1,SUMPRODUCT(($C$15:$C$262=$C45)*($S$15:$S$262<>""))))} -> 198.4 | AC45: =IF($S45="","",IFERROR(VLOOKUP($AE45,APU!$V:$X,2,FALSE),"")) -> 0.5 | AD45: =IF(OR($S45="",$AC45="",N($AC45)=0),"",$S45/$AC45) -> 8 | AE45: =IF($C45="","",IF(ISNUMBER($C45),REPLACE(TEXT($C45,"0.0000"),5,0,"."),$C45)) -> 3.02.01 | AH45: =IF($S45="","",$AB45*N($AG45)) -> 0 | AI45: =IF($S45="","",$AE45&IF(TRIM($N45)="",""," | "&TRIM($N45))&IF(OR(TRIM($O45)="",TRIM($O45)="-"),""," | "&TRIM($O45))) -> 3.02.01 | -
B46: 8.3.3 | C46: 3.03 | D46: - | E46: - | F46: - | G46: DESMONTAJE DE TUBERÍAS Y ACCESORIOS EXISTENTES | P46: =IF(TRIM($G46)="","",TRIM($G46)&IF(OR(TRIM($N46)="",TRIM($N46)="-"),""," - "&TRIM($N46))&IF(OR(TRIM($O46)="",TRIM($O46)="-"),""," - "&TRIM($O46))) -> DESMONTAJE DE TUBERÍAS Y ACCESORIOS EXISTENTES | Q46: En alcance | R46: {=IF($G46="","",IFERROR(VLOOKUP(LOOKUP(2,1/(($B$14:$B46<>"")*($C$14:$C46="")),$B$14:$B46),$AM$12:$AN$16,2,FALSE),""))} -> Mecanica | AB46: {=IF($S46="","",SUMIFS(APU!$O:$O,APU!$A:$A,IF(ISNUMBER($C46),REPLACE(TEXT($C46,"0.0000"),5,0,"."),$C46),APU!$G:$G,"hh")/MAX(1,SUMPRODUCT(($C$15:$C$262=$C46)*($S$15:$S$262<>""))))} | AC46: =IF($S46="","",IFERROR(VLOOKUP($AE46,APU!$V:$X,2,FALSE),"")) | AD46: =IF(OR($S46="",$AC46="",N($AC46)=0),"",$S46/$AC46) | AE46: =IF($C46="","",IF(ISNUMBER($C46),REPLACE(TEXT($C46,"0.0000"),5,0,"."),$C46)) -> 3.03.00 | AH46: =IF($S46="","",$AB46*N($AG46)) | AI46: =IF($S46="","",$AE46&IF(TRIM($N46)="",""," | "&TRIM($N46))&IF(OR(TRIM($O46)="",TRIM($O46)="-"),""," | "&TRIM($O46)))
B47: 8.3.3 | C47: 3.03.01 | D47: - | E47: - | F47: - | G47: Desmontaje y traslado de tuberías y accesorios existentes | N47: - | O47: - | P47: =IF(TRIM($G47)="","",TRIM($G47)&IF(OR(TRIM($N47)="",TRIM($N47)="-"),""," - "&TRIM($N47))&IF(OR(TRIM($O47)="",TRIM($O47)="-"),""," - "&TRIM($O47))) -> Desmontaje y traslado de tuberías y accesorios existentes | Q47: En alcance | R47: {=IF($G47="","",IFERROR(VLOOKUP(LOOKUP(2,1/(($B$14:$B47<>"")*($C$14:$C47="")),$B$14:$B47),$AM$12:$AN$16,2,FALSE),""))} -> Mecanica | S47: 1 | T47: Glb. | U47: =+APU!K375 -> 1074.936 | V47: =U47*S47 -> 1074.936 | AB47: {=IF($S47="","",SUMIFS(APU!$O:$O,APU!$A:$A,IF(ISNUMBER($C47),REPLACE(TEXT($C47,"0.0000"),5,0,"."),$C47),APU!$G:$G,"hh")/MAX(1,SUMPRODUCT(($C$15:$C$262=$C47)*($S$15:$S$262<>""))))} -> 112 | AC47: =IF($S47="","",IFERROR(VLOOKUP($AE47,APU!$V:$X,2,FALSE),"")) -> 0.15 | AD47: =IF(OR($S47="",$AC47="",N($AC47)=0),"",$S47/$AC47) -> 6.6666667 | AE47: =IF($C47="","",IF(ISNUMBER($C47),REPLACE(TEXT($C47,"0.0000"),5,0,"."),$C47)) -> 3.03.01 | AH47: =IF($S47="","",$AB47*N($AG47)) -> 0 | AI47: =IF($S47="","",$AE47&IF(TRIM($N47)="",""," | "&TRIM($N47))&IF(OR(TRIM($O47)="",TRIM($O47)="-"),""," | "&TRIM($O47))) -> 3.03.01 | -
B48: 8.3.4 | C48: 3.04 | D48: - | E48: - | F48: - | G48: MONTAJE E INSTALACIÓN DE BOMBAS DE DOSIFICACIÓN DE FLOCULANTE | P48: =IF(TRIM($G48)="","",TRIM($G48)&IF(OR(TRIM($N48)="",TRIM($N48)="-"),""," - "&TRIM($N48))&IF(OR(TRIM($O48)="",TRIM($O48)="-"),""," - "&TRIM($O48))) -> MONTAJE E INSTALACIÓN DE BOMBAS DE DOSIFICACIÓN DE FLOCULANTE | Q48: En alcance | R48: {=IF($G48="","",IFERROR(VLOOKUP(LOOKUP(2,1/(($B$14:$B48<>"")*($C$14:$C48="")),$B$14:$B48),$AM$12:$AN$16,2,FALSE),""))} -> Mecanica | AB48: {=IF($S48="","",SUMIFS(APU!$O:$O,APU!$A:$A,IF(ISNUMBER($C48),REPLACE(TEXT($C48,"0.0000"),5,0,"."),$C48),APU!$G:$G,"hh")/MAX(1,SUMPRODUCT(($C$15:$C$262=$C48)*($S$15:$S$262<>""))))} | AC48: =IF($S48="","",IFERROR(VLOOKUP($AE48,APU!$V:$X,2,FALSE),"")) | AD48: =IF(OR($S48="",$AC48="",N($AC48)=0),"",$S48/$AC48) | AE48: =IF($C48="","",IF(ISNUMBER($C48),REPLACE(TEXT($C48,"0.0000"),5,0,"."),$C48)) -> 3.04.00 | AH48: =IF($S48="","",$AB48*N($AG48)) | AI48: =IF($S48="","",$AE48&IF(TRIM($N48)="",""," | "&TRIM($N48))&IF(OR(TRIM($O48)="",TRIM($O48)="-"),""," | "&TRIM($O48)))
B49: 8.3.4 | C49: 3.04.01 | D49: - | E49: - | F49: - | G49: Montaje e instalación de bomba 1760-PU-33101 | N49: - | O49: - | P49: =IF(TRIM($G49)="","",TRIM($G49)&IF(OR(TRIM($N49)="",TRIM($N49)="-"),""," - "&TRIM($N49))&IF(OR(TRIM($O49)="",TRIM($O49)="-"),""," - "&TRIM($O49))&IF(ISNUMBER(SEARCH("SUMINISTRO",$G49))," - "&$AK$13,IF(ISNUMBER(SEARCH("MONTAJE",$G49))," - "&$AK$12,""))) -> Montaje e instalación de bomba 1760-PU-33101 - Suministro MY | Q49: En alcance | R49: {=IF($G49="","",IFERROR(VLOOKUP(LOOKUP(2,1/(($B$14:$B49<>"")*($C$14:$C49="")),$B$14:$B49),$AM$12:$AN$16,2,FALSE),""))} -> Mecanica | S49: 1 | T49: UND | U49: =+APU!K392 -> 356.2524 | V49: =U49*S49 -> 356.2524 | AB49: {=IF($S49="","",SUMIFS(APU!$O:$O,APU!$A:$A,IF(ISNUMBER($C49),REPLACE(TEXT($C49,"0.0000"),5,0,"."),$C49),APU!$G:$G,"hh")/MAX(1,SUMPRODUCT(($C$15:$C$262=$C49)*($S$15:$S$262<>""))))} -> 32.8 | AC49: =IF($S49="","",IFERROR(VLOOKUP($AE49,APU!$V:$X,2,FALSE),"")) -> 1 | AD49: =IF(OR($S49="",$AC49="",N($AC49)=0),"",$S49/$AC49) -> 1 | AE49: =IF($C49="","",IF(ISNUMBER($C49),REPLACE(TEXT($C49,"0.0000"),5,0,"."),$C49)) -> 3.04.01 | AH49: =IF($S49="","",$AB49*N($AG49)) -> 0 | AI49: =IF($S49="","",$AE49&IF(TRIM($N49)="",""," | "&TRIM($N49))&IF(OR(TRIM($O49)="",TRIM($O49)="-"),""," | "&TRIM($O49))) -> 3.04.01 | -
B50: 8.3.4 | C50: 3.04.02 | D50: - | E50: - | F50: - | G50: Montaje e instalación de bomba 1760-PU-33102 | N50: - | O50: - | P50: =IF(TRIM($G50)="","",TRIM($G50)&IF(OR(TRIM($N50)="",TRIM($N50)="-"),""," - "&TRIM($N50))&IF(OR(TRIM($O50)="",TRIM($O50)="-"),""," - "&TRIM($O50))&IF(ISNUMBER(SEARCH("SUMINISTRO",$G50))," - "&$AK$13,IF(ISNUMBER(SEARCH("MONTAJE",$G50))," - "&$AK$12,""))) -> Montaje e instalación de bomba 1760-PU-33102 - Suministro MY | Q50: En alcance | R50: {=IF($G50="","",IFERROR(VLOOKUP(LOOKUP(2,1/(($B$14:$B50<>"")*($C$14:$C50="")),$B$14:$B50),$AM$12:$AN$16,2,FALSE),""))} -> Mecanica | S50: 1 | T50: UND | U50: =+APU!K409 -> 356.2524 | V50: =U50*S50 -> 356.2524 | AB50: {=IF($S50="","",SUMIFS(APU!$O:$O,APU!$A:$A,IF(ISNUMBER($C50),REPLACE(TEXT($C50,"0.0000"),5,0,"."),$C50),APU!$G:$G,"hh")/MAX(1,SUMPRODUCT(($C$15:$C$262=$C50)*($S$15:$S$262<>""))))} -> 32.8 | AC50: =IF($S50="","",IFERROR(VLOOKUP($AE50,APU!$V:$X,2,FALSE),"")) -> 1 | AD50: =IF(OR($S50="",$AC50="",N($AC50)=0),"",$S50/$AC50) -> 1 | AE50: =IF($C50="","",IF(ISNUMBER($C50),REPLACE(TEXT($C50,"0.0000"),5,0,"."),$C50)) -> 3.04.02 | AH50: =IF($S50="","",$AB50*N($AG50)) -> 0 | AI50: =IF($S50="","",$AE50&IF(TRIM($N50)="",""," | "&TRIM($N50))&IF(OR(TRIM($O50)="",TRIM($O50)="-"),""," | "&TRIM($O50))) -> 3.04.02 | -
B51: 8.3.4 | C51: 3.04.03 | D51: - | E51: - | F51: - | G51: Montaje e instalación de bomba 1760-PU-33103 | N51: - | O51: - | P51: =IF(TRIM($G51)="","",TRIM($G51)&IF(OR(TRIM($N51)="",TRIM($N51)="-"),""," - "&TRIM($N51))&IF(OR(TRIM($O51)="",TRIM($O51)="-"),""," - "&TRIM($O51))&IF(ISNUMBER(SEARCH("SUMINISTRO",$G51))," - "&$AK$13,IF(ISNUMBER(SEARCH("MONTAJE",$G51))," - "&$AK$12,""))) -> Montaje e instalación de bomba 1760-PU-33103 - Suministro MY | Q51: En alcance | R51: {=IF($G51="","",IFERROR(VLOOKUP(LOOKUP(2,1/(($B$14:$B51<>"")*($C$14:$C51="")),$B$14:$B51),$AM$12:$AN$16,2,FALSE),""))} -> Mecanica | S51: 1 | T51: UND | U51: =+APU!K426 -> 356.2524 | V51: =U51*S51 -> 356.2524 | AB51: {=IF($S51="","",SUMIFS(APU!$O:$O,APU!$A:$A,IF(ISNUMBER($C51),REPLACE(TEXT($C51,"0.0000"),5,0,"."),$C51),APU!$G:$G,"hh")/MAX(1,SUMPRODUCT(($C$15:$C$262=$C51)*($S$15:$S$262<>""))))} -> 32.8 | AC51: =IF($S51="","",IFERROR(VLOOKUP($AE51,APU!$V:$X,2,FALSE),"")) -> 1 | AD51: =IF(OR($S51="",$AC51="",N($AC51)=0),"",$S51/$AC51) -> 1 | AE51: =IF($C51="","",IF(ISNUMBER($C51),REPLACE(TEXT($C51,"0.0000"),5,0,"."),$C51)) -> 3.04.03 | AH51: =IF($S51="","",$AB51*N($AG51)) -> 0 | AI51: =IF($S51="","",$AE51&IF(TRIM($N51)="",""," | "&TRIM($N51))&IF(OR(TRIM($O51)="",TRIM($O51)="-"),""," | "&TRIM($O51))) -> 3.04.03 | -
B52: 8.3.4 | C52: 3.04.04 | D52: - | E52: - | F52: - | G52: Montaje e instalación de bomba 1760-PU-33104 | N52: - | O52: - | P52: =IF(TRIM($G52)="","",TRIM($G52)&IF(OR(TRIM($N52)="",TRIM($N52)="-"),""," - "&TRIM($N52))&IF(OR(TRIM($O52)="",TRIM($O52)="-"),""," - "&TRIM($O52))&IF(ISNUMBER(SEARCH("SUMINISTRO",$G52))," - "&$AK$13,IF(ISNUMBER(SEARCH("MONTAJE",$G52))," - "&$AK$12,""))) -> Montaje e instalación de bomba 1760-PU-33104 - Suministro MY | Q52: En alcance | R52: {=IF($G52="","",IFERROR(VLOOKUP(LOOKUP(2,1/(($B$14:$B52<>"")*($C$14:$C52="")),$B$14:$B52),$AM$12:$AN$16,2,FALSE),""))} -> Mecanica | S52: 1 | T52: UND | U52: =+APU!K443 -> 356.2524 | V52: =U52*S52 -> 356.2524 | AB52: {=IF($S52="","",SUMIFS(APU!$O:$O,APU!$A:$A,IF(ISNUMBER($C52),REPLACE(TEXT($C52,"0.0000"),5,0,"."),$C52),APU!$G:$G,"hh")/MAX(1,SUMPRODUCT(($C$15:$C$262=$C52)*($S$15:$S$262<>""))))} -> 32.8 | AC52: =IF($S52="","",IFERROR(VLOOKUP($AE52,APU!$V:$X,2,FALSE),"")) -> 1 | AD52: =IF(OR($S52="",$AC52="",N($AC52)=0),"",$S52/$AC52) -> 1 | AE52: =IF($C52="","",IF(ISNUMBER($C52),REPLACE(TEXT($C52,"0.0000"),5,0,"."),$C52)) -> 3.04.04 | AH52: =IF($S52="","",$AB52*N($AG52)) -> 0 | AI52: =IF($S52="","",$AE52&IF(TRIM($N52)="",""," | "&TRIM($N52))&IF(OR(TRIM($O52)="",TRIM($O52)="-"),""," | "&TRIM($O52))) -> 3.04.04 | -
B53: 8.3.4 | C53: 3.04.05 | D53: - | E53: - | F53: - | G53: Montaje e instalación de bomba 1760-PU-33105 | N53: - | O53: - | P53: =IF(TRIM($G53)="","",TRIM($G53)&IF(OR(TRIM($N53)="",TRIM($N53)="-"),""," - "&TRIM($N53))&IF(OR(TRIM($O53)="",TRIM($O53)="-"),""," - "&TRIM($O53))&IF(ISNUMBER(SEARCH("SUMINISTRO",$G53))," - "&$AK$13,IF(ISNUMBER(SEARCH("MONTAJE",$G53))," - "&$AK$12,""))) -> Montaje e instalación de bomba 1760-PU-33105 - Suministro MY | Q53: En alcance | R53: {=IF($G53="","",IFERROR(VLOOKUP(LOOKUP(2,1/(($B$14:$B53<>"")*($C$14:$C53="")),$B$14:$B53),$AM$12:$AN$16,2,FALSE),""))} -> Mecanica | S53: 1 | T53: UND | U53: =+APU!K460 -> 356.2524 | V53: =U53*S53 -> 356.2524 | AB53: {=IF($S53="","",SUMIFS(APU!$O:$O,APU!$A:$A,IF(ISNUMBER($C53),REPLACE(TEXT($C53,"0.0000"),5,0,"."),$C53),APU!$G:$G,"hh")/MAX(1,SUMPRODUCT(($C$15:$C$262=$C53)*($S$15:$S$262<>""))))} -> 32.8 | AC53: =IF($S53="","",IFERROR(VLOOKUP($AE53,APU!$V:$X,2,FALSE),"")) -> 1 | AD53: =IF(OR($S53="",$AC53="",N($AC53)=0),"",$S53/$AC53) -> 1 | AE53: =IF($C53="","",IF(ISNUMBER($C53),REPLACE(TEXT($C53,"0.0000"),5,0,"."),$C53)) -> 3.04.05 | AH53: =IF($S53="","",$AB53*N($AG53)) -> 0 | AI53: =IF($S53="","",$AE53&IF(TRIM($N53)="",""," | "&TRIM($N53))&IF(OR(TRIM($O53)="",TRIM($O53)="-"),""," | "&TRIM($O53))) -> 3.04.05 | -
B54: 8.3.5 | C54: 3.05 | D54: - | E54: - | F54: - | G54: MONTAJE E INSTALACIÓN DE BOMBAS PARA AGUA DE DILUCIÓN | P54: =IF(TRIM($G54)="","",TRIM($G54)&IF(OR(TRIM($N54)="",TRIM($N54)="-"),""," - "&TRIM($N54))&IF(OR(TRIM($O54)="",TRIM($O54)="-"),""," - "&TRIM($O54))) -> MONTAJE E INSTALACIÓN DE BOMBAS PARA AGUA DE DILUCIÓN | Q54: En alcance | R54: {=IF($G54="","",IFERROR(VLOOKUP(LOOKUP(2,1/(($B$14:$B54<>"")*($C$14:$C54="")),$B$14:$B54),$AM$12:$AN$16,2,FALSE),""))} -> Mecanica | V54: =U54*S54 -> 0 | AB54: {=IF($S54="","",SUMIFS(APU!$O:$O,APU!$A:$A,IF(ISNUMBER($C54),REPLACE(TEXT($C54,"0.0000"),5,0,"."),$C54),APU!$G:$G,"hh")/MAX(1,SUMPRODUCT(($C$15:$C$262=$C54)*($S$15:$S$262<>""))))} | AC54: =IF($S54="","",IFERROR(VLOOKUP($AE54,APU!$V:$X,2,FALSE),"")) | AD54: =IF(OR($S54="",$AC54="",N($AC54)=0),"",$S54/$AC54) | AE54: =IF($C54="","",IF(ISNUMBER($C54),REPLACE(TEXT($C54,"0.0000"),5,0,"."),$C54)) -> 3.05.00 | AH54: =IF($S54="","",$AB54*N($AG54)) | AI54: =IF($S54="","",$AE54&IF(TRIM($N54)="",""," | "&TRIM($N54))&IF(OR(TRIM($O54)="",TRIM($O54)="-"),""," | "&TRIM($O54)))
B55: 8.3.5 | C55: 3.05.01 | D55: - | E55: - | F55: - | G55: Montaje e instalación de bomba 1760-PU-33001 | N55: - | O55: - | P55: =IF(TRIM($G55)="","",TRIM($G55)&IF(OR(TRIM($N55)="",TRIM($N55)="-"),""," - "&TRIM($N55))&IF(OR(TRIM($O55)="",TRIM($O55)="-"),""," - "&TRIM($O55))&IF(ISNUMBER(SEARCH("SUMINISTRO",$G55))," - "&$AK$13,IF(ISNUMBER(SEARCH("MONTAJE",$G55))," - "&$AK$12,""))) -> Montaje e instalación de bomba 1760-PU-33001 - Suministro MY | Q55: En alcance | R55: {=IF($G55="","",IFERROR(VLOOKUP(LOOKUP(2,1/(($B$14:$B55<>"")*($C$14:$C55="")),$B$14:$B55),$AM$12:$AN$16,2,FALSE),""))} -> Mecanica | S55: 1 | T55: UND | U55: =+APU!K478 -> 356.2524 | V55: =U55*S55 -> 356.2524 | AB55: {=IF($S55="","",SUMIFS(APU!$O:$O,APU!$A:$A,IF(ISNUMBER($C55),REPLACE(TEXT($C55,"0.0000"),5,0,"."),$C55),APU!$G:$G,"hh")/MAX(1,SUMPRODUCT(($C$15:$C$262=$C55)*($S$15:$S$262<>""))))} -> 32.8 | AC55: =IF($S55="","",IFERROR(VLOOKUP($AE55,APU!$V:$X,2,FALSE),"")) -> 1 | AD55: =IF(OR($S55="",$AC55="",N($AC55)=0),"",$S55/$AC55) -> 1 | AE55: =IF($C55="","",IF(ISNUMBER($C55),REPLACE(TEXT($C55,"0.0000"),5,0,"."),$C55)) -> 3.05.01 | AH55: =IF($S55="","",$AB55*N($AG55)) -> 0 | AI55: =IF($S55="","",$AE55&IF(TRIM($N55)="",""," | "&TRIM($N55))&IF(OR(TRIM($O55)="",TRIM($O55)="-"),""," | "&TRIM($O55))) -> 3.05.01 | -
B56: 8.3.5 | C56: 3.05.02 | D56: - | E56: - | F56: - | G56: Montaje e instalación de bomba 1760-PU-33002 | N56: - | O56: - | P56: =IF(TRIM($G56)="","",TRIM($G56)&IF(OR(TRIM($N56)="",TRIM($N56)="-"),""," - "&TRIM($N56))&IF(OR(TRIM($O56)="",TRIM($O56)="-"),""," - "&TRIM($O56))&IF(ISNUMBER(SEARCH("SUMINISTRO",$G56))," - "&$AK$13,IF(ISNUMBER(SEARCH("MONTAJE",$G56))," - "&$AK$12,""))) -> Montaje e instalación de bomba 1760-PU-33002 - Suministro MY | Q56: En alcance | R56: {=IF($G56="","",IFERROR(VLOOKUP(LOOKUP(2,1/(($B$14:$B56<>"")*($C$14:$C56="")),$B$14:$B56),$AM$12:$AN$16,2,FALSE),""))} -> Mecanica | S56: 1 | T56: UND | U56: =+APU!K495 -> 356.2524 | V56: =U56*S56 -> 356.2524 | AB56: {=IF($S56="","",SUMIFS(APU!$O:$O,APU!$A:$A,IF(ISNUMBER($C56),REPLACE(TEXT($C56,"0.0000"),5,0,"."),$C56),APU!$G:$G,"hh")/MAX(1,SUMPRODUCT(($C$15:$C$262=$C56)*($S$15:$S$262<>""))))} -> 32.8 | AC56: =IF($S56="","",IFERROR(VLOOKUP($AE56,APU!$V:$X,2,FALSE),"")) -> 1 | AD56: =IF(OR($S56="",$AC56="",N($AC56)=0),"",$S56/$AC56) -> 1 | AE56: =IF($C56="","",IF(ISNUMBER($C56),REPLACE(TEXT($C56,"0.0000"),5,0,"."),$C56)) -> 3.05.02 | AH56: =IF($S56="","",$AB56*N($AG56)) -> 0 | AI56: =IF($S56="","",$AE56&IF(TRIM($N56)="",""," | "&TRIM($N56))&IF(OR(TRIM($O56)="",TRIM($O56)="-"),""," | "&TRIM($O56))) -> 3.05.02 | -
B57: 8.3.6 | C57: 3.06 | D57: - | E57: - | F57: - | G57: MONTAJE DE TUBERÍAS Y ACCESORIOS - SISTEMA DE FLOCULANTE Y DILUCIÓN | P57: =IF(TRIM($G57)="","",TRIM($G57)&IF(OR(TRIM($N57)="",TRIM($N57)="-"),""," - "&TRIM($N57))&IF(OR(TRIM($O57)="",TRIM($O57)="-"),""," - "&TRIM($O57))) -> MONTAJE DE TUBERÍAS Y ACCESORIOS - SISTEMA DE FLOCULANTE Y DILUCIÓN | Q57: En alcance | R57: {=IF($G57="","",IFERROR(VLOOKUP(LOOKUP(2,1/(($B$14:$B57<>"")*($C$14:$C57="")),$B$14:$B57),$AM$12:$AN$16,2,FALSE),""))} -> Mecanica | AB57: {=IF($S57="","",SUMIFS(APU!$O:$O,APU!$A:$A,IF(ISNUMBER($C57),REPLACE(TEXT($C57,"0.0000"),5,0,"."),$C57),APU!$G:$G,"hh")/MAX(1,SUMPRODUCT(($C$15:$C$262=$C57)*($S$15:$S$262<>""))))} | AC57: =IF($S57="","",IFERROR(VLOOKUP($AE57,APU!$V:$X,2,FALSE),"")) | AD57: =IF(OR($S57="",$AC57="",N($AC57)=0),"",$S57/$AC57) | AE57: =IF($C57="","",IF(ISNUMBER($C57),REPLACE(TEXT($C57,"0.0000"),5,0,"."),$C57)) -> 3.06.00 | AH57: =IF($S57="","",$AB57*N($AG57)) | AI57: =IF($S57="","",$AE57&IF(TRIM($N57)="",""," | "&TRIM($N57))&IF(OR(TRIM($O57)="",TRIM($O57)="-"),""," | "&TRIM($O57)))
G58: MATERIALES ENTREGADOS POR YANACOCHA | AB58: {=IF($S58="","",SUMIFS(APU!$O:$O,APU!$A:$A,IF(ISNUMBER($C58),REPLACE(TEXT($C58,"0.0000"),5,0,"."),$C58),APU!$G:$G,"hh")/MAX(1,SUMPRODUCT(($C$15:$C$262=$C58)*($S$15:$S$262<>""))))} | AC58: =IF($S58="","",IFERROR(VLOOKUP($AE58,APU!$V:$X,2,FALSE),"")) | AD58: =IF(OR($S58="",$AC58="",N($AC58)=0),"",$S58/$AC58) | AE58: =IF($C58="","",IF(ISNUMBER($C58),REPLACE(TEXT($C58,"0.0000"),5,0,"."),$C58)) | AH58: =IF($S58="","",$AB58*N($AG58)) | AI58: =IF($S58="","",$AE58&IF(TRIM($N58)="",""," | "&TRIM($N58))&IF(OR(TRIM($O58)="",TRIM($O58)="-"),""," | "&TRIM($O58)))
B59: 8.3.6 | C59: 3.06.01 | D59: - | E59: - | F59: - | G59: =+"MONTAJE DE "&X59 -> MONTAJE DE PIPE STD WT ERW CS A53-B TYPE E | N59: 3" | O59: AA1B | P59: =IF(TRIM($G59)="","",TRIM($G59)&IF(OR(TRIM($N59)="",TRIM($N59)="-"),""," - "&TRIM($N59))&IF(OR(TRIM($O59)="",TRIM($O59)="-"),""," - "&TRIM($O59))&IF(ISNUMBER(SEARCH("SUMINISTRO",$G59))," - "&$AK$13,IF(ISNUMBER(SEARCH("MONTAJE",$G59))," - "&$AK$12,""))) -> MONTAJE DE PIPE STD WT ERW CS A53-B TYPE E - 3" - AA1B - Suministro MY | Q59: En alcance | R59: {=IF($G59="","",IFERROR(VLOOKUP(LOOKUP(2,1/(($B$14:$B59<>"")*($C$14:$C59="")),$B$14:$B59),$AM$12:$AN$16,2,FALSE),""))} -> Mecanica | S59: 312 | T59: m | U59: =+APU!K512 -> 28.220627 | V59: =U59*S59 -> 8804.8355 | X59: PIPE STD WT ERW CS A53-B TYPE E | AB59: {=IF($S59="","",SUMIFS(APU!$O:$O,APU!$A:$A,IF(ISNUMBER($C59),REPLACE(TEXT($C59,"0.0000"),5,0,"."),$C59),APU!$G:$G,"hh")/MAX(1,SUMPRODUCT(($C$15:$C$262=$C59)*($S$15:$S$262<>""))))} -> 515.84 | AC59: =IF($S59="","",IFERROR(VLOOKUP($AE59,APU!$V:$X,2,FALSE),"")) -> 15 | AD59: =IF(OR($S59="",$AC59="",N($AC59)=0),"",$S59/$AC59) -> 20.8 | AE59: =IF($C59="","",IF(ISNUMBER($C59),REPLACE(TEXT($C59,"0.0000"),5,0,"."),$C59)) -> 3.06.01 | AH59: =IF($S59="","",$AB59*N($AG59)) -> 0 | AI59: =IF($S59="","",$AE59&IF(TRIM($N59)="",""," | "&TRIM($N59))&IF(OR(TRIM($O59)="",TRIM($O59)="-"),""," | "&TRIM($O59))) -> 3.06.01 | 3" | AA1B
B60: 8.3.6 | C60: 3.06.02 | D60: - | E60: - | F60: - | G60: =+"MONTAJE DE "&X60 -> MONTAJE DE PIPE STD WT ERW CS A53-B TYPE E | N60: 4" | O60: AA1B | P60: =IF(TRIM($G60)="","",TRIM($G60)&IF(OR(TRIM($N60)="",TRIM($N60)="-"),""," - "&TRIM($N60))&IF(OR(TRIM($O60)="",TRIM($O60)="-"),""," - "&TRIM($O60))&IF(ISNUMBER(SEARCH("SUMINISTRO",$G60))," - "&$AK$13,IF(ISNUMBER(SEARCH("MONTAJE",$G60))," - "&$AK$12,""))) -> MONTAJE DE PIPE STD WT ERW CS A53-B TYPE E - 4" - AA1B - Suministro MY | Q60: En alcance | R60: {=IF($G60="","",IFERROR(VLOOKUP(LOOKUP(2,1/(($B$14:$B60<>"")*($C$14:$C60="")),$B$14:$B60),$AM$12:$AN$16,2,FALSE),""))} -> Mecanica | S60: 23.5 | T60: m | U60: =+APU!K533 -> 42.803517 | V60: =U60*S60 -> 1005.8826 | X60: PIPE STD WT ERW CS A53-B TYPE E | AB60: {=IF($S60="","",SUMIFS(APU!$O:$O,APU!$A:$A,IF(ISNUMBER($C60),REPLACE(TEXT($C60,"0.0000"),5,0,"."),$C60),APU!$G:$G,"hh")/MAX(1,SUMPRODUCT(($C$15:$C$262=$C60)*($S$15:$S$262<>""))))} -> 72.85 | AC60: =IF($S60="","",IFERROR(VLOOKUP($AE60,APU!$V:$X,2,FALSE),"")) -> 8 | AD60: =IF(OR($S60="",$AC60="",N($AC60)=0),"",$S60/$AC60) -> 2.9375 | AE60: =IF($C60="","",IF(ISNUMBER($C60),REPLACE(TEXT($C60,"0.0000"),5,0,"."),$C60)) -> 3.06.02 | AH60: =IF($S60="","",$AB60*N($AG60)) -> 0 | AI60: =IF($S60="","",$AE60&IF(TRIM($N60)="",""," | "&TRIM($N60))&IF(OR(TRIM($O60)="",TRIM($O60)="-"),""," | "&TRIM($O60))) -> 3.06.02 | 4" | AA1B
B61: 8.3.6 | C61: 3.06.03 | D61: - | E61: - | F61: - | G61: =+"MONTAJE DE "&X61 -> MONTAJE DE BUTTERFLY 150# CI LUG BUNA-N HNDL OP | N61: 3" | O61: AA1B | P61: =IF(TRIM($G61)="","",TRIM($G61)&IF(OR(TRIM($N61)="",TRIM($N61)="-"),""," - "&TRIM($N61))&IF(OR(TRIM($O61)="",TRIM($O61)="-"),""," - "&TRIM($O61))&IF(ISNUMBER(SEARCH("SUMINISTRO",$G61))," - "&$AK$13,IF(ISNUMBER(SEARCH("MONTAJE",$G61))," - "&$AK$12,""))) -> MONTAJE DE BUTTERFLY 150# CI LUG BUNA-N HNDL OP - 3" - AA1B - Suministro MY | Q61: En alcance | R61: {=IF($G61="","",IFERROR(VLOOKUP(LOOKUP(2,1/(($B$14:$B61<>"")*($C$14:$C61="")),$B$14:$B61),$AM$12:$AN$16,2,FALSE),""))} -> Mecanica | S61: 10 | T61: UND | U61: =+APU!K554 -> 39.1851 | V61: =U61*S61 -> 391.851 | X61: BUTTERFLY 150# CI LUG BUNA-N HNDL OP | AB61: {=IF($S61="","",SUMIFS(APU!$O:$O,APU!$A:$A,IF(ISNUMBER($C61),REPLACE(TEXT($C61,"0.0000"),5,0,"."),$C61),APU!$G:$G,"hh")/MAX(1,SUMPRODUCT(($C$15:$C$262=$C61)*($S$15:$S$262<>""))))} -> 42 | AC61: =IF($S61="","",IFERROR(VLOOKUP($AE61,APU!$V:$X,2,FALSE),"")) -> 4 | AD61: =IF(OR($S61="",$AC61="",N($AC61)=0),"",$S61/$AC61) -> 2.5 | AE61: =IF($C61="","",IF(ISNUMBER($C61),REPLACE(TEXT($C61,"0.0000"),5,0,"."),$C61)) -> 3.06.03 | AH61: =IF($S61="","",$AB61*N($AG61)) -> 0 | AI61: =IF($S61="","",$AE61&IF(TRIM($N61)="",""," | "&TRIM($N61))&IF(OR(TRIM($O61)="",TRIM($O61)="-"),""," | "&TRIM($O61))) -> 3.06.03 | 3" | AA1B
B62: 8.3.6 | C62: 3.06.04 | D62: - | E62: - | F62: - | G62: =+"MONTAJE DE "&X62 -> MONTAJE DE BUTTERFLY 150# CI LUG BUNA-N HNDL OP | N62: 4" | O62: AA1B | P62: =IF(TRIM($G62)="","",TRIM($G62)&IF(OR(TRIM($N62)="",TRIM($N62)="-"),""," - "&TRIM($N62))&IF(OR(TRIM($O62)="",TRIM($O62)="-"),""," - "&TRIM($O62))&IF(ISNUMBER(SEARCH("SUMINISTRO",$G62))," - "&$AK$13,IF(ISNUMBER(SEARCH("MONTAJE",$G62))," - "&$AK$12,""))) -> MONTAJE DE BUTTERFLY 150# CI LUG BUNA-N HNDL OP - 4" - AA1B - Suministro MY | Q62: En alcance | R62: {=IF($G62="","",IFERROR(VLOOKUP(LOOKUP(2,1/(($B$14:$B62<>"")*($C$14:$C62="")),$B$14:$B62),$AM$12:$AN$16,2,FALSE),""))} -> Mecanica | S62: 5 | T62: UND | U62: =+APU!K570 -> 39.1851 | V62: =U62*S62 -> 195.9255 | X62: BUTTERFLY 150# CI LUG BUNA-N HNDL OP | AB62: {=IF($S62="","",SUMIFS(APU!$O:$O,APU!$A:$A,IF(ISNUMBER($C62),REPLACE(TEXT($C62,"0.0000"),5,0,"."),$C62),APU!$G:$G,"hh")/MAX(1,SUMPRODUCT(($C$15:$C$262=$C62)*($S$15:$S$262<>""))))} -> 21 | AC62: =IF($S62="","",IFERROR(VLOOKUP($AE62,APU!$V:$X,2,FALSE),"")) -> 4 | AD62: =IF(OR($S62="",$AC62="",N($AC62)=0),"",$S62/$AC62) -> 1.25 | AE62: =IF($C62="","",IF(ISNUMBER($C62),REPLACE(TEXT($C62,"0.0000"),5,0,"."),$C62)) -> 3.06.04 | AH62: =IF($S62="","",$AB62*N($AG62)) -> 0 | AI62: =IF($S62="","",$AE62&IF(TRIM($N62)="",""," | "&TRIM($N62))&IF(OR(TRIM($O62)="",TRIM($O62)="-"),""," | "&TRIM($O62))) -> 3.06.04 | 4" | AA1B
B63: 8.3.6 | C63: 3.06.05 | D63: - | E63: - | F63: - | G63: =+"MONTAJE DE "&X63 -> MONTAJE DE CHECK 150# RF STL WAFER BUNA-N DUAL PLATE | N63: 3" | O63: AA1B | P63: =IF(TRIM($G63)="","",TRIM($G63)&IF(OR(TRIM($N63)="",TRIM($N63)="-"),""," - "&TRIM($N63))&IF(OR(TRIM($O63)="",TRIM($O63)="-"),""," - "&TRIM($O63))&IF(ISNUMBER(SEARCH("SUMINISTRO",$G63))," - "&$AK$13,IF(ISNUMBER(SEARCH("MONTAJE",$G63))," - "&$AK$12,""))) -> MONTAJE DE CHECK 150# RF STL WAFER BUNA-N DUAL PLATE - 3" - AA1B - Suministro MY | Q63: En alcance | R63: {=IF($G63="","",IFERROR(VLOOKUP(LOOKUP(2,1/(($B$14:$B63<>"")*($C$14:$C63="")),$B$14:$B63),$AM$12:$AN$16,2,FALSE),""))} -> Mecanica | S63: 2 | T63: UND | U63: =+APU!K586 -> 27.1234 | V63: =U63*S63 -> 54.2468 | X63: CHECK 150# RF STL WAFER BUNA-N DUAL PLATE | AB63: {=IF($S63="","",SUMIFS(APU!$O:$O,APU!$A:$A,IF(ISNUMBER($C63),REPLACE(TEXT($C63,"0.0000"),5,0,"."),$C63),APU!$G:$G,"hh")/MAX(1,SUMPRODUCT(($C$15:$C$262=$C63)*($S$15:$S$262<>""))))} -> 5.6 | AC63: =IF($S63="","",IFERROR(VLOOKUP($AE63,APU!$V:$X,2,FALSE),"")) -> 6 | AD63: =IF(OR($S63="",$AC63="",N($AC63)=0),"",$S63/$AC63) -> 0.33333333 | AE63: =IF($C63="","",IF(ISNUMBER($C63),REPLACE(TEXT($C63,"0.0000"),5,0,"."),$C63)) -> 3.06.05 | AH63: =IF($S63="","",$AB63*N($AG63)) -> 0 | AI63: =IF($S63="","",$AE63&IF(TRIM($N63)="",""," | "&TRIM($N63))&IF(OR(TRIM($O63)="",TRIM($O63)="-"),""," | "&TRIM($O63))) -> 3.06.05 | 3" | AA1B
B64: 8.3.6 | C64: 3.06.06 | D64: - | E64: - | F64: - | G64: =+"MONTAJE DE "&X64 -> MONTAJE DE FLG SO 150# RF STL A105 | N64: 3" | O64: AA1B | P64: =IF(TRIM($G64)="","",TRIM($G64)&IF(OR(TRIM($N64)="",TRIM($N64)="-"),""," - "&TRIM($N64))&IF(OR(TRIM($O64)="",TRIM($O64)="-"),""," - "&TRIM($O64))&IF(ISNUMBER(SEARCH("SUMINISTRO",$G64))," - "&$AK$13,IF(ISNUMBER(SEARCH("MONTAJE",$G64))," - "&$AK$12,""))) -> MONTAJE DE FLG SO 150# RF STL A105 - 3" - AA1B - Suministro MY | Q64: En alcance | R64: {=IF($G64="","",IFERROR(VLOOKUP(LOOKUP(2,1/(($B$14:$B64<>"")*($C$14:$C64="")),$B$14:$B64),$AM$12:$AN$16,2,FALSE),""))} -> Mecanica | S64: 27 | T64: UND | U64: =+APU!K602 -> 36.165667 | V64: =U64*S64 -> 976.473 | X64: FLG SO 150# RF STL A105 | AB64: {=IF($S64="","",SUMIFS(APU!$O:$O,APU!$A:$A,IF(ISNUMBER($C64),REPLACE(TEXT($C64,"0.0000"),5,0,"."),$C64),APU!$G:$G,"hh")/MAX(1,SUMPRODUCT(($C$15:$C$262=$C64)*($S$15:$S$262<>""))))} -> 111.6 | AC64: =IF($S64="","",IFERROR(VLOOKUP($AE64,APU!$V:$X,2,FALSE),"")) -> 6 | AD64: =IF(OR($S64="",$AC64="",N($AC64)=0),"",$S64/$AC64) -> 4.5 | AE64: =IF($C64="","",IF(ISNUMBER($C64),REPLACE(TEXT($C64,"0.0000"),5,0,"."),$C64)) -> 3.06.06 | AH64: =IF($S64="","",$AB64*N($AG64)) -> 0 | AI64: =IF($S64="","",$AE64&IF(TRIM($N64)="",""," | "&TRIM($N64))&IF(OR(TRIM($O64)="",TRIM($O64)="-"),""," | "&TRIM($O64))) -> 3.06.06 | 3" | AA1B
B65: 8.3.6 | C65: 3.06.07 | D65: - | E65: - | F65: - | G65: =+"MONTAJE DE "&X65 -> MONTAJE DE FLG SO 150# RF STL A105 | N65: 4" | O65: AA1B | P65: =IF(TRIM($G65)="","",TRIM($G65)&IF(OR(TRIM($N65)="",TRIM($N65)="-"),""," - "&TRIM($N65))&IF(OR(TRIM($O65)="",TRIM($O65)="-"),""," - "&TRIM($O65))&IF(ISNUMBER(SEARCH("SUMINISTRO",$G65))," - "&$AK$13,IF(ISNUMBER(SEARCH("MONTAJE",$G65))," - "&$AK$12,""))) -> MONTAJE DE FLG SO 150# RF STL A105 - 4" - AA1B - Suministro MY | Q65: En alcance | R65: {=IF($G65="","",IFERROR(VLOOKUP(LOOKUP(2,1/(($B$14:$B65<>"")*($C$14:$C65="")),$B$14:$B65),$AM$12:$AN$16,2,FALSE),""))} -> Mecanica | S65: 8 | T65: UND | U65: =+APU!K622 -> 53.832867 | V65: =U65*S65 -> 430.66293 | X65: FLG SO 150# RF STL A105 | AB65: {=IF($S65="","",SUMIFS(APU!$O:$O,APU!$A:$A,IF(ISNUMBER($C65),REPLACE(TEXT($C65,"0.0000"),5,0,"."),$C65),APU!$G:$G,"hh")/MAX(1,SUMPRODUCT(($C$15:$C$262=$C65)*($S$15:$S$262<>""))))} -> 33.066667 | AC65: =IF($S65="","",IFERROR(VLOOKUP($AE65,APU!$V:$X,2,FALSE),"")) -> 6 | AD65: =IF(OR($S65="",$AC65="",N($AC65)=0),"",$S65/$AC65) -> 1.3333333 | AE65: =IF($C65="","",IF(ISNUMBER($C65),REPLACE(TEXT($C65,"0.0000"),5,0,"."),$C65)) -> 3.06.07 | AH65: =IF($S65="","",$AB65*N($AG65)) -> 0 | AI65: =IF($S65="","",$AE65&IF(TRIM($N65)="",""," | "&TRIM($N65))&IF(OR(TRIM($O65)="",TRIM($O65)="-"),""," | "&TRIM($O65))) -> 3.06.07 | 4" | AA1B
B66: 8.3.6 | C66: 3.06.08 | D66: - | E66: - | F66: - | G66: =+"MONTAJE DE "&X66 -> MONTAJE DE FLG BLIND 150# RF STL A105 | N66: 3" | O66: AA1B | P66: =IF(TRIM($G66)="","",TRIM($G66)&IF(OR(TRIM($N66)="",TRIM($N66)="-"),""," - "&TRIM($N66))&IF(OR(TRIM($O66)="",TRIM($O66)="-"),""," - "&TRIM($O66))&IF(ISNUMBER(SEARCH("SUMINISTRO",$G66))," - "&$AK$13,IF(ISNUMBER(SEARCH("MONTAJE",$G66))," - "&$AK$12,""))) -> MONTAJE DE FLG BLIND 150# RF STL A105 - 3" - AA1B - Suministro MY | Q66: En alcance | R66: {=IF($G66="","",IFERROR(VLOOKUP(LOOKUP(2,1/(($B$14:$B66<>"")*($C$14:$C66="")),$B$14:$B66),$AM$12:$AN$16,2,FALSE),""))} -> Mecanica | S66: 3 | T66: UND | U66: =+APU!K642 -> 53.707667 | V66: =U66*S66 -> 161.123 | X66: FLG BLIND 150# RF STL A105 | AB66: {=IF($S66="","",SUMIFS(APU!$O:$O,APU!$A:$A,IF(ISNUMBER($C66),REPLACE(TEXT($C66,"0.0000"),5,0,"."),$C66),APU!$G:$G,"hh")/MAX(1,SUMPRODUCT(($C$15:$C$262=$C66)*($S$15:$S$262<>""))))} -> 12.4 | AC66: =IF($S66="","",IFERROR(VLOOKUP($AE66,APU!$V:$X,2,FALSE),"")) -> 6 | AD66: =IF(OR($S66="",$AC66="",N($AC66)=0),"",$S66/$AC66) -> 0.5 | AE66: =IF($C66="","",IF(ISNUMBER($C66),REPLACE(TEXT($C66,"0.0000"),5,0,"."),$C66)) -> 3.06.08 | AH66: =IF($S66="","",$AB66*N($AG66)) -> 0 | AI66: =IF($S66="","",$AE66&IF(TRIM($N66)="",""," | "&TRIM($N66))&IF(OR(TRIM($O66)="",TRIM($O66)="-"),""," | "&TRIM($O66))) -> 3.06.08 | 3" | AA1B
B67: 8.3.6 | C67: 3.06.09 | D67: - | E67: - | F67: - | G67: =+"MONTAJE DE "&X67 -> MONTAJE DE FLG BLIND 150# RF STL A105 | N67: 4" | O67: AA1B | P67: =IF(TRIM($G67)="","",TRIM($G67)&IF(OR(TRIM($N67)="",TRIM($N67)="-"),""," - "&TRIM($N67))&IF(OR(TRIM($O67)="",TRIM($O67)="-"),""," - "&TRIM($O67))&IF(ISNUMBER(SEARCH("SUMINISTRO",$G67))," - "&$AK$13,IF(ISNUMBER(SEARCH("MONTAJE",$G67))," - "&$AK$12,""))) -> MONTAJE DE FLG BLIND 150# RF STL A105 - 4" - AA1B - Suministro MY | Q67: En alcance | R67: {=IF($G67="","",IFERROR(VLOOKUP(LOOKUP(2,1/(($B$14:$B67<>"")*($C$14:$C67="")),$B$14:$B67),$AM$12:$AN$16,2,FALSE),""))} -> Mecanica | S67: 1 | T67: UND | U67: =+APU!K662 -> 53.832867 | V67: =U67*S67 -> 53.832867 | X67: FLG BLIND 150# RF STL A105 | AB67: {=IF($S67="","",SUMIFS(APU!$O:$O,APU!$A:$A,IF(ISNUMBER($C67),REPLACE(TEXT($C67,"0.0000"),5,0,"."),$C67),APU!$G:$G,"hh")/MAX(1,SUMPRODUCT(($C$15:$C$262=$C67)*($S$15:$S$262<>""))))} -> 4.1333333 | AC67: =IF($S67="","",IFERROR(VLOOKUP($AE67,APU!$V:$X,2,FALSE),"")) -> 6 | AD67: =IF(OR($S67="",$AC67="",N($AC67)=0),"",$S67/$AC67) -> 0.16666667 | AE67: =IF($C67="","",IF(ISNUMBER($C67),REPLACE(TEXT($C67,"0.0000"),5,0,"."),$C67)) -> 3.06.09 | AH67: =IF($S67="","",$AB67*N($AG67)) -> 0 | AI67: =IF($S67="","",$AE67&IF(TRIM($N67)="",""," | "&TRIM($N67))&IF(OR(TRIM($O67)="",TRIM($O67)="-"),""," | "&TRIM($O67))) -> 3.06.09 | 4" | AA1B
B68: 8.3.6 | C68: 3.06.10 | D68: - | E68: - | F68: - | G68: =+"MONTAJE DE "&X68 -> MONTAJE DE ELL 90 DEG STD LR WT STL A234 WPB | N68: 3" | O68: AA1B | P68: =IF(TRIM($G68)="","",TRIM($G68)&IF(OR(TRIM($N68)="",TRIM($N68)="-"),""," - "&TRIM($N68))&IF(OR(TRIM($O68)="",TRIM($O68)="-"),""," - "&TRIM($O68))&IF(ISNUMBER(SEARCH("SUMINISTRO",$G68))," - "&$AK$13,IF(ISNUMBER(SEARCH("MONTAJE",$G68))," - "&$AK$12,""))) -> MONTAJE DE ELL 90 DEG STD LR WT STL A234 WPB - 3" - AA1B - Suministro MY | Q68: En alcance | R68: {=IF($G68="","",IFERROR(VLOOKUP(LOOKUP(2,1/(($B$14:$B68<>"")*($C$14:$C68="")),$B$14:$B68),$AM$12:$AN$16,2,FALSE),""))} -> Mecanica | S68: 42 | T68: UND | U68: =+APU!K682 -> 45.579971 | V68: =U68*S68 -> 1914.3588 | X68: ELL 90 DEG STD LR WT STL A234 WPB | AB68: {=IF($S68="","",SUMIFS(APU!$O:$O,APU!$A:$A,IF(ISNUMBER($C68),REPLACE(TEXT($C68,"0.0000"),5,0,"."),$C68),APU!$G:$G,"hh")/MAX(1,SUMPRODUCT(($C$15:$C$262=$C68)*($S$15:$S$262<>""))))} -> 148.8 | AC68: =IF($S68="","",IFERROR(VLOOKUP($AE68,APU!$V:$X,2,FALSE),"")) -> 7 | AD68: =IF(OR($S68="",$AC68="",N($AC68)=0),"",$S68/$AC68) -> 6 | AE68: =IF($C68="","",IF(ISNUMBER($C68),REPLACE(TEXT($C68,"0.0000"),5,0,"."),$C68)) -> 3.06.10 | AH68: =IF($S68="","",$AB68*N($AG68)) -> 0 | AI68: =IF($S68="","",$AE68&IF(TRIM($N68)="",""," | "&TRIM($N68))&IF(OR(TRIM($O68)="",TRIM($O68)="-"),""," | "&TRIM($O68))) -> 3.06.10 | 3" | AA1B
B69: 8.3.6 | C69: 3.06.11 | D69: - | E69: - | F69: - | G69: =+"MONTAJE DE "&X69 -> MONTAJE DE ELL 90 DEG STD LR WT STL A234 WPB | N69: 4" | O69: AA1B | P69: =IF(TRIM($G69)="","",TRIM($G69)&IF(OR(TRIM($N69)="",TRIM($N69)="-"),""," - "&TRIM($N69))&IF(OR(TRIM($O69)="",TRIM($O69)="-"),""," - "&TRIM($O69))&IF(ISNUMBER(SEARCH("SUMINISTRO",$G69))," - "&$AK$13,IF(ISNUMBER(SEARCH("MONTAJE",$G69))," - "&$AK$12,""))) -> MONTAJE DE ELL 90 DEG STD LR WT STL A234 WPB - 4" - AA1B - Suministro MY | Q69: En alcance | R69: {=IF($G69="","",IFERROR(VLOOKUP(LOOKUP(2,1/(($B$14:$B69<>"")*($C$14:$C69="")),$B$14:$B69),$AM$12:$AN$16,2,FALSE),""))} -> Mecanica | S69: 6 | T69: UND | U69: =+APU!K702 -> 45.767771 | V69: =U69*S69 -> 274.60663 | X69: ELL 90 DEG STD LR WT STL A234 WPB | AB69: {=IF($S69="","",SUMIFS(APU!$O:$O,APU!$A:$A,IF(ISNUMBER($C69),REPLACE(TEXT($C69,"0.0000"),5,0,"."),$C69),APU!$G:$G,"hh")/MAX(1,SUMPRODUCT(($C$15:$C$262=$C69)*($S$15:$S$262<>""))))} -> 21.257143 | AC69: =IF($S69="","",IFERROR(VLOOKUP($AE69,APU!$V:$X,2,FALSE),"")) -> 7 | AD69: =IF(OR($S69="",$AC69="",N($AC69)=0),"",$S69/$AC69) -> 0.85714286 | AE69: =IF($C69="","",IF(ISNUMBER($C69),REPLACE(TEXT($C69,"0.0000"),5,0,"."),$C69)) -> 3.06.11 | AH69: =IF($S69="","",$AB69*N($AG69)) -> 0 | AI69: =IF($S69="","",$AE69&IF(TRIM($N69)="",""," | "&TRIM($N69))&IF(OR(TRIM($O69)="",TRIM($O69)="-"),""," | "&TRIM($O69))) -> 3.06.11 | 4" | AA1B
B70: 8.3.6 | C70: 3.06.12 | D70: - | E70: - | F70: - | G70: =+"MONTAJE DE "&X70 -> MONTAJE DE ELL 45 DEG STD WT STL A234 WPB | N70: 3" | O70: AA1B | P70: =IF(TRIM($G70)="","",TRIM($G70)&IF(OR(TRIM($N70)="",TRIM($N70)="-"),""," - "&TRIM($N70))&IF(OR(TRIM($O70)="",TRIM($O70)="-"),""," - "&TRIM($O70))&IF(ISNUMBER(SEARCH("SUMINISTRO",$G70))," - "&$AK$13,IF(ISNUMBER(SEARCH("MONTAJE",$G70))," - "&$AK$12,""))) -> MONTAJE DE ELL 45 DEG STD WT STL A234 WPB - 3" - AA1B - Suministro MY | Q70: En alcance | R70: {=IF($G70="","",IFERROR(VLOOKUP(LOOKUP(2,1/(($B$14:$B70<>"")*($C$14:$C70="")),$B$14:$B70),$AM$12:$AN$16,2,FALSE),""))} -> Mecanica | S70: 3 | T70: UND | U70: =+APU!K722 -> 52.958067 | V70: =U70*S70 -> 158.8742 | X70: ELL 45 DEG STD WT STL A234 WPB | AB70: {=IF($S70="","",SUMIFS(APU!$O:$O,APU!$A:$A,IF(ISNUMBER($C70),REPLACE(TEXT($C70,"0.0000"),5,0,"."),$C70),APU!$G:$G,"hh")/MAX(1,SUMPRODUCT(($C$15:$C$262=$C70)*($S$15:$S$262<>""))))} -> 12.4 | AC70: =IF($S70="","",IFERROR(VLOOKUP($AE70,APU!$V:$X,2,FALSE),"")) -> 6 | AD70: =IF(OR($S70="",$AC70="",N($AC70)=0),"",$S70/$AC70) -> 0.5 | AE70: =IF($C70="","",IF(ISNUMBER($C70),REPLACE(TEXT($C70,"0.0000"),5,0,"."),$C70)) -> 3.06.12 | AH70: =IF($S70="","",$AB70*N($AG70)) -> 0 | AI70: =IF($S70="","",$AE70&IF(TRIM($N70)="",""," | "&TRIM($N70))&IF(OR(TRIM($O70)="",TRIM($O70)="-"),""," | "&TRIM($O70))) -> 3.06.12 | 3" | AA1B
B71: 8.3.6 | C71: 3.06.13 | D71: - | E71: - | F71: - | G71: =+"MONTAJE DE "&X71 -> MONTAJE DE ELL 45 DEG STD WT STL A234 WPB | N71: 4" | O71: AA1B | P71: =IF(TRIM($G71)="","",TRIM($G71)&IF(OR(TRIM($N71)="",TRIM($N71)="-"),""," - "&TRIM($N71))&IF(OR(TRIM($O71)="",TRIM($O71)="-"),""," - "&TRIM($O71))&IF(ISNUMBER(SEARCH("SUMINISTRO",$G71))," - "&$AK$13,IF(ISNUMBER(SEARCH("MONTAJE",$G71))," - "&$AK$12,""))) -> MONTAJE DE ELL 45 DEG STD WT STL A234 WPB - 4" - AA1B - Suministro MY | Q71: En alcance | R71: {=IF($G71="","",IFERROR(VLOOKUP(LOOKUP(2,1/(($B$14:$B71<>"")*($C$14:$C71="")),$B$14:$B71),$AM$12:$AN$16,2,FALSE),""))} -> Mecanica | S71: 4 | T71: UND | U71: =+APU!K742 -> 53.083267 | V71: =U71*S71 -> 212.33307 | X71: ELL 45 DEG STD WT STL A234 WPB | AB71: {=IF($S71="","",SUMIFS(APU!$O:$O,APU!$A:$A,IF(ISNUMBER($C71),REPLACE(TEXT($C71,"0.0000"),5,0,"."),$C71),APU!$G:$G,"hh")/MAX(1,SUMPRODUCT(($C$15:$C$262=$C71)*($S$15:$S$262<>""))))} -> 16.533333 | AC71: =IF($S71="","",IFERROR(VLOOKUP($AE71,APU!$V:$X,2,FALSE),"")) -> 6 | AD71: =IF(OR($S71="",$AC71="",N($AC71)=0),"",$S71/$AC71) -> 0.66666667 | AE71: =IF($C71="","",IF(ISNUMBER($C71),REPLACE(TEXT($C71,"0.0000"),5,0,"."),$C71)) -> 3.06.13 | AH71: =IF($S71="","",$AB71*N($AG71)) -> 0 | AI71: =IF($S71="","",$AE71&IF(TRIM($N71)="",""," | "&TRIM($N71))&IF(OR(TRIM($O71)="",TRIM($O71)="-"),""," | "&TRIM($O71))) -> 3.06.13 | 4" | AA1B
B72: 8.3.6 | C72: 3.06.14 | D72: - | E72: - | F72: - | G72: =+"MONTAJE DE "&X72 -> MONTAJE DE TEE STD WT STL A234 WPB | N72: 3" | O72: AA1B | P72: =IF(TRIM($G72)="","",TRIM($G72)&IF(OR(TRIM($N72)="",TRIM($N72)="-"),""," - "&TRIM($N72))&IF(OR(TRIM($O72)="",TRIM($O72)="-"),""," - "&TRIM($O72))&IF(ISNUMBER(SEARCH("SUMINISTRO",$G72))," - "&$AK$13,IF(ISNUMBER(SEARCH("MONTAJE",$G72))," - "&$AK$12,""))) -> MONTAJE DE TEE STD WT STL A234 WPB - 3" - AA1B - Suministro MY | Q72: En alcance | R72: {=IF($G72="","",IFERROR(VLOOKUP(LOOKUP(2,1/(($B$14:$B72<>"")*($C$14:$C72="")),$B$14:$B72),$AM$12:$AN$16,2,FALSE),""))} -> Mecanica | S72: 6 | T72: UND | U72: =+APU!K762 -> 64.52528 | V72: =U72*S72 -> 387.15168 | X72: TEE STD WT STL A234 WPB | AB72: {=IF($S72="","",SUMIFS(APU!$O:$O,APU!$A:$A,IF(ISNUMBER($C72),REPLACE(TEXT($C72,"0.0000"),5,0,"."),$C72),APU!$G:$G,"hh")/MAX(1,SUMPRODUCT(($C$15:$C$262=$C72)*($S$15:$S$262<>""))))} -> 29.76 | AC72: =IF($S72="","",IFERROR(VLOOKUP($AE72,APU!$V:$X,2,FALSE),"")) -> 5 | AD72: =IF(OR($S72="",$AC72="",N($AC72)=0),"",$S72/$AC72) -> 1.2 | AE72: =IF($C72="","",IF(ISNUMBER($C72),REPLACE(TEXT($C72,"0.0000"),5,0,"."),$C72)) -> 3.06.14 | AH72: =IF($S72="","",$AB72*N($AG72)) -> 0 | AI72: =IF($S72="","",$AE72&IF(TRIM($N72)="",""," | "&TRIM($N72))&IF(OR(TRIM($O72)="",TRIM($O72)="-"),""," | "&TRIM($O72))) -> 3.06.14 | 3" | AA1B
B73: 8.3.6 | C73: 3.06.15 | D73: - | E73: - | F73: - | G73: =+"MONTAJE DE "&X73 -> MONTAJE DE TEE STD WT STL A234 WPB | N73: 4" | O73: AA1B | P73: =IF(TRIM($G73)="","",TRIM($G73)&IF(OR(TRIM($N73)="",TRIM($N73)="-"),""," - "&TRIM($N73))&IF(OR(TRIM($O73)="",TRIM($O73)="-"),""," - "&TRIM($O73))&IF(ISNUMBER(SEARCH("SUMINISTRO",$G73))," - "&$AK$13,IF(ISNUMBER(SEARCH("MONTAJE",$G73))," - "&$AK$12,""))) -> MONTAJE DE TEE STD WT STL A234 WPB - 4" - AA1B - Suministro MY | Q73: En alcance | R73: {=IF($G73="","",IFERROR(VLOOKUP(LOOKUP(2,1/(($B$14:$B73<>"")*($C$14:$C73="")),$B$14:$B73),$AM$12:$AN$16,2,FALSE),""))} -> Mecanica | S73: 2 | T73: UND | U73: =+APU!K782 -> 64.77568 | V73: =U73*S73 -> 129.55136 | X73: TEE STD WT STL A234 WPB | AB73: {=IF($S73="","",SUMIFS(APU!$O:$O,APU!$A:$A,IF(ISNUMBER($C73),REPLACE(TEXT($C73,"0.0000"),5,0,"."),$C73),APU!$G:$G,"hh")/MAX(1,SUMPRODUCT(($C$15:$C$262=$C73)*($S$15:$S$262<>""))))} -> 9.92 | AC73: =IF($S73="","",IFERROR(VLOOKUP($AE73,APU!$V:$X,2,FALSE),"")) -> 5 | AD73: =IF(OR($S73="",$AC73="",N($AC73)=0),"",$S73/$AC73) -> 0.4 | AE73: =IF($C73="","",IF(ISNUMBER($C73),REPLACE(TEXT($C73,"0.0000"),5,0,"."),$C73)) -> 3.06.15 | AH73: =IF($S73="","",$AB73*N($AG73)) -> 0 | AI73: =IF($S73="","",$AE73&IF(TRIM($N73)="",""," | "&TRIM($N73))&IF(OR(TRIM($O73)="",TRIM($O73)="-"),""," | "&TRIM($O73))) -> 3.06.15 | 4" | AA1B
B74: 8.3.6 | C74: 3.06.16 | D74: - | E74: - | F74: - | G74: =+"MONTAJE DE "&X74 -> MONTAJE DE REDUCER ECC STD WT STL A234 WPB | N74: 4" x 3" | O74: AA1B | P74: =IF(TRIM($G74)="","",TRIM($G74)&IF(OR(TRIM($N74)="",TRIM($N74)="-"),""," - "&TRIM($N74))&IF(OR(TRIM($O74)="",TRIM($O74)="-"),""," - "&TRIM($O74))&IF(ISNUMBER(SEARCH("SUMINISTRO",$G74))," - "&$AK$13,IF(ISNUMBER(SEARCH("MONTAJE",$G74))," - "&$AK$12,""))) -> MONTAJE DE REDUCER ECC STD WT STL A234 WPB - 4" x 3" - AA1B - Suministro MY | Q74: En alcance | R74: {=IF($G74="","",IFERROR(VLOOKUP(LOOKUP(2,1/(($B$14:$B74<>"")*($C$14:$C74="")),$B$14:$B74),$AM$12:$AN$16,2,FALSE),""))} -> Mecanica | S74: 2 | T74: UND | U74: =+APU!K802 -> 53.958067 | V74: =U74*S74 -> 107.91613 | X74: REDUCER ECC STD WT STL A234 WPB | AB74: {=IF($S74="","",SUMIFS(APU!$O:$O,APU!$A:$A,IF(ISNUMBER($C74),REPLACE(TEXT($C74,"0.0000"),5,0,"."),$C74),APU!$G:$G,"hh")/MAX(1,SUMPRODUCT(($C$15:$C$262=$C74)*($S$15:$S$262<>""))))} -> 8.2666667 | AC74: =IF($S74="","",IFERROR(VLOOKUP($AE74,APU!$V:$X,2,FALSE),"")) -> 6 | AD74: =IF(OR($S74="",$AC74="",N($AC74)=0),"",$S74/$AC74) -> 0.33333333 | AE74: =IF($C74="","",IF(ISNUMBER($C74),REPLACE(TEXT($C74,"0.0000"),5,0,"."),$C74)) -> 3.06.16 | AH74: =IF($S74="","",$AB74*N($AG74)) -> 0 | AI74: =IF($S74="","",$AE74&IF(TRIM($N74)="",""," | "&TRIM($N74))&IF(OR(TRIM($O74)="",TRIM($O74)="-"),""," | "&TRIM($O74))) -> 3.06.16 | 4" x 3" | AA1B
G75: MATERIALES ENTREGADOS POR EL CONTRATISTA | AB75: {=IF($S75="","",SUMIFS(APU!$O:$O,APU!$A:$A,IF(ISNUMBER($C75),REPLACE(TEXT($C75,"0.0000"),5,0,"."),$C75),APU!$G:$G,"hh")/MAX(1,SUMPRODUCT(($C$15:$C$262=$C75)*($S$15:$S$262<>""))))} | AC75: =IF($S75="","",IFERROR(VLOOKUP($AE75,APU!$V:$X,2,FALSE),"")) | AD75: =IF(OR($S75="",$AC75="",N($AC75)=0),"",$S75/$AC75) | AE75: =IF($C75="","",IF(ISNUMBER($C75),REPLACE(TEXT($C75,"0.0000"),5,0,"."),$C75)) | AH75: =IF($S75="","",$AB75*N($AG75)) | AI75: =IF($S75="","",$AE75&IF(TRIM($N75)="",""," | "&TRIM($N75))&IF(OR(TRIM($O75)="",TRIM($O75)="-"),""," | "&TRIM($O75)))
B76: 8.3.6 | C76: 3.06.17 | D76: - | E76: - | F76: - | G76: =+"SUMINISTRO Y MONTAJE DE "&X76 -> SUMINISTRO Y MONTAJE DE PIPE STD WT ERW CS A53-B TYPE E | N76: ½" | O76: AA1B | P76: =IF(TRIM($G76)="","",TRIM($G76)&IF(OR(TRIM($N76)="",TRIM($N76)="-"),""," - "&TRIM($N76))&IF(OR(TRIM($O76)="",TRIM($O76)="-"),""," - "&TRIM($O76))&IF(ISNUMBER(SEARCH("SUMINISTRO",$G76))," - "&$AK$13,IF(ISNUMBER(SEARCH("MONTAJE",$G76))," - "&$AK$12,""))) -> SUMINISTRO Y MONTAJE DE PIPE STD WT ERW CS A53-B TYPE E - ½" - AA1B - Suministro Contratista | Q76: En alcance | R76: {=IF($G76="","",IFERROR(VLOOKUP(LOOKUP(2,1/(($B$14:$B76<>"")*($C$14:$C76="")),$B$14:$B76),$AM$12:$AN$16,2,FALSE),""))} -> Mecanica | S76: 6 | T76: m | U76: =+APU!K822 -> 34.717533 | V76: =U76*S76 -> 208.3052 | X76: PIPE STD WT ERW CS A53-B TYPE E | AB76: {=IF($S76="","",SUMIFS(APU!$O:$O,APU!$A:$A,IF(ISNUMBER($C76),REPLACE(TEXT($C76,"0.0000"),5,0,"."),$C76),APU!$G:$G,"hh")/MAX(1,SUMPRODUCT(($C$15:$C$262=$C76)*($S$15:$S$262<>""))))} -> 5.952 | AC76: =IF($S76="","",IFERROR(VLOOKUP($AE76,APU!$V:$X,2,FALSE),"")) -> 25 | AD76: =IF(OR($S76="",$AC76="",N($AC76)=0),"",$S76/$AC76) -> 0.24 | AE76: =IF($C76="","",IF(ISNUMBER($C76),REPLACE(TEXT($C76,"0.0000"),5,0,"."),$C76)) -> 3.06.17 | AH76: =IF($S76="","",$AB76*N($AG76)) -> 0 | AI76: =IF($S76="","",$AE76&IF(TRIM($N76)="",""," | "&TRIM($N76))&IF(OR(TRIM($O76)="",TRIM($O76)="-"),""," | "&TRIM($O76))) -> 3.06.17 | ½" | AA1B
B77: 8.3.6 | C77: 3.06.18 | D77: - | E77: - | F77: - | G77: =+"SUMINISTRO Y MONTAJE DE "&X77 -> SUMINISTRO Y MONTAJE DE PIPE STD WT ERW CS A53-B TYPE E | N77: 1" | O77: AA1B | P77: =IF(TRIM($G77)="","",TRIM($G77)&IF(OR(TRIM($N77)="",TRIM($N77)="-"),""," - "&TRIM($N77))&IF(OR(TRIM($O77)="",TRIM($O77)="-"),""," - "&TRIM($O77))&IF(ISNUMBER(SEARCH("SUMINISTRO",$G77))," - "&$AK$13,IF(ISNUMBER(SEARCH("MONTAJE",$G77))," - "&$AK$12,""))) -> SUMINISTRO Y MONTAJE DE PIPE STD WT ERW CS A53-B TYPE E - 1" - AA1B - Suministro Contratista | Q77: En alcance | R77: {=IF($G77="","",IFERROR(VLOOKUP(LOOKUP(2,1/(($B$14:$B77<>"")*($C$14:$C77="")),$B$14:$B77),$AM$12:$AN$16,2,FALSE),""))} -> Mecanica | S77: 54 | T77: m | U77: =+APU!K843 -> 30.038596 | V77: =U77*S77 -> 1622.0842 | X77: PIPE STD WT ERW CS A53-B TYPE E | AB77: {=IF($S77="","",SUMIFS(APU!$O:$O,APU!$A:$A,IF(ISNUMBER($C77),REPLACE(TEXT($C77,"0.0000"),5,0,"."),$C77),APU!$G:$G,"hh")/MAX(1,SUMPRODUCT(($C$15:$C$262=$C77)*($S$15:$S$262<>""))))} -> 53.568 | AC77: =IF($S77="","",IFERROR(VLOOKUP($AE77,APU!$V:$X,2,FALSE),"")) -> 25 | AD77: =IF(OR($S77="",$AC77="",N($AC77)=0),"",$S77/$AC77) -> 2.16 | AE77: =IF($C77="","",IF(ISNUMBER($C77),REPLACE(TEXT($C77,"0.0000"),5,0,"."),$C77)) -> 3.06.18 | AH77: =IF($S77="","",$AB77*N($AG77)) -> 0 | AI77: =IF($S77="","",$AE77&IF(TRIM($N77)="",""," | "&TRIM($N77))&IF(OR(TRIM($O77)="",TRIM($O77)="-"),""," | "&TRIM($O77))) -> 3.06.18 | 1" | AA1B
B78: 8.3.6 | C78: 3.06.19 | D78: - | E78: - | F78: - | G78: =+"SUMINISTRO Y MONTAJE DE "&X78 -> SUMINISTRO Y MONTAJE DE PIPE STD WT ERW CS A53-B TYPE E | N78: 1½" | O78: AA1B | P78: =IF(TRIM($G78)="","",TRIM($G78)&IF(OR(TRIM($N78)="",TRIM($N78)="-"),""," - "&TRIM($N78))&IF(OR(TRIM($O78)="",TRIM($O78)="-"),""," - "&TRIM($O78))&IF(ISNUMBER(SEARCH("SUMINISTRO",$G78))," - "&$AK$13,IF(ISNUMBER(SEARCH("MONTAJE",$G78))," - "&$AK$12,""))) -> SUMINISTRO Y MONTAJE DE PIPE STD WT ERW CS A53-B TYPE E - 1½" - AA1B - Suministro Contratista | Q78: En alcance | R78: {=IF($G78="","",IFERROR(VLOOKUP(LOOKUP(2,1/(($B$14:$B78<>"")*($C$14:$C78="")),$B$14:$B78),$AM$12:$AN$16,2,FALSE),""))} -> Mecanica | S78: 42 | T78: m | U78: =+APU!K864 -> 35.632896 | V78: =U78*S78 -> 1496.5816 | X78: PIPE STD WT ERW CS A53-B TYPE E | AB78: {=IF($S78="","",SUMIFS(APU!$O:$O,APU!$A:$A,IF(ISNUMBER($C78),REPLACE(TEXT($C78,"0.0000"),5,0,"."),$C78),APU!$G:$G,"hh")/MAX(1,SUMPRODUCT(($C$15:$C$262=$C78)*($S$15:$S$262<>""))))} -> 41.664 | AC78: =IF($S78="","",IFERROR(VLOOKUP($AE78,APU!$V:$X,2,FALSE),"")) -> 25 | AD78: =IF(OR($S78="",$AC78="",N($AC78)=0),"",$S78/$AC78) -> 1.68 | AE78: =IF($C78="","",IF(ISNUMBER($C78),REPLACE(TEXT($C78,"0.0000"),5,0,"."),$C78)) -> 3.06.19 | AH78: =IF($S78="","",$AB78*N($AG78)) -> 0 | AI78: =IF($S78="","",$AE78&IF(TRIM($N78)="",""," | "&TRIM($N78))&IF(OR(TRIM($O78)="",TRIM($O78)="-"),""," | "&TRIM($O78))) -> 3.06.19 | 1½" | AA1B
B79: 8.3.6 | C79: 3.06.20 | D79: - | E79: - | F79: - | G79: =+"SUMINISTRO Y MONTAJE DE "&X79 -> SUMINISTRO Y MONTAJE DE PIPE STD WT ERW CS A53-B TYPE E | N79: 2" | O79: AA1B | P79: =IF(TRIM($G79)="","",TRIM($G79)&IF(OR(TRIM($N79)="",TRIM($N79)="-"),""," - "&TRIM($N79))&IF(OR(TRIM($O79)="",TRIM($O79)="-"),""," - "&TRIM($O79))&IF(ISNUMBER(SEARCH("SUMINISTRO",$G79))," - "&$AK$13,IF(ISNUMBER(SEARCH("MONTAJE",$G79))," - "&$AK$12,""))) -> SUMINISTRO Y MONTAJE DE PIPE STD WT ERW CS A53-B TYPE E - 2" - AA1B - Suministro Contratista | Q79: En alcance | R79: {=IF($G79="","",IFERROR(VLOOKUP(LOOKUP(2,1/(($B$14:$B79<>"")*($C$14:$C79="")),$B$14:$B79),$AM$12:$AN$16,2,FALSE),""))} -> Mecanica | S79: 552 | T79: m | U79: =+APU!K885 -> 40.569896 | V79: =U79*S79 -> 22394.583 | X79: PIPE STD WT ERW CS A53-B TYPE E | AB79: {=IF($S79="","",SUMIFS(APU!$O:$O,APU!$A:$A,IF(ISNUMBER($C79),REPLACE(TEXT($C79,"0.0000"),5,0,"."),$C79),APU!$G:$G,"hh")/MAX(1,SUMPRODUCT(($C$15:$C$262=$C79)*($S$15:$S$262<>""))))} -> 547.584 | AC79: =IF($S79="","",IFERROR(VLOOKUP($AE79,APU!$V:$X,2,FALSE),"")) -> 25 | AD79: =IF(OR($S79="",$AC79="",N($AC79)=0),"",$S79/$AC79) -> 22.08 | AE79: =IF($C79="","",IF(ISNUMBER($C79),REPLACE(TEXT($C79,"0.0000"),5,0,"."),$C79)) -> 3.06.20 | AH79: =IF($S79="","",$AB79*N($AG79)) -> 0 | AI79: =IF($S79="","",$AE79&IF(TRIM($N79)="",""," | "&TRIM($N79))&IF(OR(TRIM($O79)="",TRIM($O79)="-"),""," | "&TRIM($O79))) -> 3.06.20 | 2" | AA1B
B80: 8.3.6 | C80: 3.06.21 | D80: - | E80: - | F80: - | G80: =+"SUMINISTRO Y MONTAJE DE "&X80 -> SUMINISTRO Y MONTAJE DE CHECK 800# SW STL SWING | N80: 1" | O80: AA1B | P80: =IF(TRIM($G80)="","",TRIM($G80)&IF(OR(TRIM($N80)="",TRIM($N80)="-"),""," - "&TRIM($N80))&IF(OR(TRIM($O80)="",TRIM($O80)="-"),""," - "&TRIM($O80))&IF(ISNUMBER(SEARCH("SUMINISTRO",$G80))," - "&$AK$13,IF(ISNUMBER(SEARCH("MONTAJE",$G80))," - "&$AK$12,""))) -> SUMINISTRO Y MONTAJE DE CHECK 800# SW STL SWING - 1" - AA1B - Suministro Contratista | Q80: En alcance | R80: {=IF($G80="","",IFERROR(VLOOKUP(LOOKUP(2,1/(($B$14:$B80<>"")*($C$14:$C80="")),$B$14:$B80),$AM$12:$AN$16,2,FALSE),""))} -> Mecanica | S80: 5 | T80: UND | U80: =+APU!K906 -> 160.51224 | V80: =U80*S80 -> 802.5612 | X80: CHECK 800# SW STL SWING | AB80: {=IF($S80="","",SUMIFS(APU!$O:$O,APU!$A:$A,IF(ISNUMBER($C80),REPLACE(TEXT($C80,"0.0000"),5,0,"."),$C80),APU!$G:$G,"hh")/MAX(1,SUMPRODUCT(($C$15:$C$262=$C80)*($S$15:$S$262<>""))))} -> 12.4 | AC80: =IF($S80="","",IFERROR(VLOOKUP($AE80,APU!$V:$X,2,FALSE),"")) -> 10 | AD80: =IF(OR($S80="",$AC80="",N($AC80)=0),"",$S80/$AC80) -> 0.5 | AE80: =IF($C80="","",IF(ISNUMBER($C80),REPLACE(TEXT($C80,"0.0000"),5,0,"."),$C80)) -> 3.06.21 | AH80: =IF($S80="","",$AB80*N($AG80)) -> 0 | AI80: =IF($S80="","",$AE80&IF(TRIM($N80)="",""," | "&TRIM($N80))&IF(OR(TRIM($O80)="",TRIM($O80)="-"),""," | "&TRIM($O80))) -> 3.06.21 | 1" | AA1B
B81: 8.3.6 | C81: 3.06.22 | D81: - | E81: - | F81: - | G81: =+"SUMINISTRO Y MONTAJE DE "&X81 -> SUMINISTRO Y MONTAJE DE CHECK 800# SW STL SWING | N81: 1½" | O81: AA1B | P81: =IF(TRIM($G81)="","",TRIM($G81)&IF(OR(TRIM($N81)="",TRIM($N81)="-"),""," - "&TRIM($N81))&IF(OR(TRIM($O81)="",TRIM($O81)="-"),""," - "&TRIM($O81))&IF(ISNUMBER(SEARCH("SUMINISTRO",$G81))," - "&$AK$13,IF(ISNUMBER(SEARCH("MONTAJE",$G81))," - "&$AK$12,""))) -> SUMINISTRO Y MONTAJE DE CHECK 800# SW STL SWING - 1½" - AA1B - Suministro Contratista | Q81: En alcance | R81: {=IF($G81="","",IFERROR(VLOOKUP(LOOKUP(2,1/(($B$14:$B81<>"")*($C$14:$C81="")),$B$14:$B81),$AM$12:$AN$16,2,FALSE),""))} -> Mecanica | S81: 5 | T81: UND | U81: =+APU!K926 -> 175.63744 | V81: =U81*S81 -> 878.1872 | X81: CHECK 800# SW STL SWING | AB81: {=IF($S81="","",SUMIFS(APU!$O:$O,APU!$A:$A,IF(ISNUMBER($C81),REPLACE(TEXT($C81,"0.0000"),5,0,"."),$C81),APU!$G:$G,"hh")/MAX(1,SUMPRODUCT(($C$15:$C$262=$C81)*($S$15:$S$262<>""))))} -> 12.4 | AC81: =IF($S81="","",IFERROR(VLOOKUP($AE81,APU!$V:$X,2,FALSE),"")) -> 10 | AD81: =IF(OR($S81="",$AC81="",N($AC81)=0),"",$S81/$AC81) -> 0.5 | AE81: =IF($C81="","",IF(ISNUMBER($C81),REPLACE(TEXT($C81,"0.0000"),5,0,"."),$C81)) -> 3.06.22 | AH81: =IF($S81="","",$AB81*N($AG81)) -> 0 | AI81: =IF($S81="","",$AE81&IF(TRIM($N81)="",""," | "&TRIM($N81))&IF(OR(TRIM($O81)="",TRIM($O81)="-"),""," | "&TRIM($O81))) -> 3.06.22 | 1½" | AA1B
B82: 8.3.6 | C82: 3.06.23 | D82: - | E82: - | F82: - | G82: =+"SUMINISTRO Y MONTAJE DE "&X82 -> SUMINISTRO Y MONTAJE DE CHECK 800# SW STL SWING | N82: 2" | O82: AA1B | P82: =IF(TRIM($G82)="","",TRIM($G82)&IF(OR(TRIM($N82)="",TRIM($N82)="-"),""," - "&TRIM($N82))&IF(OR(TRIM($O82)="",TRIM($O82)="-"),""," - "&TRIM($O82))&IF(ISNUMBER(SEARCH("SUMINISTRO",$G82))," - "&$AK$13,IF(ISNUMBER(SEARCH("MONTAJE",$G82))," - "&$AK$12,""))) -> SUMINISTRO Y MONTAJE DE CHECK 800# SW STL SWING - 2" - AA1B - Suministro Contratista | Q82: En alcance | R82: {=IF($G82="","",IFERROR(VLOOKUP(LOOKUP(2,1/(($B$14:$B82<>"")*($C$14:$C82="")),$B$14:$B82),$AM$12:$AN$16,2,FALSE),""))} -> Mecanica | S82: 1 | T82: UND | U82: =+APU!K946 -> 202.76264 | V82: =U82*S82 -> 202.76264 | X82: CHECK 800# SW STL SWING | AB82: {=IF($S82="","",SUMIFS(APU!$O:$O,APU!$A:$A,IF(ISNUMBER($C82),REPLACE(TEXT($C82,"0.0000"),5,0,"."),$C82),APU!$G:$G,"hh")/MAX(1,SUMPRODUCT(($C$15:$C$262=$C82)*($S$15:$S$262<>""))))} -> 2.48 | AC82: =IF($S82="","",IFERROR(VLOOKUP($AE82,APU!$V:$X,2,FALSE),"")) -> 10 | AD82: =IF(OR($S82="",$AC82="",N($AC82)=0),"",$S82/$AC82) -> 0.1 | AE82: =IF($C82="","",IF(ISNUMBER($C82),REPLACE(TEXT($C82,"0.0000"),5,0,"."),$C82)) -> 3.06.23 | AH82: =IF($S82="","",$AB82*N($AG82)) -> 0 | AI82: =IF($S82="","",$AE82&IF(TRIM($N82)="",""," | "&TRIM($N82))&IF(OR(TRIM($O82)="",TRIM($O82)="-"),""," | "&TRIM($O82))) -> 3.06.23 | 2" | AA1B
B83: 8.3.6 | C83: 3.06.24 | D83: - | E83: - | F83: - | G83: =+"SUMINISTRO Y MONTAJE DE "&X83 -> SUMINISTRO Y MONTAJE DE BALL 300# SCRD STL CS/SS, HNDL OP | N83: ½" | O83: AA1B | P83: =IF(TRIM($G83)="","",TRIM($G83)&IF(OR(TRIM($N83)="",TRIM($N83)="-"),""," - "&TRIM($N83))&IF(OR(TRIM($O83)="",TRIM($O83)="-"),""," - "&TRIM($O83))&IF(ISNUMBER(SEARCH("SUMINISTRO",$G83))," - "&$AK$13,IF(ISNUMBER(SEARCH("MONTAJE",$G83))," - "&$AK$12,""))) -> SUMINISTRO Y MONTAJE DE BALL 300# SCRD STL CS/SS, HNDL OP - ½" - AA1B - Suministro Contratista | Q83: En alcance | R83: {=IF($G83="","",IFERROR(VLOOKUP(LOOKUP(2,1/(($B$14:$B83<>"")*($C$14:$C83="")),$B$14:$B83),$AM$12:$AN$16,2,FALSE),""))} -> Mecanica | S83: 21 | T83: UND | U83: =+APU!K966 -> 38.34255 | V83: =U83*S83 -> 805.19355 | X83: BALL 300# SCRD STL CS/SS, HNDL OP | AB83: {=IF($S83="","",SUMIFS(APU!$O:$O,APU!$A:$A,IF(ISNUMBER($C83),REPLACE(TEXT($C83,"0.0000"),5,0,"."),$C83),APU!$G:$G,"hh")/MAX(1,SUMPRODUCT(($C$15:$C$262=$C83)*($S$15:$S$262<>""))))} -> 44.1 | AC83: =IF($S83="","",IFERROR(VLOOKUP($AE83,APU!$V:$X,2,FALSE),"")) -> 8 | AD83: =IF(OR($S83="",$AC83="",N($AC83)=0),"",$S83/$AC83) -> 2.625 | AE83: =IF($C83="","",IF(ISNUMBER($C83),REPLACE(TEXT($C83,"0.0000"),5,0,"."),$C83)) -> 3.06.24 | AH83: =IF($S83="","",$AB83*N($AG83)) -> 0 | AI83: =IF($S83="","",$AE83&IF(TRIM($N83)="",""," | "&TRIM($N83))&IF(OR(TRIM($O83)="",TRIM($O83)="-"),""," | "&TRIM($O83))) -> 3.06.24 | ½" | AA1B
B84: 8.3.6 | C84: 3.06.25 | D84: - | E84: - | F84: - | G84: =+"SUMINISTRO Y MONTAJE DE "&X84 -> SUMINISTRO Y MONTAJE DE BALL 300# SCRD STL CS/SS, HNDL OP | N84: 1" | O84: AA1B | P84: =IF(TRIM($G84)="","",TRIM($G84)&IF(OR(TRIM($N84)="",TRIM($N84)="-"),""," - "&TRIM($N84))&IF(OR(TRIM($O84)="",TRIM($O84)="-"),""," - "&TRIM($O84))&IF(ISNUMBER(SEARCH("SUMINISTRO",$G84))," - "&$AK$13,IF(ISNUMBER(SEARCH("MONTAJE",$G84))," - "&$AK$12,""))) -> SUMINISTRO Y MONTAJE DE BALL 300# SCRD STL CS/SS, HNDL OP - 1" - AA1B - Suministro Contratista | Q84: En alcance | R84: {=IF($G84="","",IFERROR(VLOOKUP(LOOKUP(2,1/(($B$14:$B84<>"")*($C$14:$C84="")),$B$14:$B84),$AM$12:$AN$16,2,FALSE),""))} -> Mecanica | S84: 22 | T84: UND | U84: =+APU!K982 -> 46.60255 | V84: =U84*S84 -> 1025.2561 | X84: BALL 300# SCRD STL CS/SS, HNDL OP | AB84: {=IF($S84="","",SUMIFS(APU!$O:$O,APU!$A:$A,IF(ISNUMBER($C84),REPLACE(TEXT($C84,"0.0000"),5,0,"."),$C84),APU!$G:$G,"hh")/MAX(1,SUMPRODUCT(($C$15:$C$262=$C84)*($S$15:$S$262<>""))))} -> 46.2 | AC84: =IF($S84="","",IFERROR(VLOOKUP($AE84,APU!$V:$X,2,FALSE),"")) -> 8 | AD84: =IF(OR($S84="",$AC84="",N($AC84)=0),"",$S84/$AC84) -> 2.75 | AE84: =IF($C84="","",IF(ISNUMBER($C84),REPLACE(TEXT($C84,"0.0000"),5,0,"."),$C84)) -> 3.06.25 | AH84: =IF($S84="","",$AB84*N($AG84)) -> 0 | AI84: =IF($S84="","",$AE84&IF(TRIM($N84)="",""," | "&TRIM($N84))&IF(OR(TRIM($O84)="",TRIM($O84)="-"),""," | "&TRIM($O84))) -> 3.06.25 | 1" | AA1B
B85: 8.3.6 | C85: 3.06.26 | D85: - | E85: - | F85: - | G85: =+"SUMINISTRO Y MONTAJE DE "&X85 -> SUMINISTRO Y MONTAJE DE BALL 300# SCRD STL CS/SS, HNDL OP | N85: 1½" | O85: AA1B | P85: =IF(TRIM($G85)="","",TRIM($G85)&IF(OR(TRIM($N85)="",TRIM($N85)="-"),""," - "&TRIM($N85))&IF(OR(TRIM($O85)="",TRIM($O85)="-"),""," - "&TRIM($O85))&IF(ISNUMBER(SEARCH("SUMINISTRO",$G85))," - "&$AK$13,IF(ISNUMBER(SEARCH("MONTAJE",$G85))," - "&$AK$12,""))) -> SUMINISTRO Y MONTAJE DE BALL 300# SCRD STL CS/SS, HNDL OP - 1½" - AA1B - Suministro Contratista | Q85: En alcance | R85: {=IF($G85="","",IFERROR(VLOOKUP(LOOKUP(2,1/(($B$14:$B85<>"")*($C$14:$C85="")),$B$14:$B85),$AM$12:$AN$16,2,FALSE),""))} -> Mecanica | S85: 17 | T85: UND | U85: =+APU!K999 -> 48.59255 | V85: =U85*S85 -> 826.07335 | X85: BALL 300# SCRD STL CS/SS, HNDL OP | AB85: {=IF($S85="","",SUMIFS(APU!$O:$O,APU!$A:$A,IF(ISNUMBER($C85),REPLACE(TEXT($C85,"0.0000"),5,0,"."),$C85),APU!$G:$G,"hh")/MAX(1,SUMPRODUCT(($C$15:$C$262=$C85)*($S$15:$S$262<>""))))} -> 35.7 | AC85: =IF($S85="","",IFERROR(VLOOKUP($AE85,APU!$V:$X,2,FALSE),"")) -> 8 | AD85: =IF(OR($S85="",$AC85="",N($AC85)=0),"",$S85/$AC85) -> 2.125 | AE85: =IF($C85="","",IF(ISNUMBER($C85),REPLACE(TEXT($C85,"0.0000"),5,0,"."),$C85)) -> 3.06.26 | AH85: =IF($S85="","",$AB85*N($AG85)) -> 0 | AI85: =IF($S85="","",$AE85&IF(TRIM($N85)="",""," | "&TRIM($N85))&IF(OR(TRIM($O85)="",TRIM($O85)="-"),""," | "&TRIM($O85))) -> 3.06.26 | 1½" | AA1B
B86: 8.3.6 | C86: 3.06.27 | D86: - | E86: - | F86: - | G86: =+"SUMINISTRO Y MONTAJE DE "&X86 -> SUMINISTRO Y MONTAJE DE BALL 300# SCRD STL CS/SS, HNDL OP | N86: 2" | O86: AA1B | P86: =IF(TRIM($G86)="","",TRIM($G86)&IF(OR(TRIM($N86)="",TRIM($N86)="-"),""," - "&TRIM($N86))&IF(OR(TRIM($O86)="",TRIM($O86)="-"),""," - "&TRIM($O86))&IF(ISNUMBER(SEARCH("SUMINISTRO",$G86))," - "&$AK$13,IF(ISNUMBER(SEARCH("MONTAJE",$G86))," - "&$AK$12,""))) -> SUMINISTRO Y MONTAJE DE BALL 300# SCRD STL CS/SS, HNDL OP - 2" - AA1B - Suministro Contratista | Q86: En alcance | R86: {=IF($G86="","",IFERROR(VLOOKUP(LOOKUP(2,1/(($B$14:$B86<>"")*($C$14:$C86="")),$B$14:$B86),$AM$12:$AN$16,2,FALSE),""))} -> Mecanica | S86: 18 | T86: UND | U86: =+APU!K1015 -> 52.79255 | V86: =U86*S86 -> 950.2659 | X86: BALL 300# SCRD STL CS/SS, HNDL OP | AB86: {=IF($S86="","",SUMIFS(APU!$O:$O,APU!$A:$A,IF(ISNUMBER($C86),REPLACE(TEXT($C86,"0.0000"),5,0,"."),$C86),APU!$G:$G,"hh")/MAX(1,SUMPRODUCT(($C$15:$C$262=$C86)*($S$15:$S$262<>""))))} -> 37.8 | AC86: =IF($S86="","",IFERROR(VLOOKUP($AE86,APU!$V:$X,2,FALSE),"")) -> 8 | AD86: =IF(OR($S86="",$AC86="",N($AC86)=0),"",$S86/$AC86) -> 2.25 | AE86: =IF($C86="","",IF(ISNUMBER($C86),REPLACE(TEXT($C86,"0.0000"),5,0,"."),$C86)) -> 3.06.27 | AH86: =IF($S86="","",$AB86*N($AG86)) -> 0 | AI86: =IF($S86="","",$AE86&IF(TRIM($N86)="",""," | "&TRIM($N86))&IF(OR(TRIM($O86)="",TRIM($O86)="-"),""," | "&TRIM($O86))) -> 3.06.27 | 2" | AA1B
B87: 8.3.6 | C87: 3.06.28 | D87: - | E87: - | F87: - | G87: =+"SUMINISTRO Y MONTAJE DE "&X87 -> SUMINISTRO Y MONTAJE DE FLG SW CLASS 150 RF CS STD BORE A105 | N87: ½" | O87: AA1B | P87: =IF(TRIM($G87)="","",TRIM($G87)&IF(OR(TRIM($N87)="",TRIM($N87)="-"),""," - "&TRIM($N87))&IF(OR(TRIM($O87)="",TRIM($O87)="-"),""," - "&TRIM($O87))&IF(ISNUMBER(SEARCH("SUMINISTRO",$G87))," - "&$AK$13,IF(ISNUMBER(SEARCH("MONTAJE",$G87))," - "&$AK$12,""))) -> SUMINISTRO Y MONTAJE DE FLG SW CLASS 150 RF CS STD BORE A105 - ½" - AA1B - Suministro Contratista | Q87: En alcance | R87: {=IF($G87="","",IFERROR(VLOOKUP(LOOKUP(2,1/(($B$14:$B87<>"")*($C$14:$C87="")),$B$14:$B87),$AM$12:$AN$16,2,FALSE),""))} -> Mecanica | S87: 2 | T87: UND | U87: =+APU!K1031 -> 106.83839 | V87: =U87*S87 -> 213.67677 | X87: FLG SW CLASS 150 RF CS STD BORE A105 | AB87: {=IF($S87="","",SUMIFS(APU!$O:$O,APU!$A:$A,IF(ISNUMBER($C87),REPLACE(TEXT($C87,"0.0000"),5,0,"."),$C87),APU!$G:$G,"hh")/MAX(1,SUMPRODUCT(($C$15:$C$262=$C87)*($S$15:$S$262<>""))))} -> 12.4 | AC87: =IF($S87="","",IFERROR(VLOOKUP($AE87,APU!$V:$X,2,FALSE),"")) -> 4 | AD87: =IF(OR($S87="",$AC87="",N($AC87)=0),"",$S87/$AC87) -> 0.5 | AE87: =IF($C87="","",IF(ISNUMBER($C87),REPLACE(TEXT($C87,"0.0000"),5,0,"."),$C87)) -> 3.06.28 | AH87: =IF($S87="","",$AB87*N($AG87)) -> 0 | AI87: =IF($S87="","",$AE87&IF(TRIM($N87)="",""," | "&TRIM($N87))&IF(OR(TRIM($O87)="",TRIM($O87)="-"),""," | "&TRIM($O87))) -> 3.06.28 | ½" | AA1B
B88: 8.3.6 | C88: 3.06.29 | D88: - | E88: - | F88: - | G88: =+"SUMINISTRO Y MONTAJE DE "&X88 -> SUMINISTRO Y MONTAJE DE FLG SW CLASS 150 RF CS STD BORE A105 | N88: 1" | O88: AA1B | P88: =IF(TRIM($G88)="","",TRIM($G88)&IF(OR(TRIM($N88)="",TRIM($N88)="-"),""," - "&TRIM($N88))&IF(OR(TRIM($O88)="",TRIM($O88)="-"),""," - "&TRIM($O88))&IF(ISNUMBER(SEARCH("SUMINISTRO",$G88))," - "&$AK$13,IF(ISNUMBER(SEARCH("MONTAJE",$G88))," - "&$AK$12,""))) -> SUMINISTRO Y MONTAJE DE FLG SW CLASS 150 RF CS STD BORE A105 - 1" - AA1B - Suministro Contratista | Q88: En alcance | R88: {=IF($G88="","",IFERROR(VLOOKUP(LOOKUP(2,1/(($B$14:$B88<>"")*($C$14:$C88="")),$B$14:$B88),$AM$12:$AN$16,2,FALSE),""))} -> Mecanica | S88: 5 | T88: UND | U88: =+APU!K1051 -> 112.67787 | V88: =U88*S88 -> 563.38936 | X88: FLG SW CLASS 150 RF CS STD BORE A105 | AB88: {=IF($S88="","",SUMIFS(APU!$O:$O,APU!$A:$A,IF(ISNUMBER($C88),REPLACE(TEXT($C88,"0.0000"),5,0,"."),$C88),APU!$G:$G,"hh")/MAX(1,SUMPRODUCT(($C$15:$C$262=$C88)*($S$15:$S$262<>""))))} -> 31 | AC88: =IF($S88="","",IFERROR(VLOOKUP($AE88,APU!$V:$X,2,FALSE),"")) -> 4 | AD88: =IF(OR($S88="",$AC88="",N($AC88)=0),"",$S88/$AC88) -> 1.25 | AE88: =IF($C88="","",IF(ISNUMBER($C88),REPLACE(TEXT($C88,"0.0000"),5,0,"."),$C88)) -> 3.06.29 | AH88: =IF($S88="","",$AB88*N($AG88)) -> 0 | AI88: =IF($S88="","",$AE88&IF(TRIM($N88)="",""," | "&TRIM($N88))&IF(OR(TRIM($O88)="",TRIM($O88)="-"),""," | "&TRIM($O88))) -> 3.06.29 | 1" | AA1B
B89: 8.3.6 | C89: 3.06.30 | D89: - | E89: - | F89: - | G89: =+"SUMINISTRO Y MONTAJE DE "&X89 -> SUMINISTRO Y MONTAJE DE FLG SW CLASS 150 RF CS STD BORE A105 | N89: 1½" | O89: AA1B | P89: =IF(TRIM($G89)="","",TRIM($G89)&IF(OR(TRIM($N89)="",TRIM($N89)="-"),""," - "&TRIM($N89))&IF(OR(TRIM($O89)="",TRIM($O89)="-"),""," - "&TRIM($O89))&IF(ISNUMBER(SEARCH("SUMINISTRO",$G89))," - "&$AK$13,IF(ISNUMBER(SEARCH("MONTAJE",$G89))," - "&$AK$12,""))) -> SUMINISTRO Y MONTAJE DE FLG SW CLASS 150 RF CS STD BORE A105 - 1½" - AA1B - Suministro Contratista | Q89: En alcance | R89: {=IF($G89="","",IFERROR(VLOOKUP(LOOKUP(2,1/(($B$14:$B89<>"")*($C$14:$C89="")),$B$14:$B89),$AM$12:$AN$16,2,FALSE),""))} -> Mecanica | S89: 11 | T89: UND | U89: =+APU!K1071 -> 124.23164 | V89: =U89*S89 -> 1366.5481 | X89: FLG SW CLASS 150 RF CS STD BORE A105 | AB89: {=IF($S89="","",SUMIFS(APU!$O:$O,APU!$A:$A,IF(ISNUMBER($C89),REPLACE(TEXT($C89,"0.0000"),5,0,"."),$C89),APU!$G:$G,"hh")/MAX(1,SUMPRODUCT(($C$15:$C$262=$C89)*($S$15:$S$262<>""))))} -> 68.2 | AC89: =IF($S89="","",IFERROR(VLOOKUP($AE89,APU!$V:$X,2,FALSE),"")) -> 4 | AD89: =IF(OR($S89="",$AC89="",N($AC89)=0),"",$S89/$AC89) -> 2.75 | AE89: =IF($C89="","",IF(ISNUMBER($C89),REPLACE(TEXT($C89,"0.0000"),5,0,"."),$C89)) -> 3.06.30 | AH89: =IF($S89="","",$AB89*N($AG89)) -> 0 | AI89: =IF($S89="","",$AE89&IF(TRIM($N89)="",""," | "&TRIM($N89))&IF(OR(TRIM($O89)="",TRIM($O89)="-"),""," | "&TRIM($O89))) -> 3.06.30 | 1½" | AA1B
B90: 8.3.6 | C90: 3.06.31 | D90: - | E90: - | F90: - | G90: =+"SUMINISTRO Y MONTAJE DE "&X90 -> SUMINISTRO Y MONTAJE DE FLG SW CLASS 150 RF CS STD BORE A105 | N90: 2" | O90: AA1B | P90: =IF(TRIM($G90)="","",TRIM($G90)&IF(OR(TRIM($N90)="",TRIM($N90)="-"),""," - "&TRIM($N90))&IF(OR(TRIM($O90)="",TRIM($O90)="-"),""," - "&TRIM($O90))&IF(ISNUMBER(SEARCH("SUMINISTRO",$G90))," - "&$AK$13,IF(ISNUMBER(SEARCH("MONTAJE",$G90))," - "&$AK$12,""))) -> SUMINISTRO Y MONTAJE DE FLG SW CLASS 150 RF CS STD BORE A105 - 2" - AA1B - Suministro Contratista | Q90: En alcance | R90: {=IF($G90="","",IFERROR(VLOOKUP(LOOKUP(2,1/(($B$14:$B90<>"")*($C$14:$C90="")),$B$14:$B90),$AM$12:$AN$16,2,FALSE),""))} -> Mecanica | S90: 7 | T90: UND | U90: =+APU!K1091 -> 158.0943 | V90: =U90*S90 -> 1106.6601 | X90: FLG SW CLASS 150 RF CS STD BORE A105 | AB90: {=IF($S90="","",SUMIFS(APU!$O:$O,APU!$A:$A,IF(ISNUMBER($C90),REPLACE(TEXT($C90,"0.0000"),5,0,"."),$C90),APU!$G:$G,"hh")/MAX(1,SUMPRODUCT(($C$15:$C$262=$C90)*($S$15:$S$262<>""))))} -> 57.866667 | AC90: =IF($S90="","",IFERROR(VLOOKUP($AE90,APU!$V:$X,2,FALSE),"")) -> 3 | AD90: =IF(OR($S90="",$AC90="",N($AC90)=0),"",$S90/$AC90) -> 2.3333333 | AE90: =IF($C90="","",IF(ISNUMBER($C90),REPLACE(TEXT($C90,"0.0000"),5,0,"."),$C90)) -> 3.06.31 | AH90: =IF($S90="","",$AB90*N($AG90)) -> 0 | AI90: =IF($S90="","",$AE90&IF(TRIM($N90)="",""," | "&TRIM($N90))&IF(OR(TRIM($O90)="",TRIM($O90)="-"),""," | "&TRIM($O90))) -> 3.06.31 | 2" | AA1B
B91: 8.3.6 | C91: 3.06.32 | D91: - | E91: - | F91: - | G91: =+"SUMINISTRO Y MONTAJE DE "&X91 -> SUMINISTRO Y MONTAJE DE GASKET 150#NOM-ASB-RING PT AGT 1/8"THK | N91: ½" | O91: AA1B | P91: =IF(TRIM($G91)="","",TRIM($G91)&IF(OR(TRIM($N91)="",TRIM($N91)="-"),""," - "&TRIM($N91))&IF(OR(TRIM($O91)="",TRIM($O91)="-"),""," - "&TRIM($O91))&IF(ISNUMBER(SEARCH("SUMINISTRO",$G91))," - "&$AK$13,IF(ISNUMBER(SEARCH("MONTAJE",$G91))," - "&$AK$12,""))) -> SUMINISTRO Y MONTAJE DE GASKET 150#NOM-ASB-RING PT AGT 1/8"THK - ½" - AA1B - Suministro Contratista | Q91: En alcance | R91: {=IF($G91="","",IFERROR(VLOOKUP(LOOKUP(2,1/(($B$14:$B91<>"")*($C$14:$C91="")),$B$14:$B91),$AM$12:$AN$16,2,FALSE),""))} -> Mecanica | S91: 2 | T91: UND | U91: =+APU!K1111 -> 19.394808 | V91: =U91*S91 -> 38.789616 | X91: GASKET 150#NOM-ASB-RING PT AGT 1/8"THK | AB91: {=IF($S91="","",SUMIFS(APU!$O:$O,APU!$A:$A,IF(ISNUMBER($C91),REPLACE(TEXT($C91,"0.0000"),5,0,"."),$C91),APU!$G:$G,"hh")/MAX(1,SUMPRODUCT(($C$15:$C$262=$C91)*($S$15:$S$262<>""))))} -> 0.672 | AC91: =IF($S91="","",IFERROR(VLOOKUP($AE91,APU!$V:$X,2,FALSE),"")) -> 50 | AD91: =IF(OR($S91="",$AC91="",N($AC91)=0),"",$S91/$AC91) -> 0.04 | AE91: =IF($C91="","",IF(ISNUMBER($C91),REPLACE(TEXT($C91,"0.0000"),5,0,"."),$C91)) -> 3.06.32 | AH91: =IF($S91="","",$AB91*N($AG91)) -> 0 | AI91: =IF($S91="","",$AE91&IF(TRIM($N91)="",""," | "&TRIM($N91))&IF(OR(TRIM($O91)="",TRIM($O91)="-"),""," | "&TRIM($O91))) -> 3.06.32 | ½" | AA1B
B92: 8.3.6 | C92: 3.06.33 | D92: - | E92: - | F92: - | G92: =+"SUMINISTRO Y MONTAJE DE "&X92 -> SUMINISTRO Y MONTAJE DE GASKET 150#NOM-ASB-RING PT AGT 1/8"THK | N92: 1" | O92: AA1B | P92: =IF(TRIM($G92)="","",TRIM($G92)&IF(OR(TRIM($N92)="",TRIM($N92)="-"),""," - "&TRIM($N92))&IF(OR(TRIM($O92)="",TRIM($O92)="-"),""," - "&TRIM($O92))&IF(ISNUMBER(SEARCH("SUMINISTRO",$G92))," - "&$AK$13,IF(ISNUMBER(SEARCH("MONTAJE",$G92))," - "&$AK$12,""))) -> SUMINISTRO Y MONTAJE DE GASKET 150#NOM-ASB-RING PT AGT 1/8"THK - 1" - AA1B - Suministro Contratista | Q92: En alcance | R92: {=IF($G92="","",IFERROR(VLOOKUP(LOOKUP(2,1/(($B$14:$B92<>"")*($C$14:$C92="")),$B$14:$B92),$AM$12:$AN$16,2,FALSE),""))} -> Mecanica | S92: 5 | T92: UND | U92: =+APU!K1127 -> 24.394808 | V92: =U92*S92 -> 121.97404 | X92: GASKET 150#NOM-ASB-RING PT AGT 1/8"THK | AB92: {=IF($S92="","",SUMIFS(APU!$O:$O,APU!$A:$A,IF(ISNUMBER($C92),REPLACE(TEXT($C92,"0.0000"),5,0,"."),$C92),APU!$G:$G,"hh")/MAX(1,SUMPRODUCT(($C$15:$C$262=$C92)*($S$15:$S$262<>""))))} -> 1.68 | AC92: =IF($S92="","",IFERROR(VLOOKUP($AE92,APU!$V:$X,2,FALSE),"")) -> 50 | AD92: =IF(OR($S92="",$AC92="",N($AC92)=0),"",$S92/$AC92) -> 0.1 | AE92: =IF($C92="","",IF(ISNUMBER($C92),REPLACE(TEXT($C92,"0.0000"),5,0,"."),$C92)) -> 3.06.33 | AH92: =IF($S92="","",$AB92*N($AG92)) -> 0 | AI92: =IF($S92="","",$AE92&IF(TRIM($N92)="",""," | "&TRIM($N92))&IF(OR(TRIM($O92)="",TRIM($O92)="-"),""," | "&TRIM($O92))) -> 3.06.33 | 1" | AA1B
B93: 8.3.6 | C93: 3.06.34 | D93: - | E93: - | F93: - | G93: =+"SUMINISTRO Y MONTAJE DE "&X93 -> SUMINISTRO Y MONTAJE DE GASKET 150#NOM-ASB-RING PT AGT 1/8"THK | N93: 1½" | O93: AA1B | P93: =IF(TRIM($G93)="","",TRIM($G93)&IF(OR(TRIM($N93)="",TRIM($N93)="-"),""," - "&TRIM($N93))&IF(OR(TRIM($O93)="",TRIM($O93)="-"),""," - "&TRIM($O93))&IF(ISNUMBER(SEARCH("SUMINISTRO",$G93))," - "&$AK$13,IF(ISNUMBER(SEARCH("MONTAJE",$G93))," - "&$AK$12,""))) -> SUMINISTRO Y MONTAJE DE GASKET 150#NOM-ASB-RING PT AGT 1/8"THK - 1½" - AA1B - Suministro Contratista | Q93: En alcance | R93: {=IF($G93="","",IFERROR(VLOOKUP(LOOKUP(2,1/(($B$14:$B93<>"")*($C$14:$C93="")),$B$14:$B93),$AM$12:$AN$16,2,FALSE),""))} -> Mecanica | S93: 11 | T93: UND | U93: =+APU!K1143 -> 29.394808 | V93: =U93*S93 -> 323.34289 | X93: GASKET 150#NOM-ASB-RING PT AGT 1/8"THK | AB93: {=IF($S93="","",SUMIFS(APU!$O:$O,APU!$A:$A,IF(ISNUMBER($C93),REPLACE(TEXT($C93,"0.0000"),5,0,"."),$C93),APU!$G:$G,"hh")/MAX(1,SUMPRODUCT(($C$15:$C$262=$C93)*($S$15:$S$262<>""))))} -> 3.696 | AC93: =IF($S93="","",IFERROR(VLOOKUP($AE93,APU!$V:$X,2,FALSE),"")) -> 50 | AD93: =IF(OR($S93="",$AC93="",N($AC93)=0),"",$S93/$AC93) -> 0.22 | AE93: =IF($C93="","",IF(ISNUMBER($C93),REPLACE(TEXT($C93,"0.0000"),5,0,"."),$C93)) -> 3.06.34 | AH93: =IF($S93="","",$AB93*N($AG93)) -> 0 | AI93: =IF($S93="","",$AE93&IF(TRIM($N93)="",""," | "&TRIM($N93))&IF(OR(TRIM($O93)="",TRIM($O93)="-"),""," | "&TRIM($O93))) -> 3.06.34 | 1½" | AA1B
B94: 8.3.6 | C94: 3.06.35 | D94: - | E94: - | F94: - | G94: =+"SUMINISTRO Y MONTAJE DE "&X94 -> SUMINISTRO Y MONTAJE DE GASKET 150#NOM-ASB-RING PT AGT 1/8"THK | N94: 2" | O94: AA1B | P94: =IF(TRIM($G94)="","",TRIM($G94)&IF(OR(TRIM($N94)="",TRIM($N94)="-"),""," - "&TRIM($N94))&IF(OR(TRIM($O94)="",TRIM($O94)="-"),""," - "&TRIM($O94))&IF(ISNUMBER(SEARCH("SUMINISTRO",$G94))," - "&$AK$13,IF(ISNUMBER(SEARCH("MONTAJE",$G94))," - "&$AK$12,""))) -> SUMINISTRO Y MONTAJE DE GASKET 150#NOM-ASB-RING PT AGT 1/8"THK - 2" - AA1B - Suministro Contratista | Q94: En alcance | R94: {=IF($G94="","",IFERROR(VLOOKUP(LOOKUP(2,1/(($B$14:$B94<>"")*($C$14:$C94="")),$B$14:$B94),$AM$12:$AN$16,2,FALSE),""))} -> Mecanica | S94: 7 | T94: UND | U94: =+APU!K1159 -> 32.394808 | V94: =U94*S94 -> 226.76366 | X94: GASKET 150#NOM-ASB-RING PT AGT 1/8"THK | AB94: {=IF($S94="","",SUMIFS(APU!$O:$O,APU!$A:$A,IF(ISNUMBER($C94),REPLACE(TEXT($C94,"0.0000"),5,0,"."),$C94),APU!$G:$G,"hh")/MAX(1,SUMPRODUCT(($C$15:$C$262=$C94)*($S$15:$S$262<>""))))} -> 2.352 | AC94: =IF($S94="","",IFERROR(VLOOKUP($AE94,APU!$V:$X,2,FALSE),"")) -> 50 | AD94: =IF(OR($S94="",$AC94="",N($AC94)=0),"",$S94/$AC94) -> 0.14 | AE94: =IF($C94="","",IF(ISNUMBER($C94),REPLACE(TEXT($C94,"0.0000"),5,0,"."),$C94)) -> 3.06.35 | AH94: =IF($S94="","",$AB94*N($AG94)) -> 0 | AI94: =IF($S94="","",$AE94&IF(TRIM($N94)="",""," | "&TRIM($N94))&IF(OR(TRIM($O94)="",TRIM($O94)="-"),""," | "&TRIM($O94))) -> 3.06.35 | 2" | AA1B
B95: 8.3.6 | C95: 3.06.36 | D95: - | E95: - | F95: - | G95: =+"SUMINISTRO Y MONTAJE DE "&X95 -> SUMINISTRO Y MONTAJE DE GASKET 150#NOM-ASB-RING PT AGT 1/8"THK | N95: 3" | O95: AA1B | P95: =IF(TRIM($G95)="","",TRIM($G95)&IF(OR(TRIM($N95)="",TRIM($N95)="-"),""," - "&TRIM($N95))&IF(OR(TRIM($O95)="",TRIM($O95)="-"),""," - "&TRIM($O95))&IF(ISNUMBER(SEARCH("SUMINISTRO",$G95))," - "&$AK$13,IF(ISNUMBER(SEARCH("MONTAJE",$G95))," - "&$AK$12,""))) -> SUMINISTRO Y MONTAJE DE GASKET 150#NOM-ASB-RING PT AGT 1/8"THK - 3" - AA1B - Suministro Contratista | Q95: En alcance | R95: {=IF($G95="","",IFERROR(VLOOKUP(LOOKUP(2,1/(($B$14:$B95<>"")*($C$14:$C95="")),$B$14:$B95),$AM$12:$AN$16,2,FALSE),""))} -> Mecanica | S95: 28 | T95: UND | U95: =+APU!K1175 -> 40.11851 | V95: =U95*S95 -> 1123.3183 | X95: GASKET 150#NOM-ASB-RING PT AGT 1/8"THK | AB95: {=IF($S95="","",SUMIFS(APU!$O:$O,APU!$A:$A,IF(ISNUMBER($C95),REPLACE(TEXT($C95,"0.0000"),5,0,"."),$C95),APU!$G:$G,"hh")/MAX(1,SUMPRODUCT(($C$15:$C$262=$C95)*($S$15:$S$262<>""))))} -> 11.76 | AC95: =IF($S95="","",IFERROR(VLOOKUP($AE95,APU!$V:$X,2,FALSE),"")) -> 40 | AD95: =IF(OR($S95="",$AC95="",N($AC95)=0),"",$S95/$AC95) -> 0.7 | AE95: =IF($C95="","",IF(ISNUMBER($C95),REPLACE(TEXT($C95,"0.0000"),5,0,"."),$C95)) -> 3.06.36 | AH95: =IF($S95="","",$AB95*N($AG95)) -> 0 | AI95: =IF($S95="","",$AE95&IF(TRIM($N95)="",""," | "&TRIM($N95))&IF(OR(TRIM($O95)="",TRIM($O95)="-"),""," | "&TRIM($O95))) -> 3.06.36 | 3" | AA1B
B96: 8.3.6 | C96: 3.06.37 | D96: - | E96: - | F96: - | G96: =+"SUMINISTRO Y MONTAJE DE "&X96 -> SUMINISTRO Y MONTAJE DE GASKET 150#NOM-ASB-RING PT AGT 1/8"THK | N96: 4" | O96: AA1B | P96: =IF(TRIM($G96)="","",TRIM($G96)&IF(OR(TRIM($N96)="",TRIM($N96)="-"),""," - "&TRIM($N96))&IF(OR(TRIM($O96)="",TRIM($O96)="-"),""," - "&TRIM($O96))&IF(ISNUMBER(SEARCH("SUMINISTRO",$G96))," - "&$AK$13,IF(ISNUMBER(SEARCH("MONTAJE",$G96))," - "&$AK$12,""))) -> SUMINISTRO Y MONTAJE DE GASKET 150#NOM-ASB-RING PT AGT 1/8"THK - 4" - AA1B - Suministro Contratista | Q96: En alcance | R96: {=IF($G96="","",IFERROR(VLOOKUP(LOOKUP(2,1/(($B$14:$B96<>"")*($C$14:$C96="")),$B$14:$B96),$AM$12:$AN$16,2,FALSE),""))} -> Mecanica | S96: 8 | T96: UND | U96: =+APU!K1191 -> 65.11851 | V96: =U96*S96 -> 520.94808 | X96: GASKET 150#NOM-ASB-RING PT AGT 1/8"THK | AB96: {=IF($S96="","",SUMIFS(APU!$O:$O,APU!$A:$A,IF(ISNUMBER($C96),REPLACE(TEXT($C96,"0.0000"),5,0,"."),$C96),APU!$G:$G,"hh")/MAX(1,SUMPRODUCT(($C$15:$C$262=$C96)*($S$15:$S$262<>""))))} -> 3.36 | AC96: =IF($S96="","",IFERROR(VLOOKUP($AE96,APU!$V:$X,2,FALSE),"")) -> 40 | AD96: =IF(OR($S96="",$AC96="",N($AC96)=0),"",$S96/$AC96) -> 0.2 | AE96: =IF($C96="","",IF(ISNUMBER($C96),REPLACE(TEXT($C96,"0.0000"),5,0,"."),$C96)) -> 3.06.37 | AH96: =IF($S96="","",$AB96*N($AG96)) -> 0 | AI96: =IF($S96="","",$AE96&IF(TRIM($N96)="",""," | "&TRIM($N96))&IF(OR(TRIM($O96)="",TRIM($O96)="-"),""," | "&TRIM($O96))) -> 3.06.37 | 4" | AA1B
B97: 8.3.6 | C97: 3.06.38 | D97: - | E97: - | F97: - | G97: =+"SUMINISTRO Y MONTAJE DE "&X97 -> SUMINISTRO Y MONTAJE DE SOCKOLET 3000# STL A105 | N97: 1" | O97: AA1B | P97: =IF(TRIM($G97)="","",TRIM($G97)&IF(OR(TRIM($N97)="",TRIM($N97)="-"),""," - "&TRIM($N97))&IF(OR(TRIM($O97)="",TRIM($O97)="-"),""," - "&TRIM($O97))&IF(ISNUMBER(SEARCH("SUMINISTRO",$G97))," - "&$AK$13,IF(ISNUMBER(SEARCH("MONTAJE",$G97))," - "&$AK$12,""))) -> SUMINISTRO Y MONTAJE DE SOCKOLET 3000# STL A105 - 1" - AA1B - Suministro Contratista | Q97: En alcance | R97: {=IF($G97="","",IFERROR(VLOOKUP(LOOKUP(2,1/(($B$14:$B97<>"")*($C$14:$C97="")),$B$14:$B97),$AM$12:$AN$16,2,FALSE),""))} -> Mecanica | S97: 7 | T97: UND | U97: =+APU!K1207 -> 62.709669 | V97: =U97*S97 -> 438.96768 | X97: SOCKOLET 3000# STL A105 | AB97: {=IF($S97="","",SUMIFS(APU!$O:$O,APU!$A:$A,IF(ISNUMBER($C97),REPLACE(TEXT($C97,"0.0000"),5,0,"."),$C97),APU!$G:$G,"hh")/MAX(1,SUMPRODUCT(($C$15:$C$262=$C97)*($S$15:$S$262<>""))))} -> 17.36 | AC97: =IF($S97="","",IFERROR(VLOOKUP($AE97,APU!$V:$X,2,FALSE),"")) -> 10 | AD97: =IF(OR($S97="",$AC97="",N($AC97)=0),"",$S97/$AC97) -> 0.7 | AE97: =IF($C97="","",IF(ISNUMBER($C97),REPLACE(TEXT($C97,"0.0000"),5,0,"."),$C97)) -> 3.06.38 | AH97: =IF($S97="","",$AB97*N($AG97)) -> 0 | AI97: =IF($S97="","",$AE97&IF(TRIM($N97)="",""," | "&TRIM($N97))&IF(OR(TRIM($O97)="",TRIM($O97)="-"),""," | "&TRIM($O97))) -> 3.06.38 | 1" | AA1B
B98: 8.3.6 | C98: 3.06.39 | D98: - | E98: - | F98: - | G98: =+"SUMINISTRO Y MONTAJE DE "&X98 -> SUMINISTRO Y MONTAJE DE SOCKOLET 3000# STL A105 | N98: 1½" | O98: AA1B | P98: =IF(TRIM($G98)="","",TRIM($G98)&IF(OR(TRIM($N98)="",TRIM($N98)="-"),""," - "&TRIM($N98))&IF(OR(TRIM($O98)="",TRIM($O98)="-"),""," - "&TRIM($O98))&IF(ISNUMBER(SEARCH("SUMINISTRO",$G98))," - "&$AK$13,IF(ISNUMBER(SEARCH("MONTAJE",$G98))," - "&$AK$12,""))) -> SUMINISTRO Y MONTAJE DE SOCKOLET 3000# STL A105 - 1½" - AA1B - Suministro Contratista | Q98: En alcance | R98: {=IF($G98="","",IFERROR(VLOOKUP(LOOKUP(2,1/(($B$14:$B98<>"")*($C$14:$C98="")),$B$14:$B98),$AM$12:$AN$16,2,FALSE),""))} -> Mecanica | S98: 5 | T98: UND | U98: =+APU!K1228 -> 68.611754 | V98: =U98*S98 -> 343.05877 | X98: SOCKOLET 3000# STL A105 | AB98: {=IF($S98="","",SUMIFS(APU!$O:$O,APU!$A:$A,IF(ISNUMBER($C98),REPLACE(TEXT($C98,"0.0000"),5,0,"."),$C98),APU!$G:$G,"hh")/MAX(1,SUMPRODUCT(($C$15:$C$262=$C98)*($S$15:$S$262<>""))))} -> 12.4 | AC98: =IF($S98="","",IFERROR(VLOOKUP($AE98,APU!$V:$X,2,FALSE),"")) -> 10 | AD98: =IF(OR($S98="",$AC98="",N($AC98)=0),"",$S98/$AC98) -> 0.5 | AE98: =IF($C98="","",IF(ISNUMBER($C98),REPLACE(TEXT($C98,"0.0000"),5,0,"."),$C98)) -> 3.06.39 | AH98: =IF($S98="","",$AB98*N($AG98)) -> 0 | AI98: =IF($S98="","",$AE98&IF(TRIM($N98)="",""," | "&TRIM($N98))&IF(OR(TRIM($O98)="",TRIM($O98)="-"),""," | "&TRIM($O98))) -> 3.06.39 | 1½" | AA1B
B99: 8.3.6 | C99: 3.06.40 | D99: - | E99: - | F99: - | G99: =+"SUMINISTRO Y MONTAJE DE "&X99 -> SUMINISTRO Y MONTAJE DE SOCKOLET 3000# STL A105 | N99: 2" | O99: AA1B | P99: =IF(TRIM($G99)="","",TRIM($G99)&IF(OR(TRIM($N99)="",TRIM($N99)="-"),""," - "&TRIM($N99))&IF(OR(TRIM($O99)="",TRIM($O99)="-"),""," - "&TRIM($O99))&IF(ISNUMBER(SEARCH("SUMINISTRO",$G99))," - "&$AK$13,IF(ISNUMBER(SEARCH("MONTAJE",$G99))," - "&$AK$12,""))) -> SUMINISTRO Y MONTAJE DE SOCKOLET 3000# STL A105 - 2" - AA1B - Suministro Contratista | Q99: En alcance | R99: {=IF($G99="","",IFERROR(VLOOKUP(LOOKUP(2,1/(($B$14:$B99<>"")*($C$14:$C99="")),$B$14:$B99),$AM$12:$AN$16,2,FALSE),""))} -> Mecanica | S99: 3 | T99: UND | U99: =+APU!K1249 -> 84.983393 | V99: =U99*S99 -> 254.95018 | X99: SOCKOLET 3000# STL A105 | AB99: {=IF($S99="","",SUMIFS(APU!$O:$O,APU!$A:$A,IF(ISNUMBER($C99),REPLACE(TEXT($C99,"0.0000"),5,0,"."),$C99),APU!$G:$G,"hh")/MAX(1,SUMPRODUCT(($C$15:$C$262=$C99)*($S$15:$S$262<>""))))} -> 9.3 | AC99: =IF($S99="","",IFERROR(VLOOKUP($AE99,APU!$V:$X,2,FALSE),"")) -> 8 | AD99: =IF(OR($S99="",$AC99="",N($AC99)=0),"",$S99/$AC99) -> 0.375 | AE99: =IF($C99="","",IF(ISNUMBER($C99),REPLACE(TEXT($C99,"0.0000"),5,0,"."),$C99)) -> 3.06.40 | AH99: =IF($S99="","",$AB99*N($AG99)) -> 0 | AI99: =IF($S99="","",$AE99&IF(TRIM($N99)="",""," | "&TRIM($N99))&IF(OR(TRIM($O99)="",TRIM($O99)="-"),""," | "&TRIM($O99))) -> 3.06.40 | 2" | AA1B
B100: 8.3.6 | C100: 3.06.41 | D100: - | E100: - | F100: - | G100: =+"SUMINISTRO Y MONTAJE DE "&X100 -> SUMINISTRO Y MONTAJE DE ELL 90 DEG 3000# SW STL A105 | N100: ½" | O100: AA1B | P100: =IF(TRIM($G100)="","",TRIM($G100)&IF(OR(TRIM($N100)="",TRIM($N100)="-"),""," - "&TRIM($N100))&IF(OR(TRIM($O100)="",TRIM($O100)="-"),""," - "&TRIM($O100))&IF(ISNUMBER(SEARCH("SUMINISTRO",$G100))," - "&$AK$13,IF(ISNUMBER(SEARCH("MONTAJE",$G100))," - "&$AK$12,""))) -> SUMINISTRO Y MONTAJE DE ELL 90 DEG 3000# SW STL A105 - ½" - AA1B - Suministro Contratista | Q100: En alcance | R100: {=IF($G100="","",IFERROR(VLOOKUP(LOOKUP(2,1/(($B$14:$B100<>"")*($C$14:$C100="")),$B$14:$B100),$AM$12:$AN$16,2,FALSE),""))} -> Mecanica | S100: 4 | T100: UND | U100: =+APU!K1270 -> 34.262176 | V100: =U100*S100 -> 137.0487 | X100: ELL 90 DEG 3000# SW STL A105 | AB100: {=IF($S100="","",SUMIFS(APU!$O:$O,APU!$A:$A,IF(ISNUMBER($C100),REPLACE(TEXT($C100,"0.0000"),5,0,"."),$C100),APU!$G:$G,"hh")/MAX(1,SUMPRODUCT(($C$15:$C$262=$C100)*($S$15:$S$262<>""))))} -> 8.2666667 | AC100: =IF($S100="","",IFERROR(VLOOKUP($AE100,APU!$V:$X,2,FALSE),"")) -> 12 | AD100: =IF(OR($S100="",$AC100="",N($AC100)=0),"",$S100/$AC100) -> 0.33333333 | AE100: =IF($C100="","",IF(ISNUMBER($C100),REPLACE(TEXT($C100,"0.0000"),5,0,"."),$C100)) -> 3.06.41 | AH100: =IF($S100="","",$AB100*N($AG100)) -> 0 | AI100: =IF($S100="","",$AE100&IF(TRIM($N100)="",""," | "&TRIM($N100))&IF(OR(TRIM($O100)="",TRIM($O100)="-"),""," | "&TRIM($O100))) -> 3.06.41 | ½" | AA1B
B101: 8.3.6 | C101: 3.06.42 | D101: - | E101: - | F101: - | G101: =+"SUMINISTRO Y MONTAJE DE "&X101 -> SUMINISTRO Y MONTAJE DE ELL 90 DEG 3000# SW STL A105 | N101: 1" | O101: AA1B | P101: =IF(TRIM($G101)="","",TRIM($G101)&IF(OR(TRIM($N101)="",TRIM($N101)="-"),""," - "&TRIM($N101))&IF(OR(TRIM($O101)="",TRIM($O101)="-"),""," - "&TRIM($O101))&IF(ISNUMBER(SEARCH("SUMINISTRO",$G101))," - "&$AK$13,IF(ISNUMBER(SEARCH("MONTAJE",$G101))," - "&$AK$12,""))) -> SUMINISTRO Y MONTAJE DE ELL 90 DEG 3000# SW STL A105 - 1" - AA1B - Suministro Contratista | Q101: En alcance | R101: {=IF($G101="","",IFERROR(VLOOKUP(LOOKUP(2,1/(($B$14:$B101<>"")*($C$14:$C101="")),$B$14:$B101),$AM$12:$AN$16,2,FALSE),""))} -> Mecanica | S101: 38 | T101: UND | U101: =+APU!K1290 -> 39.281662 | V101: =U101*S101 -> 1492.7032 | X101: ELL 90 DEG 3000# SW STL A105 | AB101: {=IF($S101="","",SUMIFS(APU!$O:$O,APU!$A:$A,IF(ISNUMBER($C101),REPLACE(TEXT($C101,"0.0000"),5,0,"."),$C101),APU!$G:$G,"hh")/MAX(1,SUMPRODUCT(($C$15:$C$262=$C101)*($S$15:$S$262<>""))))} -> 78.533333 | AC101: =IF($S101="","",IFERROR(VLOOKUP($AE101,APU!$V:$X,2,FALSE),"")) -> 12 | AD101: =IF(OR($S101="",$AC101="",N($AC101)=0),"",$S101/$AC101) -> 3.1666667 | AE101: =IF($C101="","",IF(ISNUMBER($C101),REPLACE(TEXT($C101,"0.0000"),5,0,"."),$C101)) -> 3.06.42 | AH101: =IF($S101="","",$AB101*N($AG101)) -> 0 | AI101: =IF($S101="","",$AE101&IF(TRIM($N101)="",""," | "&TRIM($N101))&IF(OR(TRIM($O101)="",TRIM($O101)="-"),""," | "&TRIM($O101))) -> 3.06.42 | 1" | AA1B
...

Sheet APU
O1: hh | Q1: QPS S | R1: APU suma P | S1: Dif | V1: Cód. partida (norm.) | W1: Rendimiento / DIA | X1: Unidad rendimiento
C2: Partida | D2: =QPS!C16 -> 1.0101 | E2: =QPS!G16 -> Movilización y desmovilización | Q2: =QPS!V16 -> 6797.26 | R2: =SUM(P2:P14) -> 6797.26 | S2: =Q2-R2 -> 0 | V2: =IF($D2="","",IF(ISNUMBER($D2),REPLACE(TEXT($D2,"0.0000"),5,0,"."),TRIM($D2))) -> 1.01.01 | W2: =$F3 -> 0.2 | X2: =$D3 -> glb/DIA
C3: Rendimiento | D3: glb/DIA | E3: MO. | F3: 0.2 | G3: EQ. | H3: =F3 -> 0.2 | J3: Costo unitario directo por : glb | K3: =+K8+K13 -> 6797.26 | V3: =IF($D15="","",IF(ISNUMBER($D15),REPLACE(TEXT($D15,"0.0000"),5,0,"."),TRIM($D15))) -> 1.01.02 | W3: =$F16 -> 0.5 | X3: =$D16 -> glb/DIA
C4: Código | D4: Descripción Recurso | G4: Unidad | H4: Cuadrilla | I4: Cantidad | J4: Precio U$ | K4: Parcial U$ | V4: =IF($D32="","",IF(ISNUMBER($D32),REPLACE(TEXT($D32,"0.0000"),5,0,"."),TRIM($D32))) -> 1.01.03 | W4: =$F33 -> 1 | X4: =$D33 -> glb/DIA
D5: Mano de Obra | V5: =IF($D40="","",IF(ISNUMBER($D40),REPLACE(TEXT($D40,"0.0000"),5,0,"."),TRIM($D40))) -> 2.01.01 | W5: =$F41 -> 0.4 | X5: =$D41 -> m3/DIA
A6: 1.01.01 | B6: Mano de Obra | C6: 0101010002 | D6: CAPATAZ | G6: hh | H6: 1 | I6: =H6*8/$F$3 -> 40 | J6: 10.51 | K6: =I6*J6 -> 420.4 | M6: 1 | N6: Glb. | O6: =I6*M6 -> 40 | P6: =O6*J6 -> 420.4 | V6: =IF($D56="","",IF(ISNUMBER($D56),REPLACE(TEXT($D56,"0.0000"),5,0,"."),TRIM($D56))) -> 2.02.01 | W6: =$F57 -> 15 | X6: =$D57 -> m3/DIA
A7: 1.01.01 | B7: Mano de Obra | C7: 01010300030005 | D7: AYUDANTE | G7: hh | H7: 4 | I7: =H7*8/$F$3 -> 160 | J7: 6.88 | K7: =I7*J7 -> 1100.8 | M7: 1 | N7: Glb. | O7: =I7*M7 -> 160 | P7: =O7*J7 -> 1100.8 | V7: =IF($D74="","",IF(ISNUMBER($D74),REPLACE(TEXT($D74,"0.0000"),5,0,"."),TRIM($D74))) -> 2.03.01 | W7: =$F75 -> 15 | X7: =$D75 -> m3/DIA
K8: =SUM(K6:K7) -> 1521.2 | V8: =IF($D95="","",IF(ISNUMBER($D95),REPLACE(TEXT($D95,"0.0000"),5,0,"."),TRIM($D95))) -> 2.03.02 | W8: =$F96 -> 18 | X8: =$D96 -> m2/DIA
D9: Equipos | V9: =IF($D116="","",IF(ISNUMBER($D116),REPLACE(TEXT($D116,"0.0000"),5,0,"."),TRIM($D116))) -> 2.03.03 | W9: =$F117 -> 250 | X9: =$D117 -> kg/DIA
A10: 1.01.01 | B10: Equipos | C10: 0301010006 | D10: HERRAMIENTAS MANUALES | G10: %mo | I10: 5 | J10: =K8 -> 1521.2 | K10: =I10*J10/100 -> 76.06 | M10: 1 | N10: Glb. | O10: =I10*M10 -> 5 | P10: =O10*J10/100 -> 76.06 | V10: =IF($D134="","",IF(ISNUMBER($D134),REPLACE(TEXT($D134,"0.0000"),5,0,"."),TRIM($D134))) -> 2.04.01 | W10: =$F135 -> 20 | X10: =$D135 -> und/DIA
A11: 1.01.01 | B11: Equipos | D11: CAMION GRUA DE 12TN | G11: hm | H11: 1 | I11: =H11*8/$H$3 -> 40 | J11: 95 | K11: =I11*J11 -> 3800 | M11: 1 | N11: Glb. | O11: =I11*M11 -> 40 | P11: =O11*J11 -> 3800 | V11: =IF($D151="","",IF(ISNUMBER($D151),REPLACE(TEXT($D151,"0.0000"),5,0,"."),TRIM($D151))) -> 2.04.02 | W11: =$F152 -> 20 | X11: =$D152 -> m/DIA
A12: 1.01.01 | B12: Equipos | D12: CAMION BARANDA (4TN) | G12: hm | H12: 1 | I12: =H12*8/$H$3 -> 40 | J12: 35 | K12: =I12*J12 -> 1400 | M12: 1 | N12: Glb. | O12: =I12*M12 -> 40 | P12: =O12*J12 -> 1400 | V12: =IF($D168="","",IF(ISNUMBER($D168),REPLACE(TEXT($D168,"0.0000"),5,0,"."),TRIM($D168))) -> 2.04.03 | W12: =$F169 -> 250 | X12: =$D169 -> kg/DIA
K13: =SUM(K10:K12) -> 5276.06 | V13: =IF($D189="","",IF(ISNUMBER($D189),REPLACE(TEXT($D189,"0.0000"),5,0,"."),TRIM($D189))) -> 2.04.04 | W13: =$F190 -> 250 | X13: =$D190 -> kg/DIA
V14: =IF($D210="","",IF(ISNUMBER($D210),REPLACE(TEXT($D210,"0.0000"),5,0,"."),TRIM($D210))) -> 2.04.05 | W14: =$F211 -> 10 | X14: =$D211 -> l/DIA
C15: Partida | D15: =QPS!C17 -> 1.0102 | E15: =QPS!G17 -> Trazo y replanteo (preliminar y durante la obra) | Q15: =QPS!V17 -> 518.25029 | R15: =SUM(P15:P31) -> 518.25029 | S15: =Q15-R15 -> 0 | V15: =IF($D228="","",IF(ISNUMBER($D228),REPLACE(TEXT($D228,"0.0000"),5,0,"."),TRIM($D228))) -> 2.04.06 | W15: =$F229 -> 15 | X15: =$D229 -> und/DIA
C16: Rendimiento | D16: glb/DIA | E16: MO. | F16: 0.5 | G16: EQ. | H16: =F16 -> 0.5 | J16: Costo unitario directo por : glb | K16: =+K21+K26+K30 -> 518.25029 | V16: =IF($D245="","",IF(ISNUMBER($D245),REPLACE(TEXT($D245,"0.0000"),5,0,"."),TRIM($D245))) -> 2.04.07 | W16: =$F246 -> 15 | X16: =$D246 -> und/DIA
C17: Código | D17: Descripción Recurso | G17: Unidad | H17: Cuadrilla | I17: Cantidad | J17: Precio U$ | K17: Parcial U$ | V17: =IF($D262="","",IF(ISNUMBER($D262),REPLACE(TEXT($D262,"0.0000"),5,0,"."),TRIM($D262))) -> 2.04.08 | W17: =$F263 -> 15 | X17: =$D263 -> und/DIA
D18: Mano de Obra | V18: =IF($D279="","",IF(ISNUMBER($D279),REPLACE(TEXT($D279,"0.0000"),5,0,"."),TRIM($D279))) -> 2.04.09 | W18: =$F280 -> 10 | X18: =$D280 -> und/DIA
A19: 1.01.02 | B19: Mano de Obra | C19: 0101010002 | D19: CAPATAZ | G19: hh | H19: 1 | I19: =H19*8/$F$16 -> 16 | J19: 10.51 | K19: =I19*J19 -> 168.16 | M19: 1 | N19: Glb. | O19: =I19*M19 -> 16 | P19: =O19*J19 -> 168.16 | V19: =IF($D295="","",IF(ISNUMBER($D295),REPLACE(TEXT($D295,"0.0000"),5,0,"."),TRIM($D295))) -> 2.04.10 | W19: =$F296 -> 15 | X19: =$D296 -> m2/DIA
A20: 1.01.02 | B20: Mano de Obra | C20: 01010300030005 | D20: AYUDANTE | G20: hh | H20: 2 | I20: =H20*8/$F$16 -> 32 | J20: 6.88 | K20: =I20*J20 -> 220.16 | M20: 1 | N20: Glb. | O20: =I20*M20 -> 32 | P20: =O20*J20 -> 220.16 | V20: =IF($D311="","",IF(ISNUMBER($D311),REPLACE(TEXT($D311,"0.0000"),5,0,"."),TRIM($D311))) -> 3.01.01 | W20: =$F312 -> 0.1 | X20: =$D312 -> glb/DIA
K21: =SUM(K19:K20) -> 388.32 | V21: =IF($D326="","",IF(ISNUMBER($D326),REPLACE(TEXT($D326,"0.0000"),5,0,"."),TRIM($D326))) -> 3.01.02 | W21: =$F327 -> 0.5 | X21: =$D327 -> glb/DIA
D22: Materiales | V22: =IF($D342="","",IF(ISNUMBER($D342),REPLACE(TEXT($D342,"0.0000"),5,0,"."),TRIM($D342))) -> 3.01.03 | W22: =$F343 -> 0.25 | X22: =$D343 -> glb/DIA
A23: 1.01.02 | B23: Materiales | D23: YESO | G23: bolsa | I23: 2 | J23: =17.9/3.5 -> 5.1142857 | K23: =I23*J23 -> 10.228571 | M23: 1 | N23: Glb. | O23: =I23*M23 -> 2 | P23: =O23*J23 -> 10.228571 | V23: =IF($D358="","",IF(ISNUMBER($D358),REPLACE(TEXT($D358,"0.0000"),5,0,"."),TRIM($D358))) -> 3.02.01 | W23: =$F359 -> 0.5 | X23: =$D359 -> und/DIA
A24: 1.01.02 | B24: Materiales | D24: ESTACAS | G24: und | I24: 50 | J24: =4.35/3.5 -> 1.2428571 | K24: =I24*J24 -> 62.142857 | M24: 1 | N24: Glb. | O24: =I24*M24 -> 50 | P24: =O24*J24 -> 62.142857 | V24: =IF($D374="","",IF(ISNUMBER($D374),REPLACE(TEXT($D374,"0.0000"),5,0,"."),TRIM($D374))) -> 3.03.01 | W24: =$F375 -> 0.15 | X24: =$D375 -> glb/DIA
A25: 1.01.02 | B25: Materiales | D25: PINTURA AEROSOL | G25: und | I25: 5 | J25: =16.7/3.5 -> 4.7714286 | K25: =I25*J25 -> 23.857143 | M25: 1 | N25: Glb. | O25: =I25*M25 -> 5 | P25: =O25*J25 -> 23.857143 | V25: =IF($D391="","",IF(ISNUMBER($D391),REPLACE(TEXT($D391,"0.0000"),5,0,"."),TRIM($D391))) -> 3.04.01 | W25: =$F392 -> 1 | X25: =$D392 -> und/DIA
K26: =SUM(K23:K25) -> 96.228571 | V26: =IF($D408="","",IF(ISNUMBER($D408),REPLACE(TEXT($D408,"0.0000"),5,0,"."),TRIM($D408))) -> 3.04.02 | W26: =$F409 -> 1 | X26: =$D409 -> und/DIA
D27: Equipos | V27: =IF($D425="","",IF(ISNUMBER($D425),REPLACE(TEXT($D425,"0.0000"),5,0,"."),TRIM($D425))) -> 3.04.03 | W27: =$F426 -> 1 | X27: =$D426 -> und/DIA
A28: 1.01.02 | B28: Equipos | C28: 0301010006 | D28: HERRAMIENTAS MANUALES | G28: %mo | I28: 5 | J28: =K21 -> 388.32 | K28: =I28*J28/100 -> 19.416 | M28: 1 | N28: Glb. | O28: =I28*M28 -> 5 | P28: =O28*J28/100 -> 19.416 | V28: =IF($D442="","",IF(ISNUMBER($D442),REPLACE(TEXT($D442,"0.0000"),5,0,"."),TRIM($D442))) -> 3.04.04 | W28: =$F443 -> 1 | X28: =$D443 -> und/DIA
A29: 1.01.02 | B29: Equipos | D29: NIVEL DE INGENIERO | G29: hm | H29: 1 | I29: =H29*8/H16 -> 16 | J29: =25/3.5/8 -> 0.89285714 | K29: =I29*J29 -> 14.285714 | M29: 1 | N29: Glb. | O29: =I29*M29 -> 16 | P29: =O29*J29 -> 14.285714 | V29: =IF($D459="","",IF(ISNUMBER($D459),REPLACE(TEXT($D459,"0.0000"),5,0,"."),TRIM($D459))) -> 3.04.05 | W29: =$F460 -> 1 | X29: =$D460 -> und/DIA
K30: =SUM(K28:K29) -> 33.701714 | V30: =IF($D477="","",IF(ISNUMBER($D477),REPLACE(TEXT($D477,"0.0000"),5,0,"."),TRIM($D477))) -> 3.05.01 | W30: =$F478 -> 1 | X30: =$D478 -> und/DIA
V31: =IF($D494="","",IF(ISNUMBER($D494),REPLACE(TEXT($D494,"0.0000"),5,0,"."),TRIM($D494))) -> 3.05.02 | W31: =$F495 -> 1 | X31: =$D495 -> und/DIA
C32: Partida | D32: =QPS!C18 -> 1.0103 | E32: =QPS!G18 -> Limpieza del área de trabajo | Q32: =QPS!V18 -> 236.976 | R32: =SUM(P32:P39) -> 236.976 | S32: =Q32-R32 -> 0 | V32: =IF($D511="","",IF(ISNUMBER($D511),REPLACE(TEXT($D511,"0.0000"),5,0,"."),TRIM($D511))) -> 3.06.01 | W32: =$F512 -> 15 | X32: =$D512 -> m/DIA
C33: Rendimiento | D33: glb/DIA | E33: MO. | F33: 1 | G33: EQ. | H33: =F33 -> 1 | J33: Costo unitario directo por : glb | K33: =+K38 -> 236.976 | V33: =IF($D532="","",IF(ISNUMBER($D532),REPLACE(TEXT($D532,"0.0000"),5,0,"."),TRIM($D532))) -> 3.06.02 | W33: =$F533 -> 8 | X33: =$D533 -> m/DIA
C34: Código | D34: Descripción Recurso | G34: Unidad | H34: Cuadrilla | I34: Cantidad | J34: Precio U$ | K34: Parcial U$ | V34: =IF($D553="","",IF(ISNUMBER($D553),REPLACE(TEXT($D553,"0.0000"),5,0,"."),TRIM($D553))) -> 3.06.03 | W34: =$F554 -> 4 | X34: =$D554 -> und/DIA
D35: Mano de Obra | V35: =IF($D569="","",IF(ISNUMBER($D569),REPLACE(TEXT($D569,"0.0000"),5,0,"."),TRIM($D569))) -> 3.06.04 | W35: =$F570 -> 4 | X35: =$D570 -> und/DIA
A36: 1.01.03 | B36: Mano de Obra | C36: 0101010002 | D36: CAPATAZ | G36: hh | H36: 0.2 | I36: =H36*8/$F$33 -> 1.6 | J36: 10.51 | K36: =I36*J36 -> 16.816 | M36: 1 | N36: Glb. | O36: =I36*M36 -> 1.6 | P36: =O36*J36 -> 16.816 | V36: =IF($D585="","",IF(ISNUMBER($D585),REPLACE(TEXT($D585,"0.0000"),5,0,"."),TRIM($D585))) -> 3.06.05 | W36: =$F586 -> 6 | X36: =$D586 -> und/DIA
A37: 1.01.03 | B37: Mano de Obra | C37: 01010300030005 | D37: AYUDANTE | G37: hh | H37: 4 | I37: =H37*8/$F$33 -> 32 | J37: 6.88 | K37: =I37*J37 -> 220.16 | M37: 1 | N37: Glb. | O37: =I37*M37 -> 32 | P37: =O37*J37 -> 220.16 | V37: =IF($D601="","",IF(ISNUMBER($D601),REPLACE(TEXT($D601,"0.0000"),5,0,"."),TRIM($D601))) -> 3.06.06 | W37: =$F602 -> 6 | X37: =$D602 -> und/DIA
K38: =SUM(K36:K37) -> 236.976 | V38: =IF($D621="","",IF(ISNUMBER($D621),REPLACE(TEXT($D621,"0.0000"),5,0,"."),TRIM($D621))) -> 3.06.07 | W38: =$F622 -> 6 | X38: =$D622 -> und/DIA
V39: =IF($D641="","",IF(ISNUMBER($D641),REPLACE(TEXT($D641,"0.0000"),5,0,"."),TRIM($D641))) -> 3.06.08 | W39: =$F642 -> 6 | X39: =$D642 -> und/DIA
C40: Partida | D40: =QPS!C21 -> 2.0101 | E40: =QPS!G21 -> Demolición de bases e = 50 cm | Q40: =QPS!V21 -> 538.68928 | R40: =SUM(P40:P55) -> 538.68928 | S40: =Q40-R40 -> 0 | V40: =IF($D661="","",IF(ISNUMBER($D661),REPLACE(TEXT($D661,"0.0000"),5,0,"."),TRIM($D661))) -> 3.06.09 | W40: =$F662 -> 6 | X40: =$D662 -> und/DIA
C41: Rendimiento | D41: m3/DIA | E41: MO. | F41: 0.4 | G41: EQ. | H41: =F41 -> 0.4 | J41: Costo unitario directo por : m3 | K41: =+K47+K50+K54 -> 420.851 | V41: =IF($D681="","",IF(ISNUMBER($D681),REPLACE(TEXT($D681,"0.0000"),5,0,"."),TRIM($D681))) -> 3.06.10 | W41: =$F682 -> 7 | X41: =$D682 -> und/DIA
C42: Código | D42: Descripción Recurso | G42: Unidad | H42: Cuadrilla | I42: Cantidad | J42: Precio U$ | K42: Parcial U$ | V42: =IF($D701="","",IF(ISNUMBER($D701),REPLACE(TEXT($D701,"0.0000"),5,0,"."),TRIM($D701))) -> 3.06.11 | W42: =$F702 -> 7 | X42: =$D702 -> und/DIA
D43: Mano de Obra | M43: =0.5*0.5*0.5*3 -> 0.375 | V43: =IF($D721="","",IF(ISNUMBER($D721),REPLACE(TEXT($D721,"0.0000"),5,0,"."),TRIM($D721))) -> 3.06.12 | W43: =$F722 -> 6 | X43: =$D722 -> und/DIA
A44: 2.01.01 | B44: Mano de Obra | C44: 0101010002 | D44: CAPATAZ | G44: hh | H44: 0.1 | I44: =H44*8/$F$41 -> 2 | J44: 10.51 | K44: =I44*J44 -> 21.02 | M44: 1.28 | N44: m3 | O44: =I44*M44 -> 2.56 | P44: =O44*J44 -> 26.9056 | V44: =IF($D741="","",IF(ISNUMBER($D741),REPLACE(TEXT($D741,"0.0000"),5,0,"."),TRIM($D741))) -> 3.06.13 | W44: =$F742 -> 6 | X44: =$D742 -> und/DIA
A45: 2.01.01 | B45: Mano de Obra | D45: OPERARIO | G45: hh | H45: 1 | I45: =H45*8/$F$41 -> 20 | J45: 9.3 | K45: =I45*J45 -> 186 | M45: 1.28 | N45: m3 | O45: =I45*M45 -> 25.6 | P45: =O45*J45 -> 238.08 | V45: =IF($D761="","",IF(ISNUMBER($D761),REPLACE(TEXT($D761,"0.0000"),5,0,"."),TRIM($D761))) -> 3.06.14 | W45: =$F762 -> 5 | X45: =$D762 -> und/DIA
A46: 2.01.01 | B46: Mano de Obra | C46: 01010300030005 | D46: AYUDANTE | G46: hh | H46: 1 | I46: =H46*8/$F$41 -> 20 | J46: 6.88 | K46: =I46*J46 -> 137.6 | M46: 1.28 | N46: m3 | O46: =I46*M46 -> 25.6 | P46: =O46*J46 -> 176.128 | V46: =IF($D781="","",IF(ISNUMBER($D781),REPLACE(TEXT($D781,"0.0000"),5,0,"."),TRIM($D781))) -> 3.06.15 | W46: =$F782 -> 5 | X46: =$D782 -> und/DIA
K47: =SUM(K44:K46) -> 344.62 | V47: =IF($D801="","",IF(ISNUMBER($D801),REPLACE(TEXT($D801,"0.0000"),5,0,"."),TRIM($D801))) -> 3.06.16 | W47: =$F802 -> 6 | X47: =$D802 -> und/DIA
D48: Materiales | V48: =IF($D821="","",IF(ISNUMBER($D821),REPLACE(TEXT($D821,"0.0000"),5,0,"."),TRIM($D821))) -> 3.06.17 | W48: =$F822 -> 25 | X48: =$D822 -> m/DIA
A49: 2.01.01 | B49: Materiales | D49: CONSUMIBLES | G49: glb | I49: 0.05 | J49: 100 | K49: =I49*J49 -> 5 | M49: 1.28 | N49: m3 | O49: =I49*M49 -> 0.064 | P49: =O49*J49 -> 6.4 | V49: =IF($D842="","",IF(ISNUMBER($D842),REPLACE(TEXT($D842,"0.0000"),5,0,"."),TRIM($D842))) -> 3.06.18 | W49: =$F843 -> 25 | X49: =$D843 -> m/DIA
K50: =SUM(K49:K49) -> 5 | V50: =IF($D863="","",IF(ISNUMBER($D863),REPLACE(TEXT($D863,"0.0000"),5,0,"."),TRIM($D863))) -> 3.06.19 | W50: =$F864 -> 25 | X50: =$D864 -> m/DIA
D51: Equipos | V51: =IF($D884="","",IF(ISNUMBER($D884),REPLACE(TEXT($D884,"0.0000"),5,0,"."),TRIM($D884))) -> 3.06.20 | W51: =$F885 -> 25 | X51: =$D885 -> m/DIA
A52: 2.01.01 | B52: Equipos | C52: 0301010006 | D52: HERRAMIENTAS MANUALES | G52: %mo | I52: 5 | J52: =K47 -> 344.62 | K52: =I52*J52/100 -> 17.231 | M52: 1.28 | N52: m3 | O52: =I52*M52 -> 6.4 | P52: =O52*J52/100 -> 22.05568 | V52: =IF($D905="","",IF(ISNUMBER($D905),REPLACE(TEXT($D905,"0.0000"),5,0,"."),TRIM($D905))) -> 3.06.21 | W52: =$F906 -> 10 | X52: =$D906 -> und/DIA
A53: 2.01.01 | B53: Equipos | D53: ROTOMARTILLO | G53: hm | H53: 1 | I53: =H53*8/H41 -> 20 | J53: 2.7 | K53: =I53*J53 -> 54 | M53: 1.28 | N53: m3 | O53: =I53*M53 -> 25.6 | P53: =O53*J53 -> 69.12 | V53: =IF($D925="","",IF(ISNUMBER($D925),REPLACE(TEXT($D925,"0.0000"),5,0,"."),TRIM($D925))) -> 3.06.22 | W53: =$F926 -> 10 | X53: =$D926 -> und/DIA
K54: =SUM(K52:K53) -> 71.231 | V54: =IF($D945="","",IF(ISNUMBER($D945),REPLACE(TEXT($D945,"0.0000"),5,0,"."),TRIM($D945))) -> 3.06.23 | W54: =$F946 -> 10 | X54: =$D946 -> und/DIA
V55: =IF($D965="","",IF(ISNUMBER($D965),REPLACE(TEXT($D965,"0.0000"),5,0,"."),TRIM($D965))) -> 3.06.24 | W55: =$F966 -> 8 | X55: =$D966 -> und/DIA
C56: Partida | D56: =QPS!C23 -> 2.0201 | E56: =QPS!G23 -> Concreto simple f'c=100 kg/cm2 | Q56: =QPS!V23 -> 21.551559 | R56: =SUM(P56:P73) -> 21.551559 | S56: =Q56-R56 -> 0 | V56: =IF($D981="","",IF(ISNUMBER($D981),REPLACE(TEXT($D981,"0.0000"),5,0,"."),TRIM($D981))) -> 3.06.25 | W56: =$F982 -> 8 | X56: =$D982 -> und/DIA
C57: Rendimiento | D57: m3/DIA | E57: MO. | F57: 15 | G57: EQ. | H57: =F57 -> 15 | J57: Costo unitario directo por : m3 | K57: =+K64+K68+K72 -> 268.55525 | V57: =IF($D998="","",IF(ISNUMBER($D998),REPLACE(TEXT($D998,"0.0000"),5,0,"."),TRIM($D998))) -> 3.06.26 | W57: =$F999 -> 8 | X57: =$D999 -> und/DIA
C58: Código | D58: Descripción Recurso | G58: Unidad | H58: Cuadrilla | I58: Cantidad | J58: Precio U$ | K58: Parcial U$ | V58: =IF($D1014="","",IF(ISNUMBER($D1014),REPLACE(TEXT($D1014,"0.0000"),5,0,"."),TRIM($D1014))) -> 3.06.27 | W58: =$F1015 -> 8 | X58: =$D1015 -> und/DIA
D59: Mano de Obra | V59: =IF($D1030="","",IF(ISNUMBER($D1030),REPLACE(TEXT($D1030,"0.0000"),5,0,"."),TRIM($D1030))) -> 3.06.28 | W59: =$F1031 -> 4 | X59: =$D1031 -> und/DIA
A60: 2.02.01 | B60: Mano de Obra | C60: 0101010002 | D60: CAPATAZ | G60: hh | H60: 0.2 | I60: =H60*8/$F$57 -> 0.10666667 | J60: 10.51 | K60: =I60*J60 -> 1.1210667 | M60: 0.08025 | N60: m3 | O60: =I60*M60 -> 0.00856 | P60: =O60*J60 -> 0.0899656 | V60: =IF($D1050="","",IF(ISNUMBER($D1050),REPLACE(TEXT($D1050,"0.0000"),5,0,"."),TRIM($D1050))) -> 3.06.29 | W60: =$F1051 -> 4 | X60: =$D1051 -> und/DIA
A61: 2.02.01 | B61: Mano de Obra | D61: OPERARIO | G61: hh | H61: 2 | I61: =H61*8/$F$57 -> 1.0666667 | J61: 9.3 | K61: =I61*J61 -> 9.92 | M61: 0.08025 | N61: m3 | O61: =I61*M61 -> 0.0856 | P61: =O61*J61 -> 0.79608 | V61: =IF($D1070="","",IF(ISNUMBER($D1070),REPLACE(TEXT($D1070,"0.0000"),5,0,"."),TRIM($D1070))) -> 3.06.30 | W61: =$F1071 -> 4 | X61: =$D1071 -> und/DIA
A62: 2.02.01 | B62: Mano de Obra | D62: OFICIAL | G62: hh | H62: 2 | I62: =H62*8/$F$57 -> 1.0666667 | J62: 7.54 | K62: =I62*J62 -> 8.0426667 | M62: 0.08025 | N62: m3 | O62: =I62*M62 -> 0.0856 | P62: =O62*J62 -> 0.645424 | V62: =IF($D1090="","",IF(ISNUMBER($D1090),REPLACE(TEXT($D1090,"0.0000"),5,0,"."),TRIM($D1090))) -> 3.06.31 | W62: =$F1091 -> 3 | X62: =$D1091 -> und/DIA
A63: 2.02.01 | B63: Mano de Obra | C63: 01010300030005 | D63: AYUDANTE | G63: hh | H63: 4 | I63: =H63*8/$F$57 -> 2.1333333 | J63: 6.88 | K63: =I63*J63 -> 14.677333 | M63: 0.08025 | N63: m3 | O63: =I63*M63 -> 0.1712 | P63: =O63*J63 -> 1.177856 | V63: =IF($D1110="","",IF(ISNUMBER($D1110),REPLACE(TEXT($D1110,"0.0000"),5,0,"."),TRIM($D1110))) -> 3.06.32 | W63: =$F1111 -> 50 | X63: =$D1111 -> und/DIA
K64: =SUM(K60:K63) -> 33.761067 | V64: =IF($D1126="","",IF(ISNUMBER($D1126),REPLACE(TEXT($D1126,"0.0000"),5,0,"."),TRIM($D1126))) -> 3.06.33 | W64: =$F1127 -> 50 | X64: =$D1127 -> und/DIA
D65: Materiales | V65: =IF($D1142="","",IF(ISNUMBER($D1142),REPLACE(TEXT($D1142,"0.0000"),5,0,"."),TRIM($D1142))) -> 3.06.34 | W65: =$F1143 -> 50 | X65: =$D1143 -> und/DIA
A66: 2.02.01 | B66: Materiales | D66: CONCRETO PREMEZCLADO f'c=100 kg/m2 | G66: m3 | I66: 1.05 | J66: 220 | K66: =I66*J66 -> 231 | M66: 0.08025 | N66: m3 | O66: =I66*M66 -> 0.0842625 | P66: =O66*J66 -> 18.53775 | V66: =IF($D1158="","",IF(ISNUMBER($D1158),REPLACE(TEXT($D1158,"0.0000"),5,0,"."),TRIM($D1158))) -> 3.06.35 | W66: =$F1159 -> 50 | X66: =$D1159 -> und/DIA
A67: 2.02.01 | B67: Materiales | D67: SIKA ANTISOL | G67: bal | I67: 0.02 | J67: 38.64 | K67: =I67*J67 -> 0.7728 | M67: 0.08025 | N67: m3 | O67: =I67*M67 -> 0.001605 | P67: =O67*J67 -> 0.0620172 | V67: =IF($D1174="","",IF(ISNUMBER($D1174),REPLACE(TEXT($D1174,"0.0000"),5,0,"."),TRIM($D1174))) -> 3.06.36 | W67: =$F1175 -> 40 | X67: =$D1175 -> und/DIA
K68: =SUM(K66:K67) -> 231.7728 | V68: =IF($D1190="","",IF(ISNUMBER($D1190),REPLACE(TEXT($D1190,"0.0000"),5,0,"."),TRIM($D1190))) -> 3.06.37 | W68: =$F1191 -> 40 | X68: =$D1191 -> und/DIA
D69: Equipos | V69: =IF($D1206="","",IF(ISNUMBER($D1206),REPLACE(TEXT($D1206,"0.0000"),5,0,"."),TRIM($D1206))) -> 3.06.38 | W69: =$F1207 -> 10 | X69: =$D1207 -> und/DIA
A70: 2.02.01 | B70: Equipos | C70: 0301010006 | D70: HERRAMIENTAS MANUALES | G70: %mo | I70: 5 | J70: =K64 -> 33.761067 | K70: =I70*J70/100 -> 1.6880533 | M70: 0.08025 | N70: m3 | O70: =I70*M70 -> 0.40125 | P70: =O70*J70/100 -> 0.13546628 | V70: =IF($D1227="","",IF(ISNUMBER($D1227),REPLACE(TEXT($D1227,"0.0000"),5,0,"."),TRIM($D1227))) -> 3.06.39 | W70: =$F1228 -> 10 | X70: =$D1228 -> und/DIA
A71: 2.02.01 | B71: Equipos | D71: VIBRADORA DE CONCRETO | G71: hm | H71: 1 | I71: =H71*8/H57 -> 0.53333333 | J71: 2.5 | K71: =I71*J71 -> 1.3333333 | M71: 0.08025 | N71: m3 | O71: =I71*M71 -> 0.0428 | P71: =O71*J71 -> 0.107 | V71: =IF($D1248="","",IF(ISNUMBER($D1248),REPLACE(TEXT($D1248,"0.0000"),5,0,"."),TRIM($D1248))) -> 3.06.40 | W71: =$F1249 -> 8 | X71: =$D1249 -> und/DIA
K72: =SUM(K70:K71) -> 3.0213867 | V72: =IF($D1269="","",IF(ISNUMBER($D1269),REPLACE(TEXT($D1269,"0.0000"),5,0,"."),TRIM($D1269))) -> 3.06.41 | W72: =$F1270 -> 12 | X72: =$D1270 -> und/DIA
V73: =IF($D1289="","",IF(ISNUMBER($D1289),REPLACE(TEXT($D1289,"0.0000"),5,0,"."),TRIM($D1289))) -> 3.06.42 | W73: =$F1290 -> 12 | X73: =$D1290 -> und/DIA
C74: Partida | D74: =QPS!C25 -> 2.0301 | E74: =QPS!G25 -> Concreto f'c=25MPa, Cemento tipo HS | Q74: =QPS!V25 -> 288.12111 | R74: =SUM(P74:P94) -> 288.12111 | S74: =Q74-R74 -> 0 | V74: =IF($D1309="","",IF(ISNUMBER($D1309),REPLACE(TEXT($D1309,"0.0000"),5,0,"."),TRIM($D1309))) -> 3.06.43 | W74: =$F1310 -> 10 | X74: =$D1310 -> und/DIA
C75: Rendimiento | D75: m3/DIA | E75: MO. | F75: 15 | G75: EQ. | H75: =F75 -> 15 | J75: Costo unitario directo por : m3 | K75: =+K82+K86+K90+K93 -> 321.20525 | V75: =IF($D1329="","",IF(ISNUMBER($D1329),REPLACE(TEXT($D1329,"0.0000"),5,0,"."),TRIM($D1329))) -> 3.06.44 | W75: =$F1330 -> 10 | X75: =$D1330 -> und/DIA
C76: Código | D76: Descripción Recurso | G76: Unidad | H76: Cuadrilla | I76: Cantidad | J76: Precio U$ | K76: Parcial U$ | V76: =IF($D1349="","",IF(ISNUMBER($D1349),REPLACE(TEXT($D1349,"0.0000"),5,0,"."),TRIM($D1349))) -> 3.06.45 | W76: =$F1350 -> 15 | X76: =$D1350 -> und/DIA
D77: Mano de Obra | V77: =IF($D1369="","",IF(ISNUMBER($D1369),REPLACE(TEXT($D1369,"0.0000"),5,0,"."),TRIM($D1369))) -> 3.06.46 | W77: =$F1370 -> 8 | X77: =$D1370 -> und/DIA
A78: 2.03.01 | B78: Mano de Obra | C78: 0101010002 | D78: CAPATAZ | G78: hh | H78: 0.2 | I78: =H78*8/$F$75 -> 0.10666667 | J78: 10.51 | K78: =I78*J78 -> 1.1210667 | M78: 0.897 | N78: m3 | O78: =I78*M78 -> 0.09568 | P78: =O78*J78 -> 1.0055968 | V78: =IF($D1389="","",IF(ISNUMBER($D1389),REPLACE(TEXT($D1389,"0.0000"),5,0,"."),TRIM($D1389))) -> 3.06.47 | W78: =$F1390 -> 7 | X78: =$D1390 -> und/DIA
A79: 2.03.01 | B79: Mano de Obra | D79: OPERARIO | G79: hh | H79: 2 | I79: =H79*8/$F$75 -> 1.0666667 | J79: 9.3 | K79: =I79*J79 -> 9.92 | M79: 0.897 | N79: m3 | O79: =I79*M79 -> 0.9568 | P79: =O79*J79 -> 8.89824 | V79: =IF($D1409="","",IF(ISNUMBER($D1409),REPLACE(TEXT($D1409,"0.0000"),5,0,"."),TRIM($D1409))) -> 3.06.48 | W79: =$F1410 -> 7 | X79: =$D1410 -> und/DIA
A80: 2.03.01 | B80: Mano de Obra | D80: OFICIAL | G80: hh | H80: 2 | I80: =H80*8/$F$75 -> 1.0666667 | J80: 7.54 | K80: =I80*J80 -> 8.0426667 | M80: 0.897 | N80: m3 | O80: =I80*M80 -> 0.9568 | P80: =O80*J80 -> 7.214272 | V80: =IF($D1429="","",IF(ISNUMBER($D1429),REPLACE(TEXT($D1429,"0.0000"),5,0,"."),TRIM($D1429))) -> 3.06.49 | W80: =$F1430 -> 6 | X80: =$D1430 -> und/DIA
A81: 2.03.01 | B81: Mano de Obra | C81: 01010300030005 | D81: AYUDANTE | G81: hh | H81: 4 | I81: =H81*8/$F$75 -> 2.1333333 | J81: 6.88 | K81: =I81*J81 -> 14.677333 | M81: 0.897 | N81: m3 | O81: =I81*M81 -> 1.9136 | P81: =O81*J81 -> 13.165568 | V81: =IF($D1449="","",IF(ISNUMBER($D1449),REPLACE(TEXT($D1449,"0.0000"),5,0,"."),TRIM($D1449))) -> 3.06.50 | W81: =$F1450 -> 6 | X81: =$D1450 -> und/DIA
K82: =SUM(K78:K81) -> 33.761067 | V82: =IF($D1469="","",IF(ISNUMBER($D1469),REPLACE(TEXT($D1469,"0.0000"),5,0,"."),TRIM($D1469))) -> 3.06.51 | W82: =$F1470 -> 6 | X82: =$D1470 -> und/DIA
D83: Materiales | V83: =IF($D1489="","",IF(ISNUMBER($D1489),REPLACE(TEXT($D1489,"0.0000"),5,0,"."),TRIM($D1489))) -> 3.06.52 | W83: =$F1490 -> 5 | X83: =$D1490 -> und/DIA
A84: 2.03.01 | B84: Materiales | D84: CONCRETO PRE-MEZCLADO f'c= 30 Mpa | G84: m3 | I84: 1.05 | J84: 270 | K84: =I84*J84 -> 283.5 | M84: 0.897 | N84: m3 | O84: =I84*M84 -> 0.94185 | P84: =O84*J84 -> 254.2995 | V84: =IF($D1509="","",IF(ISNUMBER($D1509),REPLACE(TEXT($D1509,"0.0000"),5,0,"."),TRIM($D1509))) -> 3.06.53 | W84: =$F1510 -> 5 | X84: =$D1510 -> und/DIA
A85: 2.03.01 | B85: Materiales | D85: SIKA ANTISOL | G85: bal | I85: 0.02 | J85: =+J67 -> 38.64 | K85: =I85*J85 -> 0.7728 | M85: 0.897 | N85: m3 | O85: =I85*M85 -> 0.01794 | P85: =O85*J85 -> 0.6932016 | V85: =IF($D1529="","",IF(ISNUMBER($D1529),REPLACE(TEXT($D1529,"0.0000"),5,0,"."),TRIM($D1529))) -> 3.06.54 | W85: =$F1530 -> 5 | X85: =$D1530 -> und/DIA
K86: =SUM(K84:K85) -> 284.2728 | V86: =IF($D1549="","",IF(ISNUMBER($D1549),REPLACE(TEXT($D1549,"0.0000"),5,0,"."),TRIM($D1549))) -> 3.06.55 | W86: =$F1550 -> 10 | X86: =$D1550 -> und/DIA
D87: Equipos | V87: =IF($D1568="","",IF(ISNUMBER($D1568),REPLACE(TEXT($D1568,"0.0000"),5,0,"."),TRIM($D1568))) -> 3.06.56 | W87: =$F1569 -> 10 | X87: =$D1569 -> und/DIA
A88: 2.03.01 | B88: Equipos | C88: 0301010006 | D88: HERRAMIENTAS MANUALES | G88: %mo | I88: 5 | J88: =K82 -> 33.761067 | K88: =I88*J88/100 -> 1.6880533 | M88: 0.897 | N88: m3 | O88: =I88*M88 -> 4.485 | P88: =O88*J88/100 -> 1.5141838 | V88: =IF($D1587="","",IF(ISNUMBER($D1587),REPLACE(TEXT($D1587,"0.0000"),5,0,"."),TRIM($D1587))) -> 3.06.57 | W88: =$F1588 -> 10 | X88: =$D1588 -> und/DIA
A89: 2.03.01 | B89: Equipos | D89: VIBRADORA DE CONCRETO | G89: hm | H89: 1 | I89: =H89*8/H75 -> 0.53333333 | J89: =+J71 -> 2.5 | K89: =I89*J89 -> 1.3333333 | M89: 0.897 | N89: m3 | O89: =I89*M89 -> 0.4784 | P89: =O89*J89 -> 1.196 | V89: =IF($D1606="","",IF(ISNUMBER($D1606),REPLACE(TEXT($D1606,"0.0000"),5,0,"."),TRIM($D1606))) -> 3.06.58 | W89: =$F1607 -> 10 | X89: =$D1607 -> und/DIA
K90: =SUM(K88:K89) -> 3.0213867 | V90: =IF($D1625="","",IF(ISNUMBER($D1625),REPLACE(TEXT($D1625,"0.0000"),5,0,"."),TRIM($D1625))) -> 3.06.59 | W90: =$F1626 -> 30 | X90: =$D1626 -> und/DIA
D91: Sub Partidas | V91: =IF($D1642="","",IF(ISNUMBER($D1642),REPLACE(TEXT($D1642,"0.0000"),5,0,"."),TRIM($D1642))) -> 3.06.60 | W91: =$F1643 -> 5 | X91: =$D1643 -> und/DIA
A92: 2.03.01 | B92: Sub Partidas | D92: PRUEBAS DE CALIDAD | G92: glb | I92: 1 | J92: 15 | K92: =I92*J92/100 -> 0.15 | M92: 0.897 | N92: m3 | O92: =I92*M92 -> 0.897 | P92: =O92*J92/100 -> 0.13455 | V92: =IF($D1658="","",IF(ISNUMBER($D1658),REPLACE(TEXT($D1658,"0.0000"),5,0,"."),TRIM($D1658))) -> 3.06.61 | W92: =$F1659 -> 5 | X92: =$D1659 -> und/DIA
K93: =SUM(K92:K92) -> 0.15 | V93: =IF($D1675="","",IF(ISNUMBER($D1675),REPLACE(TEXT($D1675,"0.0000"),5,0,"."),TRIM($D1675))) -> 3.06.62 | W93: =$F1676 -> 5 | X93: =$D1676 -> und/DIA
V94: =IF($D1691="","",IF(ISNUMBER($D1691),REPLACE(TEXT($D1691,"0.0000"),5,0,"."),TRIM($D1691))) -> 3.06.63 | W94: =$F1692 -> 5 | X94: =$D1692 -> und/DIA
C95: Partida | D95: =QPS!C26 -> 2.0302 | E95: =QPS!G26 -> Encofrado y desencofrado | Q95: =QPS!V26 -> 208.03417 | R95: =SUM(P95:P115) -> 208.03417 | S95: =Q95-R95 -> 0 | V95: =IF($D1707="","",IF(ISNUMBER($D1707),REPLACE(TEXT($D1707,"0.0000"),5,0,"."),TRIM($D1707))) -> 3.06.64 | W95: =$F1708 -> 4 | X95: =$D1708 -> und/DIA
C96: Rendimiento | D96: m2/DIA | E96: MO. | F96: 18 | G96: EQ. | H96: =F96 -> 18 | J96: Costo unitario directo por : m2 | K96: =+K102+K110+K114 -> 29.719167 | V96: =IF($D1726="","",IF(ISNUMBER($D1726),REPLACE(TEXT($D1726,"0.0000"),5,0,"."),TRIM($D1726))) -> 3.06.65 | W96: =$F1727 -> 40 | X96: =$D1727 -> und/DIA
C97: Código | D97: Descripción Recurso | G97: Unidad | H97: Cuadrilla | I97: Cantidad | J97: Precio U$ | K97: Parcial U$ | V97: =IF($D1742="","",IF(ISNUMBER($D1742),REPLACE(TEXT($D1742,"0.0000"),5,0,"."),TRIM($D1742))) -> 3.06.66 | W97: =$F1743 -> 40 | X97: =$D1743 -> und/DIA
D98: Mano de Obra | V98: =IF($D1758="","",IF(ISNUMBER($D1758),REPLACE(TEXT($D1758,"0.0000"),5,0,"."),TRIM($D1758))) -> 3.06.67 | W98: =$F1759 -> 40 | X98: =$D1759 -> und/DIA
A99: 2.03.02 | B99: Mano de Obra | C99: 0101010002 | D99: CAPATAZ | G99: hh | H99: 0.2 | I99: =H99*8/$F$96 -> 0.088888889 | J99: 10.51 | K99: =I99*J99 -> 0.93422222 | M99: 7 | N99: m2 | O99: =I99*M99 -> 0.62222222 | P99: =O99*J99 -> 6.5395556 | V99: =IF($D1774="","",IF(ISNUMBER($D1774),REPLACE(TEXT($D1774,"0.0000"),5,0,"."),TRIM($D1774))) -> 3.06.68 | W99: =$F1775 -> 40 | X99: =$D1775 -> und/DIA
A100: 2.03.02 | B100: Mano de Obra | D100: OPERARIO | G100: hh | H100: 1 | I100: =H100*8/$F$96 -> 0.44444444 | J100: 9.3 | K100: =I100*J100 -> 4.1333333 | M100: 7 | N100: m2 | O100: =I100*M100 -> 3.1111111 | P100: =O100*J100 -> 28.933333 | V100: =IF($D1790="","",IF(ISNUMBER($D1790),REPLACE(TEXT($D1790,"0.0000"),5,0,"."),TRIM($D1790))) -> 3.06.69 | W100: =$F1791 -> 40 | X100: =$D1791 -> und/DIA
...

Sheet GG
B2: GASTOS GENERALES
B5: PROYECTO : | C5: "Reposición del Sistema de Floculante"
B7: FECHA: | C7: 45965
J9: COSTO DIRECTO DE OBRA: | K9: =+QPS!V263 -> 210563.04
B11: RECURSO | D11: UNIDAD | E11: CANT. | F11: PERIODO | G11: CANT PERIOD | H11: COSTO/UNIDAD $ | I11: %INC. | J11: COSTO PARCIAL $ | K11: TOTAL
B14: 01 PERSONAL ADMINISTRATIVO Y AUXILIAR
C15: GERENTE GENERAL | D15: PER | E15: 1 | F15: MES | G15: 3.5 | H15: 5000 | I15: 0.1 | J15: =I15*E15*H15 -> 500 | K15: =J15*G15 -> 1750
C16: ADMINISTRADOR | D16: PER | E16: 1 | F16: MES | G16: 3.5 | H16: 2000 | I16: 0.2 | J16: =I16*E16*H16 -> 400 | K16: =J16*G16 -> 1400
C17: RRHH | D17: PER | E17: 1 | F17: MES | G17: 3.5 | H17: 2000 | I17: 0.2 | J17: =I17*E17*H17 -> 400 | K17: =J17*G17 -> 1400
C18: COMUNICACIONES | D18: UND | E18: 3 | F18: MES | G18: 3.5 | H18: 50 | I18: 0.25 | J18: =I18*E18*H18 -> 37.5 | K18: =J18*G18 -> 131.25
C19: MATERIAL DE ESCRITORIO | D19: GLB | E19: 1 | F19: MES | G19: 3.5 | H19: 150 | I19: 0.25 | J19: =I19*E19*H19 -> 37.5 | K19: =J19*G19 -> 131.25
C20: OFICINA | D20: UND | E20: 1 | F20: MES | G20: 3.5 | H20: 250 | I20: 0.25 | J20: =I20*E20*H20 -> 62.5 | K20: =J20*G20 -> 218.75
J21: TOTAL 01 | K21: =SUM(K15:K20) -> 5031.25
B22: 02 LOGISTICA
C23: COMPRADOR | D23: PER | E23: 1 | F23: MES | G23: 3.5 | H23: 2200 | I23: 0.25 | J23: =I23*E23*H23 -> 550 | K23: =J23*G23 -> 1925
C24: ALMACENERO CENTRAL | D24: PER | E24: 1 | F24: MES | G24: 3.5 | H24: 1200 | I24: 0.35 | J24: =I24*E24*H24 -> 420 | K24: =J24*G24 -> 1470
C25: ALMACENERO SATELITAL | D25: PER | E25: 1 | F25: MES | G25: 3.5 | H25: 950 | I25: 1 | J25: =I25*E25*H25 -> 950 | K25: =J25*G25 -> 3325
C26: COMUNICACIONES | D26: UND | E26: 2 | F26: MES | G26: 3.5 | H26: 50 | I26: 0.2 | J26: =I26*E26*H26 -> 20 | K26: =J26*G26 -> 70
J27: TOTAL 02 | K27: =SUM(K23:K26) -> 6790
B28: 03 PRODUCCION
C29: JEFE DE OPERACIONES | D29: PER | E29: 1 | F29: MES | G29: 3.5 | H29: 4000 | I29: 0.3 | J29: =I29*E29*H29 -> 1200 | K29: =J29*G29 -> 4200
C30: RESIDENTE DE OBRA | D30: PER | E30: 1 | F30: MES | G30: 4 | H30: 3450 | I30: 1 | J30: =I30*E30*H30 -> 3450 | K30: =J30*G30 -> 13800
C31: INGENIERO SUPERVISOR MECÁNICO | D31: PER | E31: 1 | F31: MES | G31: 3.5 | H31: 3200 | I31: 1 | J31: =I31*E31*H31 -> 3200 | K31: =J31*G31 -> 11200
C32: INGENIERO SUPERVISOR ELECTRICISTA | D32: PER | E32: 1 | F32: MES | G32: 3.5 | H32: 3200 | I32: 1 | J32: =I32*E32*H32 -> 3200 | K32: =J32*G32 -> 11200
C33: INGENIERO DE CONTROL DE PROYECTOS | D33: PER | E33: 1 | F33: MES | G33: 3.5 | H33: 3200 | I33: 1 | J33: =I33*E33*H33 -> 3200 | K33: =J33*G33 -> 11200
C34: INGENIERO DE CALIDAD | D34: PER | E34: 1 | F34: MES | G34: 3.5 | H34: 3200 | I34: 1 | J34: =I34*E34*H34 -> 3200 | K34: =J34*G34 -> 11200
C35: ADMINISTRADOR DE OBRA | D35: PER | E35: 1 | F35: MES | G35: 3.5 | H35: 1550 | I35: 1 | J35: =I35*E35*H35 -> 1550 | K35: =J35*G35 -> 5425
C36: TOPOGRAFO | D36: PER | E36: 1 | F36: MES | G36: 3.5 | H36: 1750 | I36: 1 | J36: =I36*E36*H36 -> 1750 | K36: =J36*G36 -> 6125
C37: CAMIONETA | D37: UND | E37: 1 | F37: MES | G37: 4 | H37: 1450 | I37: 1 | J37: =I37*E37*H37 -> 1450 | K37: =J37*G37 -> 5800
C38: COUSTER | D38: UND | E38: 1 | F38: MES | G38: 3.5 | H38: =110*22+4*22*(3.75) -> 2750 | I38: 1 | J38: =I38*E38*H38 -> 2750 | K38: =J38*G38 -> 9625 | W38: 10KM/GAL | X38: 3 GAL/DÍA | Y38: =13.4*3 -> 40.2 | Z38: =Y38*30 -> 1206 | AA38: =Z38/3.42 -> 352.63158
C39: SPRINTER | D39: UND | E39: 1 | F39: MES | G39: 3.5 | H39: =90*22+4*22*(3.75) -> 2310 | I39: 1 | J39: =I39*E39*H39 -> 2310 | K39: =J39*G39 -> 8085 | W39: 10KM/GAL | X39: 3 GAL/DÍA | Y39: =13.4*3 -> 40.2 | Z39: =Y39*30 -> 1206 | AA39: =Z39/3.42 -> 352.63158
C40: CHOFER CAMIONETA | D40: UND | E40: 1 | F40: MES | G40: 4 | H40: 1400 | I40: 1 | J40: =I40*E40*H40 -> 1400 | K40: =J40*G40 -> 5600
C41: CHOFER DE COUSTER | D41: UND | E41: 2 | F41: MES | G41: 3.5 | H41: 1450 | I41: 1 | J41: =I41*E41*H41 -> 2900 | K41: =J41*G41 -> 10150
C42: CHOFER DE SPRINTER | D42: UND | E42: 2 | F42: MES | G42: 3.5 | H42: 1450 | I42: 1 | J42: =I42*E42*H42 -> 2900 | K42: =J42*G42 -> 10150
C43: MATERIAL DE ESCRITORIO | D43: GLB | E43: 1 | F43: MES | G43: 3.5 | H43: 200 | I43: 1 | J43: =I43*E43*H43 -> 200 | K43: =J43*G43 -> 700
C44: COMUNICACIONES | D44: GLB | E44: 1 | F44: MES | G44: 3.5 | H44: 200 | I44: 1 | J44: =I44*E44*H44 -> 200 | K44: =J44*G44 -> 700
J45: TOTAL 03 | K45: =SUM(K29:K44) -> 125160
B46: 04 CONTROL DE PERDIDAS Y MEDIO AMBIENTE
C47: INGENIERO JEFE DE SEGURIDAD | D47: PER | E47: 1 | F47: MES | G47: 4 | H47: =+H29 -> 4000 | I47: 0.3 | J47: =I47*E47*H47 -> 1200 | K47: =J47*G47 -> 4800
C48: INGENIERO DE SEGURIDAD (EHS) | D48: PER | E48: 1 | F48: MES | G48: 4 | H48: 2750 | I48: 1 | J48: =I48*E48*H48 -> 2750 | K48: =J48*G48 -> 11000
C49: AGUA DE BEBER EN OBRA | D49: GLB | E49: 1 | F49: MES | G49: 3.5 | H49: 50 | I49: 1 | J49: =I49*E49*H49 -> 50 | K49: =J49*G49 -> 175
C50: RADIO COMUNICACIONES | D50: UND | E50: 1 | F50: MES | G50: 3.5 | H50: 50 | I50: 1 | J50: =I50*E50*H50 -> 50 | K50: =J50*G50 -> 175
C51: MATERIAL Y EQUIPO DE PDP | D51: GLB | E51: 1 | F51: MES | G51: 3.5 | H51: 250 | I51: 1 | J51: =I51*E51*H51 -> 250 | K51: =J51*G51 -> 875
J52: TOTAL 04 | K52: =SUM(K48:K51) -> 12225
B53: 05 FINANCIEROS
C54: POLIZA (SCTR, RESPONSABILIDAD CIVIL, ETC) | D54: GLB | E54: 1 | F54: MES | G54: 3.5 | H54: 1000 | I54: 1 | J54: =I54*E54*H54 -> 1000 | K54: =J54*G54 -> 3500
C55: GASTOS FINANCIEROS | D55: GLB | E55: 1 | F55: MES | G55: 3.5 | H55: 1000 | I55: 1 | J55: =I55*E55*H55 -> 1000 | K55: =J55*G55 -> 3500
J56: TOTAL 05 | K56: =SUM(K54:K55) -> 7000
B57: 06 OTROS
C58: CONTROL DE FATIGA EN UNIDADES | D58: UND | E58: 1 | F58: MES | G58: 3.5 | H58: 94.5 | I58: 1 | J58: =I58*E58*H58 -> 94.5 | K58: =J58*G58 -> 330.75
C59: REFUGIOS CONTRA TORMENTAS ELECTRICAS | D59: UND | E59: 1 | F59: MES | G59: 4 | H59: 200 | I59: 1 | J59: =I59*E59*H59 -> 200 | K59: =J59*G59 -> 800
C60: CONTENEDOR DE OFICINAS | D60: UND | E60: 1 | F60: MES | G60: 4 | H60: 200 | I60: 1 | J60: =I60*E60*H60 -> 200 | K60: =J60*G60 -> 800
C61: CONTENEDOR DE ALMACEN | D61: UND | E61: 1 | F61: MES | G61: 4 | H61: 200 | I61: 1 | J61: =I61*E61*H61 -> 200 | K61: =J61*G61 -> 800
C62: SS.H.H. | D62: UND | E62: 3 | F62: MES | G62: 3.5 | H62: 150.65 | I62: 1 | J62: =I62*E62*H62 -> 451.95 | K62: =J62*G62 -> 1581.825
C63: LAVAMANOS | D63: UND | E63: 1 | F63: MES | G63: 3.5 | H63: 147.02 | I63: 1 | J63: =I63*E63*H63 -> 147.02 | K63: =J63*G63 -> 514.57
C64: GRUPO ELECTRÓGENO | D64: UND | E64: 1 | F64: MES | G64: 3.5 | H64: 880 | I64: 1 | J64: =I64*E64*H64 -> 880 | K64: =J64*G64 -> 3080
J65: TOTAL 05 | K65: =SUM(K58:K64) -> 7907.145
B70: RESUMEN DE GASTOS GENERALES
B73: 01 PERSONAL ADMINISTRATIVO Y AUXILIAR | E73: $ | F73: =+K21 -> 5031.25
B75: 02 LOGISTICA | E75: $ | F75: =+K27 -> 6790
B77: 03 PRODUCCION | E77: $ | F77: =K45 -> 125160
B79: 04 CONTROL DE PERDIDAS Y MEDIO AMBIENTE | E79: $ | F79: =+K52 -> 12225
B81: 05 VARIOS | E81: $ | F81: =+K56 -> 7000
B83: 06 OTROS | E83: $ | F83: =K65 -> 7907.145
B86: TOTAL GASTOS GENERALES | E86: $ | F86: =+F73+F75+F77+F79+F81+F83 -> 164113.39
B88: PORCENTAJE DE GASTOS GENERALES | F88: =+F86/K9 -> 0.77940268 | G88: %

Sheet HH - Reg Civil
B4: RÉGIMEN CIVIL
B6: Cálculo del valor de la hora hombre | G6: Cálculo del valor de la hora hombre | L6: Cálculo del valor de la hora hombre
B7: Cálculo del valor de la hora hombre | G7: Cálculo del valor de la hora hombre | L7: Cálculo del valor de la hora hombre
B8: DESCRIPCIÓN | C8: OPERARIO | G8: DESCRIPCIÓN | H8: OFICIAL | L8: DESCRIPCIÓN | M8: AYUDANTE
C9: COND | D9: bonif | H9: COND | I9: bonif | M9: COND | N9: bonif
B10: jornal básico | C10: JB | E10: 89.3 | G10: jornal básico | H10: JB | J10: 69.75 | L10: jornal básico | M10: JB | O10: 62.8
B11: Bonificaciones | G11: Bonificaciones | L11: Bonificaciones
B12: Bonificación Unificada de Construcción BUC | C12: BUC | D12: 0.32 | E12: =D12*E10 -> 28.576 | G12: Bonificación Unificada de Construcción BUC | H12: BUC | I12: 0.3 | J12: =I12*J10 -> 20.925 | L12: Bonificación Unificada de Construcción BUC | M12: BUC | N12: 0.3 | O12: =N12*O10 -> 18.84
B13: Bonificación por Alta Especialización BAE | C13: BAE | D13: 0 | E13: =D13 -> 0 | G13: Bonificación por Alta Especialización BAE | H13: BAE | I13: 0 | J13: =I13 -> 0 | L13: Bonificación por Alta Especialización BAE | M13: BAE | N13: 0 | O13: =N13 -> 0
B14: Bonificación por Altura | C14: no | D14: 0 | E14: =D14 -> 0 | G14: Bonificación por Altura | H14: no | I14: 0 | J14: =I14 -> 0 | L14: Bonificación por Altura | M14: no | N14: 0 | O14: =N14 -> 0
B15: Bonificación por Altitud | C15: si | D15: 2 | E15: =D15 -> 2 | G15: Bonificación por Altitud | H15: si | I15: 2 | J15: =I15 -> 2 | L15: Bonificación por Altitud | M15: si | N15: 2 | O15: =N15 -> 2
B16: Bonificación por Contacto por el Agua | C16: no | D16: 0 | E16: =D16 -> 0 | G16: Bonificación por Contacto por el Agua | H16: no | I16: 0 | J16: =I16 -> 0 | L16: Bonificación por Contacto por el Agua | M16: no | N16: 0 | O16: =N16 -> 0
B17: Bonificación por Aguas Servidas | C17: no | D17: 0 | E17: =D17 -> 0 | G17: Bonificación por Aguas Servidas | H17: no | I17: 0 | J17: =I17 -> 0 | L17: Bonificación por Aguas Servidas | M17: no | N17: 0 | O17: =N17 -> 0
B18: Bonificación por Horario Nocturno | C18: NO | D18: 0 | E18: =D18 -> 0 | G18: Bonificación por Horario Nocturno | H18: NO | I18: 0 | J18: =I18 -> 0 | L18: Bonificación por Horario Nocturno | M18: NO | N18: 0 | O18: =N18 -> 0
B19: Bonificación por Movilidad | C19: si | D19: 8.6 | E19: =D19 -> 8.6 | G19: Bonificación por Movilidad | H19: si | I19: 8.6 | J19: =I19 -> 8.6 | L19: Bonificación por Movilidad | M19: si | N19: 8.6 | O19: =N19 -> 8.6
B21: Leyes Sociales | C21: RÉGIMEN | E21: SNP | G21: Leyes Sociales | H21: RÉGIMEN | J21: SNP | L21: Leyes Sociales | M21: RÉGIMEN | O21: SNP
B22: Sobre el Jornal Básico (SJB) | C22: SBJ | D22: 1.2618 | E22: =D22*E10 -> 112.67874 | G22: Sobre el Jornal Básico (SJB) | H22: SBJ | I22: =D22 -> 1.2618 | J22: =I22*J10 -> 88.01055 | L22: Sobre el Jornal Básico (SJB) | M22: SBJ | N22: =D22 -> 1.2618 | O22: =N22*O10 -> 79.24104
B23: Sobre las Bonificaciones Afectas (SBA) | C23: SBA | D23: 0.12 | E23: =D23*E12 -> 3.42912 | G23: Sobre las Bonificaciones Afectas (SBA) | H23: SBA | I23: =D23 -> 0.12 | J23: =I23*J12 -> 2.511 | L23: Sobre las Bonificaciones Afectas (SBA) | M23: SBA | N23: =D23 -> 0.12 | O23: =N23*O12 -> 2.2608
B25: overol | D25: 0.4 | E25: =D25 -> 0.4 | G25: overol | I25: 0.4 | J25: =I25 -> 0.4 | L25: overol | N25: 0.4 | O25: =N25 -> 0.4
B26: ESSALUD | D26: =0.09*E10 -> 8.037 | E26: =D26 -> 8.037 | G26: ESSALUD | I26: =0.09*J10 -> 6.2775 | J26: =I26 -> 6.2775 | L26: ESSALUD | N26: =0.09*O10 -> 5.652 | O26: =N26 -> 5.652
B28: Costo Diario (DÍA) | E28: =SUM(E22:E27)+SUM(E10:E20) -> 253.02086 | G28: Costo Diario (DÍA) | J28: =SUM(J22:J27)+SUM(J10:J20) -> 198.47405 | L28: Costo Diario (DÍA) | O28: =SUM(O22:O27)+SUM(O10:O20) -> 179.79384
B29: Costo Hora Hombre (HH) | E29: =ROUND(E28/8,2) -> 31.63 | G29: Costo Hora Hombre (HH) | J29: =ROUND(J28/8,2) -> 24.81 | L29: Costo Hora Hombre (HH) | O29: =ROUND(O28/8,2) -> 22.47
B32: OTROS COSTOS | G32: OTROS COSTOS | L32: OTROS COSTOS
B33: 9 | C33: EXAMEN MÉDICO | E33: =SUM(E34:E37)/3 -> 40 | G33: 9 | H33: EXAMEN MÉDICO | J33: =SUM(J34:J37) -> 120 | L33: 9 | M33: EXAMEN MÉDICO | O33: =SUM(O34:O37) -> 120
C34: Examen Médico Pre ocupacional x 3 meses | E34: 120 | H34: Examen Médico Pre ocupacional | J34: =E34 -> 120 | M34: Examen Médico Pre ocupacional | N34: =D34 -> 0 | O34: =E34 -> 120
C35: Examen Médico Post ocupacional x 3 meses | E35: 0 | H35: Examen Médico Post ocupacional | J35: =E35 -> 0 | M35: Examen Médico Post ocupacional | N35: =D35 -> 0 | O35: =E35 -> 0
M36: Otros exámenes (sicosensométrico, altura, mayor de 40años) | N36: =D36 -> 0 | O36: =E36 -> 0
B38: 10 | C38: EPP | E38: =SUM(E39:E39) -> 124 | G38: 10 | H38: EPP | J38: =SUM(J39:J39) -> 124 | L38: 10 | M38: EPP | O38: =SUM(O39:O39) -> 124
C39: Epp Completo x 3 meses | E39: 124 | H39: Epp Completo | I39: 1 | J39: =E39 -> 124 | M39: Epp Completo | N39: 1 | O39: =E39 -> 124
B41: 11 | C41: ALIMENTACIÓN | E41: =+E42 -> 462 | G41: 11 | H41: ALIMENTACIÓN | J41: =+J42 -> 462 | L41: 11 | M41: ALIMENTACIÓN | O41: =+O42 -> 462
C42: Alimentación (Solo almuerzo) | E42: =22*21 -> 462 | H42: Alimentación (Solo almuerzo) | J42: =E42 -> 462 | M42: Alimentación (Solo almuerzo) | O42: =E42 -> 462
B43: 12 | C43: TRANSPORTE | E43: =+E44 -> 0 | G43: 12 | H43: TRANSPORTE | J43: =+J44 -> 0 | L43: 12 | M43: TRANSPORTE | O43: =+O44 -> 0
C44: Transporte | E44: 0 | H44: Transporte | J44: =E44 -> 0 | M44: Transporte | O44: =E44 -> 0
B45: 13 | C45: CURSOS DE CAPACITACIÓN | E45: =SUM(E46:E48) -> 60 | G45: 13 | H45: CURSOS DE CAPACITACIÓN | J45: =SUM(J46:J48) -> 60 | L45: 13 | M45: CURSOS DE CAPACITACIÓN | O45: =SUM(O46:O48) -> 60
C46: inducción x 3 meses | E46: 60 | H46: inducción | J46: =E46 -> 60 | M46: inducción | O46: =E46 -> 60
C48: cursos mensuales (01 curso por mes) | E48: 0 | H48: cursos mensuales (01 curso por mes) | J48: =E48 -> 0 | M48: cursos mensuales (01 curso por mes) | O48: =E48 -> 0
B50: 14 | C50: BONIFICACIÓN EXTRAORDINARIA POR PRODUCCIÓN. | E50: 200 | G50: 14 | H50: BONIFICACIÓN EXTRAORDINARIA POR PRODUCCIÓN. | J50: 150 | L50: 14 | M50: BONIFICACIÓN EXTRAORDINARIA POR PRODUCCIÓN. | O50: 100
B51: 15 | G51: 15 | L51: 15
B52: OTROS COSTOS MESES (PLAZO, modificable a duración de obra) | D52: 4 | E52: =+E45+E41+E38+E33+E43+E50 -> 886 | G52: OTROS COSTOS MESES (PLAZO, modificable a duración de obra) | I52: 4 | J52: =+J45+J41+J38+J33+J43+J50 -> 916 | L52: OTROS COSTOS MESES (PLAZO, modificable a duración de obra) | N52: 4 | O52: =+O45+O41+O38+O33+O43+O50 -> 866
B53: TASA DE CAMBIO | D53: 3.5 | G53: TASA DE CAMBIO | I53: =D53 -> 3.5 | L53: TASA DE CAMBIO | N53: =D53 -> 3.5
B55: COSTO LABORAL POR MES Y EN SOLES | E55: =+E52+(E29*216) -> 7718.08 | G55: COSTO LABORAL POR MES Y EN SOLES | J55: =+J52+(J29*216) -> 6274.96 | L55: COSTO LABORAL POR MES Y EN SOLES | O55: =+O52+(O29*216) -> 5719.52
B56: COSTO LABORAL POR MES Y DÓLARES AMERICANOS | D56: 3.5 | E56: =+E55/D56 -> 2205.1657 | G56: COSTO LABORAL POR MES Y DÓLARES AMERICANOS | I56: =+I53 -> 3.5 | J56: =+J55/I56 -> 1792.8457 | L56: COSTO LABORAL POR MES Y DÓLARES AMERICANOS | N56: =+N53 -> 3.5 | O56: =+O55/N56 -> 1634.1486
B57: HORAS HOMBRE X MES LABORADO EN UN RÉGIMEN COMÚN DE 48 HORAS | E57: 216 | G57: HORAS HOMBRE X MES LABORADO EN UN RÉGIMEN COMÚN DE 48 HORAS | J57: =+E57 -> 216 | L57: HORAS HOMBRE X MES LABORADO EN UN RÉGIMEN COMÚN DE 48 HORAS | O57: =+J57 -> 216
B58: COSTO POR HORA HOMBRE EN SOLES | E58: =+E55/E57 -> 35.731852 | G58: COSTO POR HORA HOMBRE EN SOLES | J58: =+J55/J57 -> 29.050741 | L58: COSTO POR HORA HOMBRE EN SOLES | O58: =+O55/O57 -> 26.479259
B59: COSTO POR HORA HOMBRE $ | D59: =+D53 -> 3.5 | E59: =ROUND(E58/D59,2) -> 10.21 | G59: COSTO POR HORA HOMBRE $ | I59: =+I53 -> 3.5 | J59: =ROUNDUP(J58/I59,2) -> 8.31 | L59: COSTO POR HORA HOMBRE $ | N59: =+N53 -> 3.5 | O59: =ROUNDUP(O58/N59,2) -> 7.57
E64: RÉGIMEN CIVIL
E66: Cálculo del valor de la hora hombre | J66: Cálculo del valor de la hora hombre | O66: Cálculo del valor de la hora hombre
E67: Cálculo del valor de la hora hombre | J67: Cálculo del valor de la hora hombre | O67: Cálculo del valor de la hora hombre
E68: DESCRIPCIÓN | F68: OPERARIO ELECTRICISTA | J68: DESCRIPCIÓN | K68: OFICIAL ELECTRICISTA | O68: DESCRIPCIÓN | P68: AYUDANTE ELECTRICISTA
F69: COND | G69: bonif | K69: COND | L69: bonif | P69: COND | Q69: bonif
E70: jornal básico | F70: JB | H70: 89.3 | J70: jornal básico | K70: JB | M70: 69.75 | O70: jornal básico | P70: JB | R70: 62.8
E71: Bonificaciones | J71: Bonificaciones | O71: Bonificaciones
E72: Bonificación Unificada de Construcción BUC | F72: BUC | G72: 0.32 | H72: =G72*H70 -> 28.576 | J72: Bonificación Unificada de Construcción BUC | K72: BUC | L72: 0.3 | M72: =L72*M70 -> 20.925 | O72: Bonificación Unificada de Construcción BUC | P72: BUC | Q72: 0.3 | R72: =Q72*R70 -> 18.84
E73: Bonificación por Alta Especialización BAE | F73: BAE | G73: 0 | H73: =G73 -> 0 | J73: Bonificación por Alta Especialización BAE | K73: BAE | L73: 0 | M73: =L73 -> 0 | O73: Bonificación por Alta Especialización BAE | P73: BAE | Q73: 0 | R73: =Q73 -> 0
E74: Bonificación por Altura | F74: no | G74: 0 | H74: =G74 -> 0 | J74: Bonificación por Altura | K74: no | L74: 0 | M74: =L74 -> 0 | O74: Bonificación por Altura | P74: no | Q74: 0 | R74: =Q74 -> 0
E75: Bonificación por Altitud | F75: si | G75: 2 | H75: =G75 -> 2 | J75: Bonificación por Altitud | K75: si | L75: 2 | M75: =L75 -> 2 | O75: Bonificación por Altitud | P75: si | Q75: 2 | R75: =Q75 -> 2
E76: Bonificación por Contacto por el Agua | F76: no | G76: 0 | H76: =G76 -> 0 | J76: Bonificación por Contacto por el Agua | K76: no | L76: 0 | M76: =L76 -> 0 | O76: Bonificación por Contacto por el Agua | P76: no | Q76: 0 | R76: =Q76 -> 0
E77: Bonificación por Aguas Servidas | F77: no | G77: 0 | H77: =G77 -> 0 | J77: Bonificación por Aguas Servidas | K77: no | L77: 0 | M77: =L77 -> 0 | O77: Bonificación por Aguas Servidas | P77: no | Q77: 0 | R77: =Q77 -> 0
E78: Bonificación por Horario Nocturno | F78: NO | G78: 0 | H78: =G78 -> 0 | J78: Bonificación por Horario Nocturno | K78: NO | L78: 0 | M78: =L78 -> 0 | O78: Bonificación por Horario Nocturno | P78: NO | Q78: 0 | R78: =Q78 -> 0
E79: Bonificación por Movilidad | F79: si | G79: 8.6 | H79: =G79 -> 8.6 | J79: Bonificación por Movilidad | K79: si | L79: 8.6 | M79: =L79 -> 8.6 | O79: Bonificación por Movilidad | P79: si | Q79: 8.6 | R79: =Q79 -> 8.6
E81: Leyes Sociales | F81: RÉGIMEN | H81: SNP | J81: Leyes Sociales | K81: RÉGIMEN | M81: SNP | O81: Leyes Sociales | P81: RÉGIMEN | R81: SNP
E82: Sobre el Jornal Básico (SJB) | F82: SBJ | G82: 1.2618 | H82: =G82*H70 -> 112.67874 | J82: Sobre el Jornal Básico (SJB) | K82: SBJ | L82: =G82 -> 1.2618 | M82: =L82*M70 -> 88.01055 | O82: Sobre el Jornal Básico (SJB) | P82: SBJ | Q82: =G82 -> 1.2618 | R82: =Q82*R70 -> 79.24104
E83: Sobre las Bonificaciones Afectas (SBA) | F83: SBA | G83: 0.12 | H83: =G83*H72 -> 3.42912 | J83: Sobre las Bonificaciones Afectas (SBA) | K83: SBA | L83: =G83 -> 0.12 | M83: =L83*M72 -> 2.511 | O83: Sobre las Bonificaciones Afectas (SBA) | P83: SBA | Q83: =G83 -> 0.12 | R83: =Q83*R72 -> 2.2608
E85: overol | G85: 0.4 | H85: =G85 -> 0.4 | J85: overol | L85: 0.4 | M85: =L85 -> 0.4 | O85: overol | Q85: 0.4 | R85: =Q85 -> 0.4
E86: ESSALUD | G86: =0.09*H70 -> 8.037 | H86: =G86 -> 8.037 | J86: ESSALUD | L86: =0.09*M70 -> 6.2775 | M86: =L86 -> 6.2775 | O86: ESSALUD | Q86: =0.09*R70 -> 5.652 | R86: =Q86 -> 5.652
E88: Costo Diario (DÍA) | H88: =SUM(H82:H87)+SUM(H70:H80) -> 253.02086 | J88: Costo Diario (DÍA) | M88: =SUM(M82:M87)+SUM(M70:M80) -> 198.47405 | O88: Costo Diario (DÍA) | R88: =SUM(R82:R87)+SUM(R70:R80) -> 179.79384
E89: Costo Hora Hombre (HH) | H89: =ROUND(H88/8,2) -> 31.63 | J89: Costo Hora Hombre (HH) | M89: =ROUND(M88/8,2) -> 24.81 | O89: Costo Hora Hombre (HH) | R89: =ROUND(R88/8,2) -> 22.47
E92: OTROS COSTOS | J92: OTROS COSTOS | O92: OTROS COSTOS
E93: 9 | F93: EXAMEN MÉDICO | H93: =SUM(H94:H97)/3 -> 40 | J93: 9 | K93: EXAMEN MÉDICO | M93: =SUM(M94:M97) -> 120 | O93: 9 | P93: EXAMEN MÉDICO | R93: =SUM(R94:R97) -> 120
F94: Examen Médico Pre ocupacional x 3 meses | H94: 120 | K94: Examen Médico Pre ocupacional | M94: =H94 -> 120 | P94: Examen Médico Pre ocupacional | Q94: =G94 -> 0 | R94: =H94 -> 120
F95: Examen Médico Post ocupacional x 3 meses | H95: 0 | K95: Examen Médico Post ocupacional | M95: =H95 -> 0 | P95: Examen Médico Post ocupacional | Q95: =G95 -> 0 | R95: =H95 -> 0
P96: Otros exámenes (sicosensométrico, altura, mayor de 40años) | Q96: =G96 -> 0 | R96: =H96 -> 0
E98: 10 | F98: EPP | H98: =SUM(H99:H99) -> 399 | J98: 10 | K98: EPP | M98: =SUM(M99:M99) -> 173.09333 | O98: 10 | P98: EPP | R98: =SUM(R99:R99) -> 173.09333
F99: Epp Completo x 3 meses | H99: 399 | K99: Epp Completo | L99: 1 | M99: 173.09333 | P99: Epp Completo | Q99: 1 | R99: 173.09333
E101: 11 | F101: ALIMENTACIÓN | H101: =+H102 -> 462 | J101: 11 | K101: ALIMENTACIÓN | M101: =+M102 -> 462 | O101: 11 | P101: ALIMENTACIÓN | R101: =+R102 -> 462
F102: Alimentación (Solo almuerzo) | H102: =+E42 -> 462 | K102: Alimentación (Solo almuerzo) | M102: =H102 -> 462 | P102: Alimentación (Solo almuerzo) | R102: =H102 -> 462
E103: 12 | F103: TRANSPORTE | H103: =+H104 -> 0 | J103: 12 | K103: TRANSPORTE | M103: =+M104 -> 0 | O103: 12 | P103: TRANSPORTE | R103: =+R104 -> 0
F104: Transporte | H104: 0 | K104: Transporte | M104: =H104 -> 0 | P104: Transporte | R104: =H104 -> 0
E105: 13 | F105: CURSOS DE CAPACITACIÓN | H105: =SUM(H106:H108) -> 371.66667 | J105: 13 | K105: CURSOS DE CAPACITACIÓN | M105: =SUM(M106:M108) -> 371.66667 | O105: 13 | P105: CURSOS DE CAPACITACIÓN | R105: =SUM(R106:R108) -> 371.66667
F106: inducción x 3 meses | H106: 20 | K106: inducción | M106: =H106 -> 20 | P106: inducción | R106: =H106 -> 20
F108: cursos mensuales (01 curso por mes) | H108: 351.66667 | K108: cursos mensuales (01 curso por mes) | M108: =H108 -> 351.66667 | P108: cursos mensuales (01 curso por mes) | R108: =H108 -> 351.66667
E110: 14 | F110: BONIFICACIÓN EXTRAORDINARIA POR PRODUCCIÓN. | H110: 250 | J110: 14 | K110: BONIFICACIÓN EXTRAORDINARIA POR PRODUCCIÓN. | M110: 200 | O110: 14 | P110: BONIFICACIÓN EXTRAORDINARIA POR PRODUCCIÓN. | R110: 150
E111: 15 | J111: 15 | O111: 15
E112: OTROS COSTOS MESES (PLAZO, modificable a duración de obra) | G112: 1 | H112: =+H105+H101+H98+H93+H103+H110 -> 1522.6667 | J112: OTROS COSTOS MESES (PLAZO, modificable a duración de obra) | L112: 1 | M112: =+M105+M101+M98+M93+M103+M110 -> 1326.76 | O112: OTROS COSTOS MESES (PLAZO, modificable a duración de obra) | Q112: 1 | R112: =+R105+R101+R98+R93+R103+R110 -> 1276.76
E113: TASA DE CAMBIO | G113: 3.5 | J113: TASA DE CAMBIO | L113: =G113 -> 3.5 | O113: TASA DE CAMBIO | Q113: =G113 -> 3.5
E115: COSTO LABORAL POR MES Y EN SOLES | H115: =+H112+(H89*216) -> 8354.7467 | J115: COSTO LABORAL POR MES Y EN SOLES | M115: =+M112+(M89*216) -> 6685.72 | O115: COSTO LABORAL POR MES Y EN SOLES | R115: =+R112+(R89*216) -> 6130.28
E116: COSTO LABORAL POR MES Y DÓLARES AMERICANOS | G116: =+G113 -> 3.5 | H116: =+H115/G116 -> 2387.0705 | J116: COSTO LABORAL POR MES Y DÓLARES AMERICANOS | L116: =+L113 -> 3.5 | M116: =+M115/L116 -> 1910.2057 | O116: COSTO LABORAL POR MES Y DÓLARES AMERICANOS | Q116: =+Q113 -> 3.5 | R116: =+R115/Q116 -> 1751.5086
E117: HORAS HOMBRE X MES LABORADO EN UN RÉGIMEN COMÚN DE 48 HORAS | H117: 216 | J117: HORAS HOMBRE X MES LABORADO EN UN RÉGIMEN COMÚN DE 48 HORAS | M117: =+H117 -> 216 | O117: HORAS HOMBRE X MES LABORADO EN UN RÉGIMEN COMÚN DE 48 HORAS | R117: =+M117 -> 216
E118: COSTO POR HORA HOMBRE EN SOLES | H118: =+H115/H117 -> 38.679383 | J118: COSTO POR HORA HOMBRE EN SOLES | M118: =+M115/M117 -> 30.952407 | O118: COSTO POR HORA HOMBRE EN SOLES | R118: =+R115/R117 -> 28.380926
E119: COSTO POR HORA HOMBRE $ | G119: =+G113 -> 3.5 | H119: =ROUND(H118/G119,2) -> 11.05 | J119: COSTO POR HORA HOMBRE $ | L119: =+L113 -> 3.5 | M119: =ROUNDUP(M118/L119,2) -> 8.85 | O119: COSTO POR HORA HOMBRE $ | Q119: =+Q113 -> 3.5 | R119: =ROUNDUP(R118/Q119,2) -> 8.11

Sheet HH - Reg. común
D2: CAPATAZ ELECTRICISTA | E2: TC | F2: 3.5 | I2: CAPATAZ | J2: TC | K2: 3.5 | N2: SOLDADOR 4G | O2: TC | P2: 3.5
C3: ITEM | D3: DESCRIPCION | E3: % | H3: ITEM | I3: DESCRIPCION | J3: % | M3: ITEM | N3: DESCRIPCION | O3: %
C4: COSTOS MENSUALES REFERENCIALES | H4: COSTOS MENSUALES REFERENCIALES | M4: COSTOS MENSUALES REFERENCIALES
C5: 1 | D5: SUELDO BRUTO | F5: =+F6+F7 -> 4613 | H5: 1 | I5: SUELDO BRUTO | K5: =+K6+K7 -> 4613 | M5: 1 | N5: SUELDO BRUTO | P5: =+P6+P7 -> 5113
D6: Haber básico mensual | E6: - | F6: 4500 | I6: Haber básico mensual | J6: - | K6: 4500 | N6: Haber básico mensual | O6: - | P6: 5000
D7: Asignación familiar | E7: - | F7: 113 | I7: Asignación familiar | J7: - | K7: 113 | N7: Asignación familiar | O7: - | P7: =+K7 -> 113
C8: 2 | D8: AFP | F8: =SUM(F9:F11) -> 599.69 | H8: 2 | I8: AFP | K8: =SUM(K9:K11) -> 599.69 | M8: 2 | N8: AFP | P8: =SUM(P9:P11) -> 664.69
D9: Aporte obligatorio 10% | E9: 10 | F9: =+F5*$E9/100 -> 461.3 | I9: Aporte obligatorio 10% | J9: 10 | K9: =+K5*$E9/100 -> 461.3 | N9: Aporte obligatorio 10% | O9: 10 | P9: =+P5*$E9/100 -> 511.3
D10: Prima de seguro 1.23% | E10: 1.23 | F10: =+F5*$E10/100 -> 56.7399 | I10: Prima de seguro 1.23% | J10: 1.23 | K10: =+K5*$E10/100 -> 56.7399 | N10: Prima de seguro 1.23% | O10: 1.23 | P10: =+P5*$E10/100 -> 62.8899
D11: Comisión variable 1.47% - 1.77% | E11: 1.77 | F11: =+F5*$E11/100 -> 81.6501 | I11: Comisión variable 1.47% - 1.77% | J11: 1.77 | K11: =+K5*$E11/100 -> 81.6501 | N11: Comisión variable 1.47% - 1.77% | O11: 1.77 | P11: =+P5*$E11/100 -> 90.5001
C12: 3 | D12: RENTA QUINTA CATEGORÍA | F12: =+F13 -> 487.9 | H12: 3 | I12: RENTA QUINTA CATEGORÍA | K12: =+K13 -> 487.9 | M12: 3 | N12: RENTA QUINTA CATEGORÍA | P12: =+P13 -> 575.4
D13: Impuesto | E13: 15 | F13: =IF(F5*14>3650*7,(((F5*14)-(3650*7))/12)*$E13/100,0) -> 487.9 | I13: Impuesto | J13: 15 | K13: =IF(K5*14>3650*7,(((K5*14)-(3650*7))/12)*$E13/100,0) -> 487.9 | N13: Impuesto | O13: 15 | P13: =IF(P5*14>3650*7,(((P5*14)-(3650*7))/12)*$E13/100,0) -> 575.4
C14: SUELDO NETO O LIQUIDO MENSUAL | F14: =+F5-F8-F12 -> 3525.41 | H14: SUELDO NETO O LIQUIDO MENSUAL | K14: =+K5-K8-K12 -> 3525.41 | M14: SUELDO NETO O LIQUIDO MENSUAL | P14: =+P5-P8-P12 -> 3872.91
C15: 4 | D15: ESSSALUD | F15: =+F16 -> 415.17 | H15: 4 | I15: ESSSALUD | K15: =+K16 -> 415.17 | M15: 4 | N15: ESSSALUD | P15: =+P16 -> 460.17
D16: Aporte mensual (9% del sueldo bruto) | E16: 9 | F16: =+F5*$E16/100 -> 415.17 | I16: Aporte mensual (9% del sueldo bruto) | J16: 9 | K16: =+K5*$E16/100 -> 415.17 | N16: Aporte mensual (9% del sueldo bruto) | O16: 9 | P16: =+P5*$E16/100 -> 460.17
C17: 5 | D17: SCTR LEY 26790 | F17: =SUM(F18:F19) -> 64.582 | H17: 5 | I17: SCTR LEY 26790 | K17: =SUM(K18:K19) -> 64.582 | M17: 5 | N17: SCTR LEY 26790 | P17: =SUM(P18:P19) -> 71.582
D18: SCTR Salud - Aporte mensual (0.70% del sueldo bruto) | E18: 0.7 | F18: =+F5*$E18/100 -> 32.291 | I18: SCTR Salud - Aporte mensual (0.70% del sueldo bruto) | J18: 0.7 | K18: =+K5*$E18/100 -> 32.291 | N18: SCTR Salud - Aporte mensual (0.70% del sueldo bruto) | O18: 0.7 | P18: =+P5*$E18/100 -> 35.791
D19: SCTR Pensión - Aporte mensual (0.70% del sueldo bruto) | E19: 0.7 | F19: =+F5*$E19/100 -> 32.291 | I19: SCTR Pensión - Aporte mensual (0.70% del sueldo bruto) | J19: 0.7 | K19: =+K5*$E19/100 -> 32.291 | N19: SCTR Pensión - Aporte mensual (0.70% del sueldo bruto) | O19: 0.7 | P19: =+P5*$E19/100 -> 35.791
C20: OBLIGACIONES DEL EMPLEADOR MENSUAL | F20: =+F15+F17 -> 479.752 | H20: OBLIGACIONES DEL EMPLEADOR MENSUAL | K20: =+K15+K17 -> 479.752 | M20: OBLIGACIONES DEL EMPLEADOR MENSUAL | P20: =+P15+P17 -> 531.752
C21: PROVISIONES MENSUALES POR CIERRE DE CONTRATO | H21: PROVISIONES MENSUALES POR CIERRE DE CONTRATO | M21: PROVISIONES MENSUALES POR CIERRE DE CONTRATO
C22: 6 | D22: LIQUIDACIÓN | F22: =SUM(F23:F26) -> 1670.9311 | H22: 6 | I22: LIQUIDACIÓN | K22: =SUM(K23:K26) -> 1670.9311 | M22: 6 | N22: LIQUIDACIÓN | P22: =SUM(P23:P26) -> 1852.0422
D23: Gratificaciones - 2 sueldos anuales | F23: =+F5/6 -> 768.83333 | I23: Gratificaciones - 2 sueldos anuales | K23: =+K5/6 -> 768.83333 | N23: Gratificaciones - 2 sueldos anuales | P23: =+P5/6 -> 852.16667
D24: Bonificación extraordinaria | E24: 9 | F24: =+F23*$E24/100 -> 69.195 | I24: Bonificación extraordinaria | J24: 9 | K24: =+K23*$E24/100 -> 69.195 | N24: Bonificación extraordinaria | O24: 9 | P24: =+P23*$E24/100 -> 76.695
D25: Vacaciones - 1 sueldo anual | F25: =+F5/12 -> 384.41667 | I25: Vacaciones - 1 sueldo anual | K25: =+K5/12 -> 384.41667 | N25: Vacaciones - 1 sueldo anual | P25: =+P5/12 -> 426.08333
D26: CTS - 1 sueldo anual - No afecto a tributación | F26: =+(F5+F23)/12 -> 448.48611 | I26: CTS - 1 sueldo anual - No afecto a tributación | K26: =+(K5+K23)/12 -> 448.48611 | N26: CTS - 1 sueldo anual - No afecto a tributación | P26: =+(P5+P23)/12 -> 497.09722
C27: 7 | D27: AFP | F27: =SUM(F28:F30) -> 49.974167 | H27: 7 | I27: AFP | K27: =SUM(K28:K30) -> 49.974167 | M27: 7 | N27: AFP | P27: =SUM(P28:P30) -> 55.390833
D28: Aporte obligatorio 10% | E28: 10 | F28: =SUM(F25)*$E28/100 -> 38.441667 | I28: Aporte obligatorio 10% | J28: 10 | K28: =SUM(K25)*$E28/100 -> 38.441667 | N28: Aporte obligatorio 10% | O28: 10 | P28: =SUM(P25)*$E28/100 -> 42.608333
D29: Prima de seguro 1.23% | E29: 1.23 | F29: =SUM(F25)*$E29/100 -> 4.728325 | I29: Prima de seguro 1.23% | J29: 1.23 | K29: =SUM(K25)*$E29/100 -> 4.728325 | N29: Prima de seguro 1.23% | O29: 1.23 | P29: =SUM(P25)*$E29/100 -> 5.240825
D30: Comisión variable 1.47% - 1.77% | E30: 1.77 | F30: =SUM(F25)*$E30/100 -> 6.804175 | I30: Comisión variable 1.47% - 1.77% | J30: 1.77 | K30: =SUM(K25)*$E30/100 -> 6.804175 | N30: Comisión variable 1.47% - 1.77% | O30: 1.77 | P30: =SUM(P25)*$E30/100 -> 7.541675
C31: LIQUIDACIÓN NETA | F31: =+F22-F27 -> 1620.9569 | H31: LIQUIDACIÓN NETA | K31: =+K22-K27 -> 1620.9569 | M31: LIQUIDACIÓN NETA | P31: =+P22-P27 -> 1796.6514
C32: 8 | D32: ESSSALUD | F32: =+F33 -> 34.5975 | H32: 8 | I32: ESSSALUD | K32: =+K33 -> 34.5975 | M32: 8 | N32: ESSSALUD | P32: =+P33 -> 38.3475
D33: Provisión de aporte por vacaciones | E33: 9 | F33: =+F25*$E33/100 -> 34.5975 | I33: Provisión de aporte por vacaciones | J33: 9 | K33: =+K25*$E33/100 -> 34.5975 | N33: Provisión de aporte por vacaciones | O33: 9 | P33: =+P25*$E33/100 -> 38.3475
C34: OBLIGACIONES DEL EMPLEADOR | F34: =+F32 -> 34.5975 | H34: OBLIGACIONES DEL EMPLEADOR | K34: =+K32 -> 34.5975 | M34: OBLIGACIONES DEL EMPLEADOR | P34: =+P32 -> 38.3475
C36: COSTO DIRECTO MENSUAL | F36: =+F5+F20+F22+F34 -> 6798.2806 | H36: COSTO DIRECTO MENSUAL | K36: =+K5+K20+K22+K34 -> 6798.2806 | M36: COSTO DIRECTO MENSUAL | P36: =+P5+P20+P22+P34 -> 7535.1417
C37: COSTO DIRECTO MENSUAL $ | E37: =+F2 -> 3.5 | F37: =+F36/E37 -> 1942.3659 | H37: COSTO DIRECTO MENSUAL $ | J37: =+K2 -> 3.5 | K37: =+K36/J37 -> 1942.3659 | M37: COSTO DIRECTO MENSUAL $ | O37: =+P2 -> 3.5 | P37: =+P36/O37 -> 2152.8976
C39: OTROS COSTOS | H39: OTROS COSTOS | M39: OTROS COSTOS
C40: 9 | D40: EXAMEN MÉDICO | F40: =SUM(F41:F44)/3 -> 40 | H40: 9 | I40: EXAMEN MÉDICO | K40: =SUM(K41:K44)/3 -> 40 | M40: 9 | N40: EXAMEN MÉDICO | P40: =SUM(P41:P44) -> 120
D41: Examen Médico Pre ocupacional | F41: 120 | I41: Examen Médico Pre ocupacional | K41: 120 | N41: Examen Médico Pre ocupacional | P41: =+K41 -> 120
D42: Examen Médico Post ocupacional | F42: 0 | I42: Examen Médico Post ocupacional | K42: 0 | N42: Examen Médico Post ocupacional | P42: =+K42 -> 0
D43: Otros exámenes (levantamiento de observaciones) | F43: 0 | I43: Otros exámenes (levantamiento de observaciones) | K43: 0 | N43: Otros exámenes (levantamiento de observaciones) | P43: =+K43 -> 0
C45: 10 | D45: EPP | F45: =SUM(F46:F46) -> 389.29 | H45: 10 | I45: EPP | K45: =SUM(K46:K46) -> 114.54 | M45: 10 | N45: EPP | P45: =SUM(P46:P46) -> 411.74
D46: Epp Completo | F46: 389.29 | I46: Epp Completo (Incluye epp específico) | K46: 114.54 | N46: Epp Completo (incluye específico) | P46: 411.74
C47: 11 | D47: ALIMENTACIÓN | F47: =+F48 -> 132 | H47: 11 | I47: ALIMENTACIÓN | K47: =+K48 -> 132 | M47: 11 | N47: ALIMENTACIÓN | P47: =+P48 -> 132
D48: Alimentación (Solo almuerzo) | F48: =21*22/3.5 -> 132 | I48: Alimentación (Solo almuerzo) | K48: =21*22/3.5 -> 132 | N48: Alimentación (Solo almuerzo) | P48: =21*22/3.5 -> 132
C49: 12 | D49: TRANSPORTE | F49: =+F50 -> 0 | H49: 12 | I49: TRANSPORTE | K49: =+K50 -> 0 | M49: 12 | N49: TRANSPORTE | P49: =+P50 -> 0
D50: Transporte | I50: Transporte | N50: Transporte
C51: 13 | D51: CURSOS DE CAPACITACION | F51: =SUM(F52:F53)/3 -> 70 | H51: 13 | I51: CURSOS DE CAPACITACION | K51: =SUM(K52:K54)/3 -> 70 | M51: 13 | N51: CURSOS DE CAPACITACION | P51: =SUM(P52:P54) -> 421.86
D52: induccion | F52: 60 | I52: induccion | K52: 60 | N52: induccion | P52: 60
D53: cursos mensuales | F53: 150 | I53: cursos mensuales | K53: 150 | N53: cursos mensuales | P53: 150
N54: Homologación de soldadores | P54: 211.86
C55: 14 | D55: BONIFICACIONES | F55: =SUM(F56:F57) -> 500 | H55: 14 | I55: BONIFICACIONES | K55: =SUM(K56:K57) -> 500 | M55: 14 | N55: BONIFICACIONES | P55: =SUM(P56:P57) -> 500
D56: bonificación por especialización | F56: 500 | I56: bonificación por especialización | K56: 500 | N56: bonificación por especialización | P56: 500
C58: OTROS COSTOS | F58: =+F51+F47+F45+F40+F49+F55 -> 1131.29 | H58: OTROS COSTOS | K58: =+K51+K47+K45+K40+K49+K55 -> 856.54 | M58: OTROS COSTOS | P58: =+P51+P47+P45+P40+P49+P55 -> 1585.6
C59: OTROS COSTOS $ | E59: =+E37 -> 3.5 | F59: =+F58/E59 -> 323.22571 | H59: OTROS COSTOS $ | J59: =K2 -> 3.5 | K59: =+K58/J59 -> 244.72571 | M59: OTROS COSTOS $ | O59: =+P2 -> 3.5 | P59: =+P58/O59 -> 453.02857
C61: COSTO TOTAL | F61: =+F58+F36 -> 7929.5706 | H61: COSTO TOTAL | K61: =+K58+K36 -> 7654.8206 | M61: COSTO TOTAL | P61: =+P58+P36 -> 9120.7417
E62: =+E59 -> 3.5 | F62: =+F61/E62 -> 2265.5916 | J62: =+J59 -> 3.5 | K62: =+K61/J62 -> 2187.0916 | O62: =+O59 -> 3.5 | P62: =+P61/O62 -> 2605.9262
C63: HORAS HOMBRE X MES LABORADO EN UN REGIMEN COMÚN DE 48 HORAS | F63: 208 | H63: HORAS HOMBRE X MES LABORADO EN UN REGIMEN COMÚN DE 48 HORAS | K63: 208 | M63: HORAS HOMBRE X MES LABORADO EN UN REGIMEN COMÚN DE 48 HORAS | P63: 208
C64: COSTO POR HORA HOMBRE | F64: =+F61/F63 -> 38.122936 | H64: COSTO POR HORA HOMBRE | K64: =+K61/K63 -> 36.802022 | M64: COSTO POR HORA HOMBRE | P64: =+P61/P63 -> 43.84972
C65: COSTO POR HORA HOMBRE $ | E65: =+E59 -> 3.5 | F65: =+F64/E65 -> 10.892267 | H65: COSTO POR HORA HOMBRE $ | J65: =+J59 -> 3.5 | K65: =+K64/J65 -> 10.514863 | M65: COSTO POR HORA HOMBRE $ | O65: =+O59 -> 3.5 | P65: =+P64/O65 -> 12.528491
C67: STAFF
D69: STAFF | E69: TC | F69: 3.5
C70: ITEM | D70: DESCRIPCION | E70: %
C71: COSTOS MENSUALES REFERENCIALES
C72: 1 | D72: SUELDO BRUTO | F72: =+F73+F74 -> 8102.5 | I72: capatas | J72: 10.51
D73: Haber básico mensual | E73: - | F73: 8000 | I73: capataz ele | J73: 10.89
D74: Asignación familiar | E74: - | F74: =102.5 -> 102.5 | I74: operario | J74: 9.3
C75: 2 | D75: AFP | F75: =SUM(F76:F78) -> 1053.325 | I75: operario ele
D76: Aporte obligatorio 10% | E76: 10 | F76: =+F72*$E76/100 -> 810.25 | I76: oficial | J76: 7.54
D77: Prima de seguro 1.23% | E77: 1.23 | F77: =+F72*$E77/100 -> 99.66075 | I77: oficial ele
D78: Comisión variable 1.47% - 1.77% | E78: 1.77 | F78: =+F72*$E78/100 -> 143.41425 | I78: ayduan | J78: 6.88
C79: 3 | D79: RENTA QUINTA CATEGORÍA | F79: =+F80 -> 1098.5625
D80: Impuesto | E80: 15 | F80: =IF(F72*14>3650*7,(((F72*14)-(3650*7))/12)*$E80/100,0) -> 1098.5625
C81: SUELDO NETO O LIQUIDO MENSUAL | F81: =+F72-F75-F79 -> 5950.6125
C82: 4 | D82: ESSSALUD | F82: =+F83 -> 729.225
D83: Aporte mensual (9% del sueldo bruto) | E83: 9 | F83: =+F72*$E83/100 -> 729.225
C84: 5 | D84: SCTR LEY 26790 | F84: =SUM(F85:F86) -> 113.435
D85: SCTR Salud - Aporte mensual (0.70% del sueldo bruto) | E85: 0.7 | F85: =+F72*$E85/100 -> 56.7175
D86: SCTR Pensión - Aporte mensual (0.70% del sueldo bruto) | E86: 0.7 | F86: =+F72*$E86/100 -> 56.7175
C87: OBLIGACIONES DEL EMPLEADOR MENSUAL | F87: =+F82+F84 -> 842.66
C88: PROVISIONES MENSUALES POR CIERRE DE CONTRATO
C89: 6 | D89: LIQUIDACIÓN | F89: =SUM(F90:F93) -> 2934.9056
D90: Gratificaciones - 2 sueldos anuales | F90: =+F72/6 -> 1350.4167
D91: Bonificación extraordinaria | E91: 9 | F91: =+F90*$E91/100 -> 121.5375
D92: Vacaciones - 1 sueldo anual | F92: =+F72/12 -> 675.20833
D93: CTS - 1 sueldo anual - No afecto a tributación | F93: =+(F72+F90)/12 -> 787.74306
C94: 7 | D94: AFP | F94: =SUM(F95:F97) -> 87.777083
D95: Aporte obligatorio 10% | E95: 10 | F95: =SUM(F92)*$E95/100 -> 67.520833
D96: Prima de seguro 1.23% | E96: 1.23 | F96: =SUM(F92)*$E96/100 -> 8.3050625
D97: Comisión variable 1.47% - 1.77% | E97: 1.77 | F97: =SUM(F92)*$E97/100 -> 11.951188
C98: LIQUIDACIÓN NETA | F98: =+F89-F94 -> 2847.1285
C99: 8 | D99: ESSSALUD | F99: =+F100 -> 60.76875
D100: Provisión de aporte por vacaciones | E100: 9 | F100: =+F92*$E100/100 -> 60.76875
C101: OBLIGACIONES DEL EMPLEADOR | F101: =+F99 -> 60.76875
C103: COSTO DIRECTO MENSUAL | F103: =+F72+F87+F89+F101 -> 11940.834
C104: COSTO DIRECTO MENSUAL $ | E104: =+F69 -> 3.5 | F104: =+F103/E104 -> 3411.6669
C106: OTROS COSTOS
C107: 9 | D107: EXAMEN MÉDICO | F107: =SUM(F108:F111) -> 260
D108: Examen Médico Pre ocupacional | F108: 130
D109: Examen Médico Post ocupacional | F109: 130
D110: Otros exámenes (levantamiento de observaciones) | F110: 0
...

Sheet CARa
K1: SUPERINTENDENCIA DE INGENIERIA
K2: FORMATO | AJ2: Código: PCS-IN-FO-008
A3: PROYECTOS DE CAPITAL SOSTENIBLE | K3: CANTIDADES Y PRECIOS OFERTADOS (QPS) | AJ3: Ver 01 / 23-May-2022
B7: WBS Nº: 0535
B10: AÑO: 2024
B14: QPS Nº: CRD-QPS-30535-6-32-3702
B17: LISTADO DE CANTIDADES Y PRECIOS OFERTADOS (QPS) LÍNEA EN 22.9 kV - ALTERNATIVA 2
B21: SISTEMA INTEGRADO DE DRENAJES DE LOS DEPOSITOS TOPSOIL CANTA, NOEMI Y CAPTACIONES CERRO NEGRO
B25: DISCIPLINA: ELECTRICIDAD
B28: Preparado por:
B29: GRUPO CREDCO S.A.C.
B32: Aprobado por:
B34: Jefe de Disciplina | J34: : | K34: Jour Diaz
B35: Gerente de proyecto - CREDCO | J35: : | K35: Victor Soto
B36: Gerente de proyecto - MYSRL | J36: : | K36: Luis Cabanillas
A38: Rev. | E38: Elaborado | K38: Emitido Para | AB38: Fecha | AG38: Revisado | AL38: Aprobado
A39: A | E39: F. Delgado | K39: Revisión interna | AB39: 45575 | AG39: J. Diaz | AL39: V. Soto
A42: Comentarios:

Sheet MTO Ref
A2: BAG1
A3: PIPE
A4: PIPE SCH 10S EFW 316/316L SS A 312 (*) | B4: 6 | C4: M | D4: 20
A5: FITTINGS
A6: ELL 90 DEG | B6: 6 | C6: EACH | D6: 7
A7: ELL 90 DEG 3000# SW 304/304L SS | B7: 2 | C7: EACH | D7: 2
A8: ELL 90 DEG | B8: 2 | C8: EACH | D8: 2
A9: RED ECC. | B9: 6" X 3" | C9: EACH | D9: 2
A10: RED CONC. | B10: 3" X 2" | C10: EACH | D10: 2
A11: STUB END (SHORT) | B11: 6 | C11: EACH | D11: 13
A12: STUB END (SHORT) | B12: 3 | C12: EACH | D12: 2
A13: NIPPLE SCH 40S 304/304L SS (TOE) | B13: 1 X 3 | C13: EACH | D13: 4
A14: NIPPLE SCH 40S 304/304L SS (TOE) | B14: 1/2 X 3 | C14: EACH | D14: 4
A15: NIPPLE SCH 40S 304/304L SS (TBE) | B15: 1 1/2 x 3 | C15: EACH | D15: 2
A16: FLANGE LAP JOINT 150# STL A105 | B16: 6 | C16: EACH | D16: 13
A17: FLANGE LAP JOINT 150# STL A105 | B17: 3 | C17: EACH | D17: 2
A18: FLANGE SW 150# RF 304/304L SS 40S | B18: 2 | C18: EACH | D18: 2
A19: RED. CONC. | B19: 6 X 3 | C19: EACH | D19: 2
A20: SOCKOLET 3000# 304/304L SS | B20: 6 X 1/2 | C20: EACH | D20: 4
A21: SOCKOLET 3000# 304/304L SS | B21: 6 X 1 | C21: EACH | D21: 4
A22: SOCKOLET 3000# 304/304L SS | B22: 6x1 1/2 | C22: EACH | D22: 2
A23: GASKET 150# PTFE RING THK 1/16" | B23: 6 | C23: EACH | D23: 7
A24: GASKET 150# PTFE RING THK 1/16" | B24: 3 | C24: EACH | D24: 4
A25: GASKET 150# PTFE RING THK 1/16" | B25: 2 | C25: EACH | D25: 2
A26: VALVES
A27: CHECK 150# RF 316 SS WAFER (TAG C-7) | B27: 6 | C27: EACH | D27: 4
A28: BUTTERFLY 150# CI LUG BUNA-N HNLD OP (TAG B-1) | B28: 6 | C28: EACH | D28: 6
A29: BALL 300# SCRD 316 HNDL OP (TAG A-11) | B29: 0.5 | C29: EACH | D29: 4
A30: BALL 300# SCRD 316 HNDL OP (TAG A-11) | B30: 1 | C30: EACH | D30: 4
A31: BALL 300# SCRD 316 HNDL OP (TAG A-11) | B31: 1 1/2 | C31: EACH | D31: 2
A32: EXP JOINT 150# FF CHLOROBUTYL/FIBERGLASS | B32: 3 | C32: EACH | D32: 2
A33: BOLTING
A34: MACHINE BOLT STEEL A307 GRADE B | B34: 3/4-10 X 2 | C34: EACH | D34: 64
A35: MACHINE BOLT STEEL A307 GRADE B | B35: 3/4-10 X 2 3/4 | C35: EACH | D35: 32
A36: STUD-BOLT A-103 GR B7 3M | B36: 3/4 X 8 1/4 | C36: EACH | D36: 32
A37: STUD-BOLT A-103 GR B7 3M | B37: 5/8 X 3 3/4 | C37: EACH | D37: 32
A40: ULUF3
A41: PIPE
A42: PIPE SDR 17 HD POLYETHYLENE (*) | B42: 3 | C42: M | D42: 30
A43: PIPE SDR 17 HD POLYETHYLENE | B43: 6 | C43: M | D43: 2374
A44: PIPE SDR 17 HD POLYETHYLENE (*) | B44: 6 | C44: M | D44: 32
A45: SOLID CPT PIPE, TYPE S | B45: 12 (300) | C45: M | D45: 24
A46: FITTINGS
A47: ELL 90 DEG SDR 17 HD POLYETHYLENE MOLDED | B47: 6 | C47: EACH | D47: 19
A48: ELL 90 DEG SDR 17 HD POLYETHYLENE MOLDED | B48: 4 | C48: EACH | D48: 2
A49: ELL 45 DEG SDR 17 HD POLYETHYLENE MOLDED | B49: 3 | C49: EACH | D49: 4
A50: ELL 45 DEG SDR 17 HD POLYETHYLENE MOLDED | B50: 6 | C50: EACH | D50: 10
A51: FLANGE ADAPTOR SDR 17 HDPE MOLDED | B51: 6 | C51: EACH | D51: 12
A52: FLANGE ADAPTOR SDR 17 HDPE MOLDED | B52: 4 | C52: EACH | D52: 2
A53: FLANGE ADAPTOR SDR 17 HDPE MOLDED | B53: 3 | C53: EACH | D53: 1
A54: FLG BACKUP 150# CS STL A105 | B54: 6 | C54: EACH | D54: 12
A55: FLG BACKUP 150# CS STL A105 | B55: 4 | C55: EACH | D55: 2
A56: FLG BACKUP 150# CS STL A105 | B56: 3 | C56: EACH | D56: 1
A57: NIPPLE SCH 40S 304/304L SS (TBE) | B57: 1 X 3 | C57: EACH | D57: 10
A58: BRANCH OUTLET 304/304L SS FNPT | B58: 6.625 X 1 | C58: EACH | D58: 5
A59: GASKET 150# RF NON-ASB 1/16" THK | B59: 6 | C59: EACH | D59: 9
A60: VALVES
A61: BUTTERFLY 150# CI LUG BUNA-N HNLD OP (TAG B-1) | B61: 4 | C61: EACH | D61: 2
A62: BALL 300# SCDR 316 HNDL OP (TAG A-11) | B62: 1 | C62: EACH | D62: 5
A63: AIR VACCUM VALVE, 150# CI, BUNA-N FNPT | B63: 1 | C63: EACH | D63: 3
A64: COMBINATION AIR RELEASE & VACCUM VALVE | B64: 1 | C64: EACH | D64: 2
A65: BOLTING
A66: MACHINE BOLT STEEL A307 GRADE B | B66: 5/8-11 X 1 3/4" | C66: EACH | D66: 8
A67: STUD-BOLT STEEL A193 GR B7 3m. | B67: 3/4 X 5 | C67: EACH | D67: 72
A68: STUD-BOLT STEEL A193 GR B7 3m. | B68: 5/8 X 4 | C68: EACH | D68: 4
A69: MACHINE BOLT STEEL A307 GRADE B | B69: 5/8-11 X 2 1/4" | C69: EACH | D69: 8
A73: ULUF4
A74: PIPE
A75: PIPE SDR 11 HD POLYETHYLENE (*) | B75: 8 | C75: M | D75: 1828
A76: PIPE SDR 11 HD POLYETHYLENE (*) | B76: 6(150) | C76: M | D76: 384
A77: PIPE SDR 11 HD POLYETHYLENE (*) | B77: 6 | C77: M | D77: 416
A78: SOLID CPT PIPE, TYPE S | B78: 12 (300) | C78: M | D78: 20
A79: FITTINGS
A80: ELL 90 DEG SDR 11 HD POLYETHYLENE MOLDED | B80: 8 | C80: EACH | D80: 9
A81: ELL 90 DEG SDR 11 HD POLYETHYLENE MOLDED | B81: 6 | C81: EACH | D81: 2
A82: ELL 45 DEG SDR 11 HD POLYETHYLENE MOLDED | B82: 8 | C82: EACH | D82: 10
A83: ELL 45 DEG SDR 11 HD POLYETHYLENE MOLDED | B83: 6 | C83: EACH | D83: 2
A84: FLANGE ADAPTOR SDR 11 HDPE MOLDED | B84: 8 | C84: EACH | D84: 2
A85: FLANGE ADAPTOR SDR 11 HDPE MOLDED | B85: 6 | C85: EACH | D85: 7
A86: FLG BACKUP 150# CS STL A105 | B86: 8 | C86: EACH | D86: 2
A87: FLG BACKUP 150# CS STL A105 | B87: 6 | C87: EACH | D87: 7
A88: REDUCER CONC SDR 11 HD POLYETHYLENE MOLDED | B88: 8 X 6 | C88: EACH | D88: 4
A89: BRANCH SADDLE REDUCING TEES | B89: 8 X 6 | C89: EACH | D89: 1
A90: BRANCH OUTLET 304/304L SS FNPT | B90: 8.625 X 1 | C90: EACH | D90: 4
A91: BRANCH OUTLET 304/304L SS FNPT | B91: 6.625 X 1 | C91: EACH | D91: 1
A92: NIPPLE SCH 40S 304/304L SS (TBE) | B92: 1 X 3 | C92: EACH | D92: 10
A93: VALVES
A94: BALL 300# SCDR 316 HNDL OP (TAG A-11) | B94: 1 | C94: EACH | D94: 5
A95: GASKET 150# RF NON-ASB 1/16" THK | B95: 8 | C95: EACH | D95: 1
A96: GASKET 150# RF NON-ASB 1/16" THK | B96: 6 | C96: EACH | D96: 6
A97: AIR VACCUM VALVE 150# CI, BUNA-N FNPT | B97: 1 | C97: EACH | D97: 1
A98: BOLTING
A99: STUD-BOLT A-193 GR B7 3M | B99: 3/4x5 | C99: EACH | D99: 40
A100: STUD-BOLT A-193 GR B7 3M | B100: 3/4 X 6 | C100: EACH | D100: 24
A103: CAA1B
A104: PIPE
A105: PIPE STD WT ERW STL API-5L-B / A53-B | B105: 3 | C105: M | D105: 1
A106: FITTINGS | D106: 0
A107: FLG SO 150# RF STL A105 | B107: 3 | C107: EACH | D107: 1
A108: VALVES
...

Sheet MAPEO
A1: MAPEO CRONOGRAMA ↔ QPS
A2: Vincula cada actividad del cronograma con las partidas del QPS. El avance se pondera por HH (mano de obra).
A3: Editable: Activity ID, Código QPS y % Asignación. El resto son fórmulas.
P4: CONTROLES DE INTEGRIDAD
A5: Activity ID | B5: Actividad (Cronograma) | C5: Fila Cron. | D5: Código QPS | E5: Partida (QPS) | F5: Tamaño | G5: Clase | H5: Und. | I5: HH partida | J5: % Asign. | K5: HH asignadas | L5: % Avance QPS | M5: HH ganadas | N5: Confianza | P5: HH total QPS (mano de obra) | Q5: =SUM(QPS!$AB$15:$AB$262) -> 10210.525 | S5: Ocurrencia | T5: Lista Activity ID | U5: Lista Cod QPS
A6: A1000 | B6: {=IF($C6="","",TRIM(INDEX(CRONOGRAMA!$D:$D,$C6)))} -> KOM | C6: 8 | E6: =IF($D6="","",IFERROR(INDEX(QPS!$G:$G,MATCH($D6,QPS!$AE:$AE,0)),"NO EXISTE")) | F6: {=IF($D6="","",IFERROR(INDEX(QPS!$N:$N,SMALL(IF(QPS!$AE$15:$AE$262=$D6,ROW(QPS!$AE$15:$AE$262)),$S6)),""))} | G6: {=IF($D6="","",IFERROR(INDEX(QPS!$O:$O,SMALL(IF(QPS!$AE$15:$AE$262=$D6,ROW(QPS!$AE$15:$AE$262)),$S6)),""))} | H6: =IF($D6="","",IFERROR(INDEX(QPS!$T:$T,MATCH($D6,QPS!$AE:$AE,0)),"")) | I6: {=IF($D6="","",IFERROR(INDEX(QPS!$AB:$AB,SMALL(IF(QPS!$AE$15:$AE$262=$D6,ROW(QPS!$AE$15:$AE$262)),$S6)),0))} | J6: =IF($D6="","",1) | K6: =IF($D6="","",N($I6)*N($J6)) | L6: {=IF($D6="","",IFERROR(IF(INDEX(QPS!$AB:$AB,SMALL(IF(QPS!$AE$15:$AE$262=$D6,ROW(QPS!$AE$15:$AE$262)),$S6))=0,0,INDEX(QPS!$AH:$AH,SMALL(IF(QPS!$AE$15:$AE$262=$D6,ROW(QPS!$AE$15:$AE$262)),$S6))/INDEX(QPS!$AB:$AB,SMALL(IF(QPS!$AE$15:$AE$262=$D6,ROW(QPS!$AE$15:$AE$262)),$S6))),0))} | M6: =IF($D6="","",N($K6)*N($L6)) | N6: Sin asignar | P6: HH asignadas en MAPEO | Q6: =SUM($K$6:$K$232) -> 9972.4303 | S6: =IF($D6="","",COUNTIF($D$6:$D6,$D6)) | T6: A1000 | U6: 1.01.00
A7: A1010 | B7: {=IF($C7="","",TRIM(INDEX(CRONOGRAMA!$D:$D,$C7)))} -> GESTION DE RIESGOS | C7: 9 | E7: =IF($D7="","",IFERROR(INDEX(QPS!$G:$G,MATCH($D7,QPS!$AE:$AE,0)),"NO EXISTE")) | F7: {=IF($D7="","",IFERROR(INDEX(QPS!$N:$N,SMALL(IF(QPS!$AE$15:$AE$262=$D7,ROW(QPS!$AE$15:$AE$262)),$S7)),""))} | G7: {=IF($D7="","",IFERROR(INDEX(QPS!$O:$O,SMALL(IF(QPS!$AE$15:$AE$262=$D7,ROW(QPS!$AE$15:$AE$262)),$S7)),""))} | H7: =IF($D7="","",IFERROR(INDEX(QPS!$T:$T,MATCH($D7,QPS!$AE:$AE,0)),"")) | I7: {=IF($D7="","",IFERROR(INDEX(QPS!$AB:$AB,SMALL(IF(QPS!$AE$15:$AE$262=$D7,ROW(QPS!$AE$15:$AE$262)),$S7)),0))} | J7: =IF($D7="","",1) | K7: =IF($D7="","",N($I7)*N($J7)) | L7: {=IF($D7="","",IFERROR(IF(INDEX(QPS!$AB:$AB,SMALL(IF(QPS!$AE$15:$AE$262=$D7,ROW(QPS!$AE$15:$AE$262)),$S7))=0,0,INDEX(QPS!$AH:$AH,SMALL(IF(QPS!$AE$15:$AE$262=$D7,ROW(QPS!$AE$15:$AE$262)),$S7))/INDEX(QPS!$AB:$AB,SMALL(IF(QPS!$AE$15:$AE$262=$D7,ROW(QPS!$AE$15:$AE$262)),$S7))),0))} | M7: =IF($D7="","",N($K7)*N($L7)) | N7: Sin asignar | P7: Diferencia (debe ser 0) | Q7: =Q6-Q5 -> -238.09488 | S7: =IF($D7="","",COUNTIF($D$6:$D7,$D7)) | T7: A1010 | U7: 1.01.01
A8: A1020 | B8: {=IF($C8="","",TRIM(INDEX(CRONOGRAMA!$D:$D,$C8)))} -> PMAS | C8: 10 | E8: =IF($D8="","",IFERROR(INDEX(QPS!$G:$G,MATCH($D8,QPS!$AE:$AE,0)),"NO EXISTE")) | F8: {=IF($D8="","",IFERROR(INDEX(QPS!$N:$N,SMALL(IF(QPS!$AE$15:$AE$262=$D8,ROW(QPS!$AE$15:$AE$262)),$S8)),""))} | G8: {=IF($D8="","",IFERROR(INDEX(QPS!$O:$O,SMALL(IF(QPS!$AE$15:$AE$262=$D8,ROW(QPS!$AE$15:$AE$262)),$S8)),""))} | H8: =IF($D8="","",IFERROR(INDEX(QPS!$T:$T,MATCH($D8,QPS!$AE:$AE,0)),"")) | I8: {=IF($D8="","",IFERROR(INDEX(QPS!$AB:$AB,SMALL(IF(QPS!$AE$15:$AE$262=$D8,ROW(QPS!$AE$15:$AE$262)),$S8)),0))} | J8: =IF($D8="","",1) | K8: =IF($D8="","",N($I8)*N($J8)) | L8: {=IF($D8="","",IFERROR(IF(INDEX(QPS!$AB:$AB,SMALL(IF(QPS!$AE$15:$AE$262=$D8,ROW(QPS!$AE$15:$AE$262)),$S8))=0,0,INDEX(QPS!$AH:$AH,SMALL(IF(QPS!$AE$15:$AE$262=$D8,ROW(QPS!$AE$15:$AE$262)),$S8))/INDEX(QPS!$AB:$AB,SMALL(IF(QPS!$AE$15:$AE$262=$D8,ROW(QPS!$AE$15:$AE$262)),$S8))),0))} | M8: =IF($D8="","",N($K8)*N($L8)) | N8: Sin asignar | P8: Vínculos con partida asignada | Q8: =COUNTIF($D$6:$D$232,"?*") -> 208 | S8: =IF($D8="","",COUNTIF($D$6:$D8,$D8)) | T8: A1020 | U8: 1.01.02
A9: A1030 | B9: {=IF($C9="","",TRIM(INDEX(CRONOGRAMA!$D:$D,$C9)))} -> FOTOCHECKS | C9: 11 | E9: =IF($D9="","",IFERROR(INDEX(QPS!$G:$G,MATCH($D9,QPS!$AE:$AE,0)),"NO EXISTE")) | F9: {=IF($D9="","",IFERROR(INDEX(QPS!$N:$N,SMALL(IF(QPS!$AE$15:$AE$262=$D9,ROW(QPS!$AE$15:$AE$262)),$S9)),""))} | G9: {=IF($D9="","",IFERROR(INDEX(QPS!$O:$O,SMALL(IF(QPS!$AE$15:$AE$262=$D9,ROW(QPS!$AE$15:$AE$262)),$S9)),""))} | H9: =IF($D9="","",IFERROR(INDEX(QPS!$T:$T,MATCH($D9,QPS!$AE:$AE,0)),"")) | I9: {=IF($D9="","",IFERROR(INDEX(QPS!$AB:$AB,SMALL(IF(QPS!$AE$15:$AE$262=$D9,ROW(QPS!$AE$15:$AE$262)),$S9)),0))} | J9: =IF($D9="","",1) | K9: =IF($D9="","",N($I9)*N($J9)) | L9: {=IF($D9="","",IFERROR(IF(INDEX(QPS!$AB:$AB,SMALL(IF(QPS!$AE$15:$AE$262=$D9,ROW(QPS!$AE$15:$AE$262)),$S9))=0,0,INDEX(QPS!$AH:$AH,SMALL(IF(QPS!$AE$15:$AE$262=$D9,ROW(QPS!$AE$15:$AE$262)),$S9))/INDEX(QPS!$AB:$AB,SMALL(IF(QPS!$AE$15:$AE$262=$D9,ROW(QPS!$AE$15:$AE$262)),$S9))),0))} | M9: =IF($D9="","",N($K9)*N($L9)) | N9: Sin asignar | P9: Actividades sin partida | Q9: =COUNTIFS($A$6:$A$232,"?*",$D$6:$D$232,"") -> 7 | S9: =IF($D9="","",COUNTIF($D$6:$D9,$D9)) | T9: A1030 | U9: 1.01.03
A10: A1040 | B10: {=IF($C10="","",TRIM(INDEX(CRONOGRAMA!$D:$D,$C10)))} -> MOVILIZACION DE FACILIDADES, PERSONAL Y EQUIPOS E INDUCCION ESPECIFICA | C10: 12 | D10: 1.01.01 | E10: =IF($D10="","",IFERROR(INDEX(QPS!$G:$G,MATCH($D10,QPS!$AE:$AE,0)),"NO EXISTE")) -> Movilización y desmovilización | F10: {=IF($D10="","",IFERROR(INDEX(QPS!$N:$N,SMALL(IF(QPS!$AE$15:$AE$262=$D10,ROW(QPS!$AE$15:$AE$262)),$S10)),""))} -> - | G10: {=IF($D10="","",IFERROR(INDEX(QPS!$O:$O,SMALL(IF(QPS!$AE$15:$AE$262=$D10,ROW(QPS!$AE$15:$AE$262)),$S10)),""))} -> - | H10: =IF($D10="","",IFERROR(INDEX(QPS!$T:$T,MATCH($D10,QPS!$AE:$AE,0)),"")) -> Glb. | I10: {=IF($D10="","",IFERROR(INDEX(QPS!$AB:$AB,SMALL(IF(QPS!$AE$15:$AE$262=$D10,ROW(QPS!$AE$15:$AE$262)),$S10)),0))} -> 200 | J10: =IF($D10="","",1) -> 1 | K10: =IF($D10="","",N($I10)*N($J10)) -> 200 | L10: {=IF($D10="","",IFERROR(IF(INDEX(QPS!$AB:$AB,SMALL(IF(QPS!$AE$15:$AE$262=$D10,ROW(QPS!$AE$15:$AE$262)),$S10))=0,0,INDEX(QPS!$AH:$AH,SMALL(IF(QPS!$AE$15:$AE$262=$D10,ROW(QPS!$AE$15:$AE$262)),$S10))/INDEX(QPS!$AB:$AB,SMALL(IF(QPS!$AE$15:$AE$262=$D10,ROW(QPS!$AE$15:$AE$262)),$S10))),0))} -> 0 | M10: =IF($D10="","",N($K10)*N($L10)) -> 0 | N10: Alta | P10: Partidas sin actividad | Q10: =COUNTIFS($A$6:$A$232,"",$D$6:$D$232,"?*") -> 0 | S10: =IF($D10="","",COUNTIF($D$6:$D10,$D10)) -> 1 | T10: A1040 | U10: 2.01.00
A11: A1040 | B11: {=IF($C11="","",TRIM(INDEX(CRONOGRAMA!$D:$D,$C11)))} -> MOVILIZACION DE FACILIDADES, PERSONAL Y EQUIPOS E INDUCCION ESPECIFICA | C11: 12 | D11: 1.01.02 | E11: =IF($D11="","",IFERROR(INDEX(QPS!$G:$G,MATCH($D11,QPS!$AE:$AE,0)),"NO EXISTE")) -> Trazo y replanteo (preliminar y durante la obra) | F11: {=IF($D11="","",IFERROR(INDEX(QPS!$N:$N,SMALL(IF(QPS!$AE$15:$AE$262=$D11,ROW(QPS!$AE$15:$AE$262)),$S11)),""))} -> - | G11: {=IF($D11="","",IFERROR(INDEX(QPS!$O:$O,SMALL(IF(QPS!$AE$15:$AE$262=$D11,ROW(QPS!$AE$15:$AE$262)),$S11)),""))} -> - | H11: =IF($D11="","",IFERROR(INDEX(QPS!$T:$T,MATCH($D11,QPS!$AE:$AE,0)),"")) -> Glb. | I11: {=IF($D11="","",IFERROR(INDEX(QPS!$AB:$AB,SMALL(IF(QPS!$AE$15:$AE$262=$D11,ROW(QPS!$AE$15:$AE$262)),$S11)),0))} -> 48 | J11: =IF($D11="","",1) -> 1 | K11: =IF($D11="","",N($I11)*N($J11)) -> 48 | L11: {=IF($D11="","",IFERROR(IF(INDEX(QPS!$AB:$AB,SMALL(IF(QPS!$AE$15:$AE$262=$D11,ROW(QPS!$AE$15:$AE$262)),$S11))=0,0,INDEX(QPS!$AH:$AH,SMALL(IF(QPS!$AE$15:$AE$262=$D11,ROW(QPS!$AE$15:$AE$262)),$S11))/INDEX(QPS!$AB:$AB,SMALL(IF(QPS!$AE$15:$AE$262=$D11,ROW(QPS!$AE$15:$AE$262)),$S11))),0))} -> 0 | M11: =IF($D11="","",N($K11)*N($L11)) -> 0 | N11: Media | P11: HH sin asignar a actividad | Q11: =SUMIFS($K$6:$K$232,$A$6:$A$232,"",$D$6:$D$232,"?*") -> 0 | S11: =IF($D11="","",COUNTIF($D$6:$D11,$D11)) -> 1 | T11: A1050 | U11: 2.01.01
A12: A1040 | B12: {=IF($C12="","",TRIM(INDEX(CRONOGRAMA!$D:$D,$C12)))} -> MOVILIZACION DE FACILIDADES, PERSONAL Y EQUIPOS E INDUCCION ESPECIFICA | C12: 12 | D12: 1.01.03 | E12: =IF($D12="","",IFERROR(INDEX(QPS!$G:$G,MATCH($D12,QPS!$AE:$AE,0)),"NO EXISTE")) -> Limpieza del área de trabajo | F12: {=IF($D12="","",IFERROR(INDEX(QPS!$N:$N,SMALL(IF(QPS!$AE$15:$AE$262=$D12,ROW(QPS!$AE$15:$AE$262)),$S12)),""))} -> - | G12: {=IF($D12="","",IFERROR(INDEX(QPS!$O:$O,SMALL(IF(QPS!$AE$15:$AE$262=$D12,ROW(QPS!$AE$15:$AE$262)),$S12)),""))} -> - | H12: =IF($D12="","",IFERROR(INDEX(QPS!$T:$T,MATCH($D12,QPS!$AE:$AE,0)),"")) -> Glb. | I12: {=IF($D12="","",IFERROR(INDEX(QPS!$AB:$AB,SMALL(IF(QPS!$AE$15:$AE$262=$D12,ROW(QPS!$AE$15:$AE$262)),$S12)),0))} -> 33.6 | J12: =IF($D12="","",1) -> 1 | K12: =IF($D12="","",N($I12)*N($J12)) -> 33.6 | L12: {=IF($D12="","",IFERROR(IF(INDEX(QPS!$AB:$AB,SMALL(IF(QPS!$AE$15:$AE$262=$D12,ROW(QPS!$AE$15:$AE$262)),$S12))=0,0,INDEX(QPS!$AH:$AH,SMALL(IF(QPS!$AE$15:$AE$262=$D12,ROW(QPS!$AE$15:$AE$262)),$S12))/INDEX(QPS!$AB:$AB,SMALL(IF(QPS!$AE$15:$AE$262=$D12,ROW(QPS!$AE$15:$AE$262)),$S12))),0))} -> 0 | M12: =IF($D12="","",N($K12)*N($L12)) -> 0 | N12: Media | P12: % Avance global (por HH) | Q12: =IF(Q6=0,0,SUM($M$6:$M$232)/Q6) -> 0 | S12: =IF($D12="","",COUNTIF($D$6:$D12,$D12)) -> 1 | T12: A1060 | U12: 2.02.00
A13: A1050 | B13: {=IF($C13="","",TRIM(INDEX(CRONOGRAMA!$D:$D,$C13)))} -> DESMONTAJE DE TUBERIAS Y ACCESORIOS EXISTENTES | C13: 15 | D13: 3.03.01 | E13: =IF($D13="","",IFERROR(INDEX(QPS!$G:$G,MATCH($D13,QPS!$AE:$AE,0)),"NO EXISTE")) -> Desmontaje y traslado de tuberías y accesorios existentes | F13: {=IF($D13="","",IFERROR(INDEX(QPS!$N:$N,SMALL(IF(QPS!$AE$15:$AE$262=$D13,ROW(QPS!$AE$15:$AE$262)),$S13)),""))} -> - | G13: {=IF($D13="","",IFERROR(INDEX(QPS!$O:$O,SMALL(IF(QPS!$AE$15:$AE$262=$D13,ROW(QPS!$AE$15:$AE$262)),$S13)),""))} -> - | H13: =IF($D13="","",IFERROR(INDEX(QPS!$T:$T,MATCH($D13,QPS!$AE:$AE,0)),"")) -> Glb. | I13: {=IF($D13="","",IFERROR(INDEX(QPS!$AB:$AB,SMALL(IF(QPS!$AE$15:$AE$262=$D13,ROW(QPS!$AE$15:$AE$262)),$S13)),0))} -> 112 | J13: =IF($D13="","",1) -> 1 | K13: =IF($D13="","",N($I13)*N($J13)) -> 112 | L13: {=IF($D13="","",IFERROR(IF(INDEX(QPS!$AB:$AB,SMALL(IF(QPS!$AE$15:$AE$262=$D13,ROW(QPS!$AE$15:$AE$262)),$S13))=0,0,INDEX(QPS!$AH:$AH,SMALL(IF(QPS!$AE$15:$AE$262=$D13,ROW(QPS!$AE$15:$AE$262)),$S13))/INDEX(QPS!$AB:$AB,SMALL(IF(QPS!$AE$15:$AE$262=$D13,ROW(QPS!$AE$15:$AE$262)),$S13))),0))} -> 0 | M13: =IF($D13="","",N($K13)*N($L13)) -> 0 | N13: Alta | S13: =IF($D13="","",COUNTIF($D$6:$D13,$D13)) -> 1 | T13: A1070 | U13: 2.02.01
A14: A1060 | B14: {=IF($C14="","",TRIM(INDEX(CRONOGRAMA!$D:$D,$C14)))} -> DESMONTAJE DE BOMBAS EXISTENTES | C14: 16 | D14: 3.02.01 | E14: =IF($D14="","",IFERROR(INDEX(QPS!$G:$G,MATCH($D14,QPS!$AE:$AE,0)),"NO EXISTE")) -> Desmontaje y traslado de bombas existentes | F14: {=IF($D14="","",IFERROR(INDEX(QPS!$N:$N,SMALL(IF(QPS!$AE$15:$AE$262=$D14,ROW(QPS!$AE$15:$AE$262)),$S14)),""))} -> - | G14: {=IF($D14="","",IFERROR(INDEX(QPS!$O:$O,SMALL(IF(QPS!$AE$15:$AE$262=$D14,ROW(QPS!$AE$15:$AE$262)),$S14)),""))} -> - | H14: =IF($D14="","",IFERROR(INDEX(QPS!$T:$T,MATCH($D14,QPS!$AE:$AE,0)),"")) -> UND | I14: {=IF($D14="","",IFERROR(INDEX(QPS!$AB:$AB,SMALL(IF(QPS!$AE$15:$AE$262=$D14,ROW(QPS!$AE$15:$AE$262)),$S14)),0))} -> 198.4 | J14: =IF($D14="","",1) -> 1 | K14: =IF($D14="","",N($I14)*N($J14)) -> 198.4 | L14: {=IF($D14="","",IFERROR(IF(INDEX(QPS!$AB:$AB,SMALL(IF(QPS!$AE$15:$AE$262=$D14,ROW(QPS!$AE$15:$AE$262)),$S14))=0,0,INDEX(QPS!$AH:$AH,SMALL(IF(QPS!$AE$15:$AE$262=$D14,ROW(QPS!$AE$15:$AE$262)),$S14))/INDEX(QPS!$AB:$AB,SMALL(IF(QPS!$AE$15:$AE$262=$D14,ROW(QPS!$AE$15:$AE$262)),$S14))),0))} -> 0 | M14: =IF($D14="","",N($K14)*N($L14)) -> 0 | N14: Alta | S14: =IF($D14="","",COUNTIF($D$6:$D14,$D14)) -> 1 | T14: A1080 | U14: 2.03.00
